Workbook

Sheet MASTER_DATABASE
A1: Devmobile Stores and Common Service Center & Aadhaar Centre — MASTER DATABASE (one row = one service)
A2: Blue header = type / choose here (editable). Green header + grey cells = formula (do not type over). Add a new service: copy an existing row (Ctrl+C, paste under the last row) then edit. Documents are edited in SERVICE_DOCUMENTS.
A3: Service ID | B3: Service Center | C3: Main Category | D3: Sub Category | E3: Service Name English | F3: Service Name Hindi | G3: Short Description | H3: Detailed Description | I3: Service Availability | J3: Availability Status | K3: Authorization Required | L3: Authorization Status | M3: Required Documents | N3: Additional Documents | O3: Customer Eligibility | P3: Process / How It Works | Q3: Estimated Processing Time | R3: Government Fee | S3: Shop Service Charge | T3: Total Customer Charge | U3: Charge Status | V3: Price Display on Website | W3: Payment Mode | X3: Online / Offline / Both | Y3: Portal Required | Z3: Portal Name | AA3: Customer Must Visit Shop | AB3: Contact Required | AC3: WhatsApp Available | AD3: Call Available | AE3: Booking Required | AF3: Appointment Required | AG3: Service Status | AH3: Website Visible | AI3: Featured Service | AJ3: Popular Service | AK3: Homepage Display | AL3: Website Category | AM3: Website Subcategory | AN3: Search Keywords | AO3: Website Slug | AP3: Icon | AQ3: Display Order | AR3: FAQ | AS3: Important Note | AT3: Terms / Conditions | AU3: Last Verified Date | AV3: Verification Status | AW3: Internal Remarks | AX3: SEO Title | AY3: SEO Description | AZ3: Hindi Keywords | BA3: English Keywords | BB3: Service Image | BC3: Category Icon | BD3: Service Page | BE3: Live on Website | BF3: Benefits | BG3: Customer Action | BH3: Center Key (auto) | BI3: Featured Seq (auto) | BJ3: Popular Seq (auto) | BK3: Homepage Seq (auto) | BL3: To Verify Seq (auto)
A4: AAD-001 | B4: Aadhaar Centre | C4: Aadhaar Services | D4: Enrolment | E4: New Aadhaar Enrolment – Adult (18+ years) | F4: नया आधार नामांकन – वयस्क (18+ वर्ष) | G4: Get New Aadhaar Enrolment – Adult (18+ years) done at our Aadhaar Centre. | H4: Fresh Aadhaar enrolment for adults. The operator captures demographic details, fingerprints, iris and photograph, and gives an enrolment acknowledgement. | I4: Authorization Required | J4: =IFERROR(INDEX(AVAILABILITY_MASTER!$C$4:$C$10,MATCH(I4,AVAILABILITY_MASTER!$A$4:$A$10,0)),"To Be Confirmed") -> Please Confirm at Shop | K4: Yes | L4: To Verify | M4: =IFERROR(INDEX(SERVICE_DOCUMENTS!$S$4:$S$1000,MATCH(A4,SERVICE_DOCUMENTS!$A$4:$A$1000,0))&"","") -> ✓ Identity Proof ✓ Address Proof ✓ Date of Birth Proof ✓ Customer Presence for Biometrics | N4: =IFERROR(INDEX(SERVICE_DOCUMENTS!$T$4:$T$1000,MATCH(A4,SERVICE_DOCUMENTS!$A$4:$A$1000,0))&"","") -> • Active Mobile Number (If Applicable) | O4: Residents aged 18 years or above who do not yet have an Aadhaar. | P4: Step 1 → Adult applicant comes in person with original identity, address and date-of-birth documents. Step 2 → Operator fills the enrolment form with your details. Step 3 → Fingerprints, iris and photograph are captured. Step 4 → You review the entered details; sign the consent. Step 5 → Collect the enrolment slip (EID) and track the status; Aadhaar is delivered after UIDAI processing. | Q4: Depends on Department | R4: To Verify | S4: To Verify | T4: =IF(AND(OR(ISNUMBER(R4),R4="N/A"),OR(ISNUMBER(S4),S4="N/A"),OR(ISNUMBER(R4),ISNUMBER(S4))),N(R4)+N(S4),"To Verify") -> To Verify | U4: To Verify | V4: No | W4: Depends on Service | X4: Offline | Y4: No | AA4: Yes | AB4: Yes | AC4: To Verify | AD4: To Verify | AE4: No | AF4: To Verify | AG4: To Verify | AH4: No | AI4: No | AJ4: No | AK4: No | AL4: Aadhaar Centre | AM4: Enrolment | AN4: =BA4&", "&AZ4 -> New Aadhaar Enrolment – Adult (18+ years), Aadhaar Centre, Devmobile Stores, नया आधार नामांकन – वयस्क (18+ वर्ष), आधार सेंटर, सेवा | AO4: new-aadhaar-enrolment-adult-18-years | AP4: 🆕 | AQ4: 10 | AR4: Q1: Do I need to visit in person? A1: Yes, biometrics are captured at the centre. Q2: How long does Aadhaar take? A2: Processing is done by UIDAI; the time depends on the department. | AS4: Aadhaar services depend on UIDAI operator authorization. Please confirm with the shop before visiting. | AT4: Fees, documents and processing time are subject to change as per government / bank / portal rules. Final charges are confirmed at the shop before the service starts. | AV4: To Verify | AW4: Fresh enrolment needs valid PoI/PoA/DoB documents as per current UIDAI list | AX4: New Aadhaar Enrolment – Adult (18+ years) Service | Devmobile Stores | AY4: New Aadhaar Enrolment – Adult (18+ years) (नया आधार नामांकन – वयस्क (18+ वर्ष)) at Devmobile Stores and Common Service Center & Aadhaar Centre. Check required documents, charges and process before you visit. | AZ4: नया आधार नामांकन – वयस्क (18+ वर्ष), आधार सेंटर, सेवा | BA4: New Aadhaar Enrolment – Adult (18+ years), Aadhaar Centre, Devmobile Stores | BC4: =IFERROR(INDEX(CATEGORY_MASTER!$C$4:$C$30,MATCH(B4,CATEGORY_MASTER!$A$4:$A$30,0)),"") -> 🪪 | BD4: ="/services/"&AO4 -> /services/new-aadhaar-enrolment-adult-18-years | BE4: =IF(AND(AH4="Yes",AG4="Active",I4<>"Not Available"),"LIVE","HIDDEN") -> HIDDEN | BF4: Get your first Aadhaar • Biometric capture done at the centre • Acknowledgement slip for tracking | BG4: Check Documents | BH4: =B4&"|"&COUNTIF($B$4:B4,B4) -> Aadhaar Centre|1 | BI4: =IF(AND(AI4="Yes",BE4="LIVE"),COUNTIFS($AI$4:AI4,"Yes",$BE$4:BE4,"LIVE"),"") | BJ4: =IF(AND(AJ4="Yes",BE4="LIVE"),COUNTIFS($AJ$4:AJ4,"Yes",$BE$4:BE4,"LIVE"),"") | BK4: =IF(AND(AK4="Yes",BE4="LIVE"),COUNTIFS($AK$4:AK4,"Yes",$BE$4:BE4,"LIVE"),"") | BL4: =IF(I4="To Verify",COUNTIF($I$4:I4,"To Verify"),"")
A5: AAD-002 | B5: Aadhaar Centre | C5: Aadhaar Services | D5: Enrolment | E5: New Aadhaar Enrolment – Child (5 to 17 years) | F5: नया आधार नामांकन – बच्चा (5 से 17 वर्ष) | G5: Get New Aadhaar Enrolment – Child (5 to 17 years) done at our Aadhaar Centre. | H5: New Aadhaar enrolment for a child between 5 and 17 years with biometric capture. | I5: Authorization Required | J5: =IFERROR(INDEX(AVAILABILITY_MASTER!$C$4:$C$10,MATCH(I5,AVAILABILITY_MASTER!$A$4:$A$10,0)),"To Be Confirmed") -> Please Confirm at Shop | K5: Yes | L5: To Verify | M5: =IFERROR(INDEX(SERVICE_DOCUMENTS!$S$4:$S$1000,MATCH(A5,SERVICE_DOCUMENTS!$A$4:$A$1000,0))&"","") -> ✓ Parent / Guardian Aadhaar ✓ Birth Certificate ✓ Customer Presence for Biometrics | N5: =IFERROR(INDEX(SERVICE_DOCUMENTS!$T$4:$T$1000,MATCH(A5,SERVICE_DOCUMENTS!$A$4:$A$1000,0))&"","") -> • Address Proof (If Applicable) | O5: Children aged 5 to 17 years without an Aadhaar. | P5: Step 1 → Parent / guardian brings the child with the child's birth proof and the parent's Aadhaar. Step 2 → Operator fills the child's enrolment form. Step 3 → Child's fingerprints, iris and photograph are captured. Step 4 → Parent reviews and signs the consent. Step 5 → Collect the enrolment slip (EID) and track the status. | Q5: Depends on Department | R5: To Verify | S5: To Verify | T5: =IF(AND(OR(ISNUMBER(R5),R5="N/A"),OR(ISNUMBER(S5),S5="N/A"),OR(ISNUMBER(R5),ISNUMBER(S5))),N(R5)+N(S5),"To Verify") -> To Verify | U5: To Verify | V5: No | W5: Depends on Service | X5: Offline | Y5: No | AA5: Yes | AB5: Yes | AC5: To Verify | AD5: To Verify | AE5: No | AF5: To Verify | AG5: To Verify | AH5: No | AI5: No | AJ5: No | AK5: No | AL5: Aadhaar Centre | AM5: Enrolment | AN5: =BA5&", "&AZ5 -> New Aadhaar Enrolment – Child (5 to 17 years), Aadhaar Centre, Devmobile Stores, नया आधार नामांकन – बच्चा (5 से 17 वर्ष), आधार सेंटर, सेवा | AO5: new-aadhaar-enrolment-child-5-to-17-years | AP5: 🆕 | AQ5: 20 | AR5: Q1: Who should accompany the child? A1: A parent or guardian with their Aadhaar. | AS5: Aadhaar services depend on UIDAI operator authorization. Please confirm with the shop before visiting. | AT5: Fees, documents and processing time are subject to change as per government / bank / portal rules. Final charges are confirmed at the shop before the service starts. | AV5: To Verify | AW5: Biometrics captured; mandatory biometric update applies at age 15 | AX5: New Aadhaar Enrolment – Child (5 to 17 years) Service | Devmobile Stores | AY5: New Aadhaar Enrolment – Child (5 to 17 years) (नया आधार नामांकन – बच्चा (5 से 17 वर्ष)) at Devmobile Stores and Common Service Center & Aadhaar Centre. Check required documents, charges and process before you visit. | AZ5: नया आधार नामांकन – बच्चा (5 से 17 वर्ष), आधार सेंटर, सेवा | BA5: New Aadhaar Enrolment – Child (5 to 17 years), Aadhaar Centre, Devmobile Stores | BC5: =IFERROR(INDEX(CATEGORY_MASTER!$C$4:$C$30,MATCH(B5,CATEGORY_MASTER!$A$4:$A$30,0)),"") -> 🪪 | BD5: ="/services/"&AO5 -> /services/new-aadhaar-enrolment-child-5-to-17-years | BE5: =IF(AND(AH5="Yes",AG5="Active",I5<>"Not Available"),"LIVE","HIDDEN") -> HIDDEN | BF5: Aadhaar for school / scholarship needs • Child biometrics captured • Acknowledgement slip | BG5: Check Documents | BH5: =B5&"|"&COUNTIF($B$4:B5,B5) -> Aadhaar Centre|2 | BI5: =IF(AND(AI5="Yes",BE5="LIVE"),COUNTIFS($AI$4:AI5,"Yes",$BE$4:BE5,"LIVE"),"") | BJ5: =IF(AND(AJ5="Yes",BE5="LIVE"),COUNTIFS($AJ$4:AJ5,"Yes",$BE$4:BE5,"LIVE"),"") | BK5: =IF(AND(AK5="Yes",BE5="LIVE"),COUNTIFS($AK$4:AK5,"Yes",$BE$4:BE5,"LIVE"),"") | BL5: =IF(I5="To Verify",COUNTIF($I$4:I5,"To Verify"),"")
A6: AAD-003 | B6: Aadhaar Centre | C6: Aadhaar Services | D6: Enrolment | E6: New Aadhaar Enrolment – Child (0 to 5 years, Baal Aadhaar) | F6: नया आधार नामांकन – बच्चा (0 से 5 वर्ष, बाल आधार) | G6: Get New Aadhaar Enrolment – Child (0 to 5 years, Baal Aadhaar) done at our Aadhaar Centre. | H6: Baal Aadhaar enrolment for newborns and children below 5 years, linked to a parent's Aadhaar. | I6: Authorization Required | J6: =IFERROR(INDEX(AVAILABILITY_MASTER!$C$4:$C$10,MATCH(I6,AVAILABILITY_MASTER!$A$4:$A$10,0)),"To Be Confirmed") -> Please Confirm at Shop | K6: Yes | L6: To Verify | M6: =IFERROR(INDEX(SERVICE_DOCUMENTS!$S$4:$S$1000,MATCH(A6,SERVICE_DOCUMENTS!$A$4:$A$1000,0))&"","") -> ✓ Parent / Guardian Aadhaar ✓ Birth Certificate ✓ Customer Presence for Biometrics | N6: =IFERROR(INDEX(SERVICE_DOCUMENTS!$T$4:$T$1000,MATCH(A6,SERVICE_DOCUMENTS!$A$4:$A$1000,0))&"","") -> • Address Proof (If Applicable) | O6: Children below 5 years (Baal Aadhaar). | P6: Step 1 → Parent brings the child (under 5 years) with the child's birth proof and the parent's Aadhaar. Step 2 → Operator fills the child's enrolment form linked to the parent's Aadhaar. Step 3 → Child's photograph is captured (fingerprints / iris are not captured under 5 years). Step 4 → Parent reviews and signs the consent. Step 5 → Collect the enrolment slip (EID) and track the status. | Q6: Depends on Department | R6: To Verify | S6: To Verify | T6: =IF(AND(OR(ISNUMBER(R6),R6="N/A"),OR(ISNUMBER(S6),S6="N/A"),OR(ISNUMBER(R6),ISNUMBER(S6))),N(R6)+N(S6),"To Verify") -> To Verify | U6: To Verify | V6: No | W6: Depends on Service | X6: Offline | Y6: No | AA6: Yes | AB6: Yes | AC6: To Verify | AD6: To Verify | AE6: No | AF6: To Verify | AG6: To Verify | AH6: No | AI6: No | AJ6: No | AK6: No | AL6: Aadhaar Centre | AM6: Enrolment | AN6: =BA6&", "&AZ6 -> New Aadhaar Enrolment – Child (0 to 5 years, Baal Aadhaar), Aadhaar Centre, Devmobile Stores, नया आधार नामांकन – बच्चा (0 से 5 वर्ष, बाल आधार), आधार सेंटर, सेवा | AO6: new-aadhaar-enrolment-child-0-to-5-years-baal-aadhaar | AP6: 🆕 | AQ6: 30 | AR6: Q1: Is a biometric needed for a baby? A1: Under 5 years, biometrics are not captured; a mandatory biometric update is done later. | AS6: Aadhaar services depend on UIDAI operator authorization. Please confirm with the shop before visiting. | AT6: Fees, documents and processing time are subject to change as per government / bank / portal rules. Final charges are confirmed at the shop before the service starts. | AV6: To Verify | AW6: Biometrics are not captured below 5 years; parent's Aadhaar and child's proof required | AX6: New Aadhaar Enrolment – Child (0 to 5 years, Baal Aadhaar) Service | Devmobile Stores | AY6: New Aadhaar Enrolment – Child (0 to 5 years, Baal Aadhaar) (नया आधार नामांकन – बच्चा (0 से 5 वर्ष, बाल आधार)) at Devmobile Stores and Common Service Center & Aadhaar Centre. Check required documents, charges and process before you visit. | AZ6: नया आधार नामांकन – बच्चा (0 से 5 वर्ष, बाल आधार), आधार सेंटर, सेवा | BA6: New Aadhaar Enrolment – Child (0 to 5 years, Baal Aadhaar), Aadhaar Centre, Devmobile Stores | BC6: =IFERROR(INDEX(CATEGORY_MASTER!$C$4:$C$30,MATCH(B6,CATEGORY_MASTER!$A$4:$A$30,0)),"") -> 🪪 | BD6: ="/services/"&AO6 -> /services/new-aadhaar-enrolment-child-0-to-5-years-baal-aadhaar | BE6: =IF(AND(AH6="Yes",AG6="Active",I6<>"Not Available"),"LIVE","HIDDEN") -> HIDDEN | BF6: Early Aadhaar for infants • No biometrics needed for very young children • Acknowledgement slip | BG6: Check Documents | BH6: =B6&"|"&COUNTIF($B$4:B6,B6) -> Aadhaar Centre|3 | BI6: =IF(AND(AI6="Yes",BE6="LIVE"),COUNTIFS($AI$4:AI6,"Yes",$BE$4:BE6,"LIVE"),"") | BJ6: =IF(AND(AJ6="Yes",BE6="LIVE"),COUNTIFS($AJ$4:AJ6,"Yes",$BE$4:BE6,"LIVE"),"") | BK6: =IF(AND(AK6="Yes",BE6="LIVE"),COUNTIFS($AK$4:AK6,"Yes",$BE$4:BE6,"LIVE"),"") | BL6: =IF(I6="To Verify",COUNTIF($I$4:I6,"To Verify"),"")
A7: AAD-004 | B7: Aadhaar Centre | C7: Aadhaar Services | D7: Enrolment | E7: Aadhaar Enrolment – Head of Family / Introducer Based | F7: आधार नामांकन – परिवार मुखिया / परिचयकर्ता आधारित | G7: Get Aadhaar Enrolment – Head of Family / Introducer Based done at our Aadhaar Centre. | H7: Special-case Aadhaar enrolment. Availability at this centre is still to be confirmed. | I7: To Verify | J7: =IFERROR(INDEX(AVAILABILITY_MASTER!$C$4:$C$10,MATCH(I7,AVAILABILITY_MASTER!$A$4:$A$10,0)),"To Be Confirmed") -> To Be Confirmed | K7: Depends | L7: To Verify | M7: =IFERROR(INDEX(SERVICE_DOCUMENTS!$S$4:$S$1000,MATCH(A7,SERVICE_DOCUMENTS!$A$4:$A$1000,0))&"","") -> ✓ Customer Presence for Biometrics | N7: =IFERROR(INDEX(SERVICE_DOCUMENTS!$T$4:$T$1000,MATCH(A7,SERVICE_DOCUMENTS!$A$4:$A$1000,0))&"","") -> • Original Documents (To Verify) | O7: Special enrolment cases as permitted by UIDAI. | P7: Step 1 → Contact the shop to confirm whether this special enrolment case can be handled here. Step 2 → If yes, bring the documents the operator asks for. Step 3 → Operator follows the UIDAI procedure for this case. Step 4 → Collect the acknowledgement slip and track the status. | Q7: Depends on Department | R7: To Verify | S7: To Verify | T7: =IF(AND(OR(ISNUMBER(R7),R7="N/A"),OR(ISNUMBER(S7),S7="N/A"),OR(ISNUMBER(R7),ISNUMBER(S7))),N(R7)+N(S7),"To Verify") -> To Verify | U7: To Verify | V7: No | W7: Depends on Service | X7: Offline | Y7: No | AA7: Yes | AB7: Yes | AC7: To Verify | AD7: To Verify | AE7: No | AF7: To Verify | AG7: To Verify | AH7: No | AI7: No | AJ7: No | AK7: No | AL7: Aadhaar Centre | AM7: Enrolment | AN7: =BA7&", "&AZ7 -> Aadhaar Enrolment – Head of Family / Introducer Based, Aadhaar Centre, Devmobile Stores, आधार नामांकन – परिवार मुखिया / परिचयकर्ता आधारित, आधार सेंटर, सेवा | AO7: aadhaar-enrolment-head-of-family-introducer-based | AP7: 🆕 | AQ7: 40 | AR7: Q1: Where can I check the current charges? A1: Charges are confirmed at the shop and may change as per government / bank rules. | AS7: Aadhaar services depend on UIDAI operator authorization. Please confirm with the shop before visiting. | AT7: Fees, documents and processing time are subject to change as per government / bank / portal rules. Final charges are confirmed at the shop before the service starts. | AV7: To Verify | AW7: Only where UIDAI currently permits; confirm with your Registrar | AX7: Aadhaar Enrolment – Head of Family / Introducer Based Service | Devmobile Stores | AY7: Aadhaar Enrolment – Head of Family / Introducer Based (आधार नामांकन – परिवार मुखिया / परिचयकर्ता आधारित) at Devmobile Stores and Common Service Center & Aadhaar Centre. Check required documents, charges and process before you visit. | AZ7: आधार नामांकन – परिवार मुखिया / परिचयकर्ता आधारित, आधार सेंटर, सेवा | BA7: Aadhaar Enrolment – Head of Family / Introducer Based, Aadhaar Centre, Devmobile Stores | BC7: =IFERROR(INDEX(CATEGORY_MASTER!$C$4:$C$30,MATCH(B7,CATEGORY_MASTER!$A$4:$A$30,0)),"") -> 🪪 | BD7: ="/services/"&AO7 -> /services/aadhaar-enrolment-head-of-family-introducer-based | BE7: =IF(AND(AH7="Yes",AG7="Active",I7<>"Not Available"),"LIVE","HIDDEN") -> HIDDEN | BF7: In-person assistance at the shop • Help checking your documents • Receipt / acknowledgement where applicable | BG7: Call Us | BH7: =B7&"|"&COUNTIF($B$4:B7,B7) -> Aadhaar Centre|4 | BI7: =IF(AND(AI7="Yes",BE7="LIVE"),COUNTIFS($AI$4:AI7,"Yes",$BE$4:BE7,"LIVE"),"") | BJ7: =IF(AND(AJ7="Yes",BE7="LIVE"),COUNTIFS($AJ$4:AJ7,"Yes",$BE$4:BE7,"LIVE"),"") | BK7: =IF(AND(AK7="Yes",BE7="LIVE"),COUNTIFS($AK$4:AK7,"Yes",$BE$4:BE7,"LIVE"),"") | BL7: =IF(I7="To Verify",COUNTIF($I$4:I7,"To Verify"),"") -> 1
A8: AAD-005 | B8: Aadhaar Centre | C8: Aadhaar Services | D8: Enrolment | E8: Aadhaar Enrolment – NRI / Foreign Resident | F8: आधार नामांकन – NRI / विदेशी निवासी | G8: Get Aadhaar Enrolment – NRI / Foreign Resident done at our Aadhaar Centre. | H8: Special-case Aadhaar enrolment. Availability at this centre is still to be confirmed. | I8: To Verify | J8: =IFERROR(INDEX(AVAILABILITY_MASTER!$C$4:$C$10,MATCH(I8,AVAILABILITY_MASTER!$A$4:$A$10,0)),"To Be Confirmed") -> To Be Confirmed | K8: Depends | L8: To Verify | M8: =IFERROR(INDEX(SERVICE_DOCUMENTS!$S$4:$S$1000,MATCH(A8,SERVICE_DOCUMENTS!$A$4:$A$1000,0))&"","") -> ✓ Customer Presence for Biometrics | N8: =IFERROR(INDEX(SERVICE_DOCUMENTS!$T$4:$T$1000,MATCH(A8,SERVICE_DOCUMENTS!$A$4:$A$1000,0))&"","") -> • Original Documents (To Verify) | O8: Special enrolment cases as permitted by UIDAI. | P8: Step 1 → Contact the shop to confirm whether this special enrolment case can be handled here. Step 2 → If yes, bring the documents the operator asks for. Step 3 → Operator follows the UIDAI procedure for this case. Step 4 → Collect the acknowledgement slip and track the status. | Q8: Depends on Department | R8: To Verify | S8: To Verify | T8: =IF(AND(OR(ISNUMBER(R8),R8="N/A"),OR(ISNUMBER(S8),S8="N/A"),OR(ISNUMBER(R8),ISNUMBER(S8))),N(R8)+N(S8),"To Verify") -> To Verify | U8: To Verify | V8: No | W8: Depends on Service | X8: Offline | Y8: No | AA8: Yes | AB8: Yes | AC8: To Verify | AD8: To Verify | AE8: No | AF8: To Verify | AG8: To Verify | AH8: No | AI8: No | AJ8: No | AK8: No | AL8: Aadhaar Centre | AM8: Enrolment | AN8: =BA8&", "&AZ8 -> Aadhaar Enrolment – NRI / Foreign Resident, Aadhaar Centre, Devmobile Stores, आधार नामांकन – NRI / विदेशी निवासी, आधार सेंटर, सेवा | AO8: aadhaar-enrolment-nri-foreign-resident | AP8: 🆕 | AQ8: 50 | AR8: Q1: Where can I check the current charges? A1: Charges are confirmed at the shop and may change as per government / bank rules. | AS8: Aadhaar services depend on UIDAI operator authorization. Please confirm with the shop before visiting. | AT8: Fees, documents and processing time are subject to change as per government / bank / portal rules. Final charges are confirmed at the shop before the service starts. | AV8: To Verify | AW8: Usually handled at Aadhaar Seva Kendra; confirm before offering | AX8: Aadhaar Enrolment – NRI / Foreign Resident Service | Devmobile Stores | AY8: Aadhaar Enrolment – NRI / Foreign Resident (आधार नामांकन – NRI / विदेशी निवासी) at Devmobile Stores and Common Service Center & Aadhaar Centre. Check required documents, charges and process before you visit. | AZ8: आधार नामांकन – NRI / विदेशी निवासी, आधार सेंटर, सेवा | BA8: Aadhaar Enrolment – NRI / Foreign Resident, Aadhaar Centre, Devmobile Stores | BC8: =IFERROR(INDEX(CATEGORY_MASTER!$C$4:$C$30,MATCH(B8,CATEGORY_MASTER!$A$4:$A$30,0)),"") -> 🪪 | BD8: ="/services/"&AO8 -> /services/aadhaar-enrolment-nri-foreign-resident | BE8: =IF(AND(AH8="Yes",AG8="Active",I8<>"Not Available"),"LIVE","HIDDEN") -> HIDDEN | BF8: In-person assistance at the shop • Help checking your documents • Receipt / acknowledgement where applicable | BG8: Call Us | BH8: =B8&"|"&COUNTIF($B$4:B8,B8) -> Aadhaar Centre|5 | BI8: =IF(AND(AI8="Yes",BE8="LIVE"),COUNTIFS($AI$4:AI8,"Yes",$BE$4:BE8,"LIVE"),"") | BJ8: =IF(AND(AJ8="Yes",BE8="LIVE"),COUNTIFS($AJ$4:AJ8,"Yes",$BE$4:BE8,"LIVE"),"") | BK8: =IF(AND(AK8="Yes",BE8="LIVE"),COUNTIFS($AK$4:AK8,"Yes",$BE$4:BE8,"LIVE"),"") | BL8: =IF(I8="To Verify",COUNTIF($I$4:I8,"To Verify"),"") -> 2
A9: AAD-006 | B9: Aadhaar Centre | C9: Aadhaar Services | D9: Enrolment | E9: Aadhaar Enrolment – Biometric Exception Case | F9: आधार नामांकन – बायोमेट्रिक अपवाद मामला | G9: Get Aadhaar Enrolment – Biometric Exception Case done at our Aadhaar Centre. | H9: Special-case Aadhaar enrolment. Availability at this centre is still to be confirmed. | I9: To Verify | J9: =IFERROR(INDEX(AVAILABILITY_MASTER!$C$4:$C$10,MATCH(I9,AVAILABILITY_MASTER!$A$4:$A$10,0)),"To Be Confirmed") -> To Be Confirmed | K9: Depends | L9: To Verify | M9: =IFERROR(INDEX(SERVICE_DOCUMENTS!$S$4:$S$1000,MATCH(A9,SERVICE_DOCUMENTS!$A$4:$A$1000,0))&"","") -> ✓ Customer Presence for Biometrics | N9: =IFERROR(INDEX(SERVICE_DOCUMENTS!$T$4:$T$1000,MATCH(A9,SERVICE_DOCUMENTS!$A$4:$A$1000,0))&"","") -> • Original Documents (To Verify) | O9: Special enrolment cases as permitted by UIDAI. | P9: Step 1 → Contact the shop to confirm whether this special enrolment case can be handled here. Step 2 → If yes, bring the documents the operator asks for. Step 3 → Operator follows the UIDAI procedure for this case. Step 4 → Collect the acknowledgement slip and track the status. | Q9: Depends on Department | R9: To Verify | S9: To Verify | T9: =IF(AND(OR(ISNUMBER(R9),R9="N/A"),OR(ISNUMBER(S9),S9="N/A"),OR(ISNUMBER(R9),ISNUMBER(S9))),N(R9)+N(S9),"To Verify") -> To Verify | U9: To Verify | V9: No | W9: Depends on Service | X9: Offline | Y9: No | AA9: Yes | AB9: Yes | AC9: To Verify | AD9: To Verify | AE9: No | AF9: To Verify | AG9: To Verify | AH9: No | AI9: No | AJ9: No | AK9: No | AL9: Aadhaar Centre | AM9: Enrolment | AN9: =BA9&", "&AZ9 -> Aadhaar Enrolment – Biometric Exception Case, Aadhaar Centre, Devmobile Stores, आधार नामांकन – बायोमेट्रिक अपवाद मामला, आधार सेंटर, सेवा | AO9: aadhaar-enrolment-biometric-exception-case | AP9: 🆕 | AQ9: 60 | AR9: Q1: Where can I check the current charges? A1: Charges are confirmed at the shop and may change as per government / bank rules. | AS9: Aadhaar services depend on UIDAI operator authorization. Please confirm with the shop before visiting. | AT9: Fees, documents and processing time are subject to change as per government / bank / portal rules. Final charges are confirmed at the shop before the service starts. | AV9: To Verify | AW9: Special procedure; confirm with Registrar / UIDAI | AX9: Aadhaar Enrolment – Biometric Exception Case Service | Devmobile Stores | AY9: Aadhaar Enrolment – Biometric Exception Case (आधार नामांकन – बायोमेट्रिक अपवाद मामला) at Devmobile Stores and Common Service Center & Aadhaar Centre. Check required documents, charges and process before you visit. | AZ9: आधार नामांकन – बायोमेट्रिक अपवाद मामला, आधार सेंटर, सेवा | BA9: Aadhaar Enrolment – Biometric Exception Case, Aadhaar Centre, Devmobile Stores | BC9: =IFERROR(INDEX(CATEGORY_MASTER!$C$4:$C$30,MATCH(B9,CATEGORY_MASTER!$A$4:$A$30,0)),"") -> 🪪 | BD9: ="/services/"&AO9 -> /services/aadhaar-enrolment-biometric-exception-case | BE9: =IF(AND(AH9="Yes",AG9="Active",I9<>"Not Available"),"LIVE","HIDDEN") -> HIDDEN | BF9: In-person assistance at the shop • Help checking your documents • Receipt / acknowledgement where applicable | BG9: Call Us | BH9: =B9&"|"&COUNTIF($B$4:B9,B9) -> Aadhaar Centre|6 | BI9: =IF(AND(AI9="Yes",BE9="LIVE"),COUNTIFS($AI$4:AI9,"Yes",$BE$4:BE9,"LIVE"),"") | BJ9: =IF(AND(AJ9="Yes",BE9="LIVE"),COUNTIFS($AJ$4:AJ9,"Yes",$BE$4:BE9,"LIVE"),"") | BK9: =IF(AND(AK9="Yes",BE9="LIVE"),COUNTIFS($AK$4:AK9,"Yes",$BE$4:BE9,"LIVE"),"") | BL9: =IF(I9="To Verify",COUNTIF($I$4:I9,"To Verify"),"") -> 3
A10: AAD-007 | B10: Aadhaar Centre | C10: Aadhaar Services | D10: Demographic Update | E10: Aadhaar Name Update | F10: आधार नाम अपडेट | G10: Get Aadhaar Name Update done at our Aadhaar Centre. | H10: Update or correct the name recorded in your Aadhaar through the Aadhaar Centre. | I10: Available | J10: =IFERROR(INDEX(AVAILABILITY_MASTER!$C$4:$C$10,MATCH(I10,AVAILABILITY_MASTER!$A$4:$A$10,0)),"To Be Confirmed") -> Available | K10: Yes | L10: To Verify | M10: =IFERROR(INDEX(SERVICE_DOCUMENTS!$S$4:$S$1000,MATCH(A10,SERVICE_DOCUMENTS!$A$4:$A$1000,0))&"","") -> ✓ Aadhaar Card ✓ Proof of Name | N10: =IFERROR(INDEX(SERVICE_DOCUMENTS!$T$4:$T$1000,MATCH(A10,SERVICE_DOCUMENTS!$A$4:$A$1000,0))&"","") | O10: Aadhaar holders whose details need correction, subject to UIDAI update limits. | P10: Step 1 → Bring your Aadhaar card and proof of name (originals). Step 2 → Operator checks your current Aadhaar details and the document for the name change. Step 3 → Aadhaar holder gives fingerprint / biometric authentication at the centre. Step 4 → New name details are entered and shown to you for checking before submission. Step 5 → Pay the charge and collect the acknowledgement slip (URN) to track the update. | Q10: Depends on Department | R10: To Verify | S10: To Verify | T10: =IF(AND(OR(ISNUMBER(R10),R10="N/A"),OR(ISNUMBER(S10),S10="N/A"),OR(ISNUMBER(R10),ISNUMBER(S10))),N(R10)+N(S10),"To Verify") -> To Verify | U10: To Verify | V10: No | W10: Depends on Service | X10: Offline | Y10: No | AA10: Yes | AB10: Yes | AC10: To Verify | AD10: To Verify | AE10: No | AF10: To Verify | AG10: Active | AH10: Yes | AI10: No | AJ10: No | AK10: No | AL10: Aadhaar Centre | AM10: Demographic Update | AN10: =BA10&", "&AZ10 -> Aadhaar Name Update, Aadhaar Centre, Devmobile Stores, आधार नाम अपडेट, आधार सेंटर, सेवा | AO10: aadhaar-name-update | AP10: ✏️ | AQ10: 70 | AR10: Q1: Do I need to come in person? A1: Yes, the Aadhaar holder normally gives biometric authentication at the centre. Q2: Is there a limit on changes? A2: UIDAI limits some updates. Ask the operator for the current rule. | AS10: Aadhaar services depend on UIDAI operator authorization. Please confirm with the shop before visiting. | AT10: Fees, documents and processing time are subject to change as per government / bank / portal rules. Final charges are confirmed at the shop before the service starts. | AV10: To Verify | AW10: UIDAI limits how many times name can be changed; verify current rule | Set to Available as per owner's example; authorization still To Verify. | AX10: Aadhaar Name Update Service | Devmobile Stores | AY10: Aadhaar Name Update (आधार नाम अपडेट) at Devmobile Stores and Common Service Center & Aadhaar Centre. Check required documents, charges and process before you visit. | AZ10: आधार नाम अपडेट, आधार सेंटर, सेवा | BA10: Aadhaar Name Update, Aadhaar Centre, Devmobile Stores | BC10: =IFERROR(INDEX(CATEGORY_MASTER!$C$4:$C$30,MATCH(B10,CATEGORY_MASTER!$A$4:$A$30,0)),"") -> 🪪 | BD10: ="/services/"&AO10 -> /services/aadhaar-name-update | BE10: =IF(AND(AH10="Yes",AG10="Active",I10<>"Not Available"),"LIVE","HIDDEN") -> LIVE | BF10: Correct Aadhaar details • Biometric-verified update • Acknowledgement slip | BG10: Check Documents | BH10: =B10&"|"&COUNTIF($B$4:B10,B10) -> Aadhaar Centre|7 | BI10: =IF(AND(AI10="Yes",BE10="LIVE"),COUNTIFS($AI$4:AI10,"Yes",$BE$4:BE10,"LIVE"),"") | BJ10: =IF(AND(AJ10="Yes",BE10="LIVE"),COUNTIFS($AJ$4:AJ10,"Yes",$BE$4:BE10,"LIVE"),"") | BK10: =IF(AND(AK10="Yes",BE10="LIVE"),COUNTIFS($AK$4:AK10,"Yes",$BE$4:BE10,"LIVE"),"") | BL10: =IF(I10="To Verify",COUNTIF($I$4:I10,"To Verify"),"")
A11: AAD-008 | B11: Aadhaar Centre | C11: Aadhaar Services | D11: Demographic Update | E11: Aadhaar Date of Birth Update | F11: आधार जन्म तिथि अपडेट | G11: Get Aadhaar Date of Birth Update done at our Aadhaar Centre. | H11: Update or correct the date of birth recorded in your Aadhaar through the Aadhaar Centre. | I11: Available | J11: =IFERROR(INDEX(AVAILABILITY_MASTER!$C$4:$C$10,MATCH(I11,AVAILABILITY_MASTER!$A$4:$A$10,0)),"To Be Confirmed") -> Available | K11: Yes | L11: To Verify | M11: =IFERROR(INDEX(SERVICE_DOCUMENTS!$S$4:$S$1000,MATCH(A11,SERVICE_DOCUMENTS!$A$4:$A$1000,0))&"","") -> ✓ Aadhaar Card ✓ Date of Birth Proof | N11: =IFERROR(INDEX(SERVICE_DOCUMENTS!$T$4:$T$1000,MATCH(A11,SERVICE_DOCUMENTS!$A$4:$A$1000,0))&"","") | O11: Aadhaar holders whose details need correction, subject to UIDAI update limits. | P11: Step 1 → Bring your Aadhaar card and date-of-birth proof (originals). Step 2 → Operator checks your current Aadhaar details and the document for the date of birth change. Step 3 → Aadhaar holder gives fingerprint / biometric authentication at the centre. Step 4 → New date of birth details are entered and shown to you for checking before submission. Step 5 → Pay the charge and collect the acknowledgement slip (URN) to track the update. | Q11: Depends on Department | R11: To Verify | S11: To Verify | T11: =IF(AND(OR(ISNUMBER(R11),R11="N/A"),OR(ISNUMBER(S11),S11="N/A"),OR(ISNUMBER(R11),ISNUMBER(S11))),N(R11)+N(S11),"To Verify") -> To Verify | U11: To Verify | V11: No | W11: Depends on Service | X11: Offline | Y11: No | AA11: Yes | AB11: Yes | AC11: To Verify | AD11: To Verify | AE11: No | AF11: To Verify | AG11: Active | AH11: Yes | AI11: No | AJ11: No | AK11: No | AL11: Aadhaar Centre | AM11: Demographic Update | AN11: =BA11&", "&AZ11 -> Aadhaar Date of Birth Update, Aadhaar Centre, Devmobile Stores, आधार जन्म तिथि अपडेट, आधार सेंटर, सेवा | AO11: aadhaar-date-of-birth-update | AP11: ✏️ | AQ11: 80 | AR11: Q1: Do I need to come in person? A1: Yes, the Aadhaar holder normally gives biometric authentication at the centre. Q2: Is there a limit on changes? A2: UIDAI limits some updates. Ask the operator for the current rule. | AS11: Aadhaar services depend on UIDAI operator authorization. Please confirm with the shop before visiting. | AT11: Fees, documents and processing time are subject to change as per government / bank / portal rules. Final charges are confirmed at the shop before the service starts. | AV11: To Verify | AW11: UIDAI limits DoB changes; supporting DoB proof needed; verify current rule | Set to Available as per owner's example; authorization still To Verify. | AX11: Aadhaar Date of Birth Update Service | Devmobile Stores | AY11: Aadhaar Date of Birth Update (आधार जन्म तिथि अपडेट) at Devmobile Stores and Common Service Center & Aadhaar Centre. Check required documents, charges and process before you visit. | AZ11: आधार जन्म तिथि अपडेट, आधार सेंटर, सेवा | BA11: Aadhaar Date of Birth Update, Aadhaar Centre, Devmobile Stores | BC11: =IFERROR(INDEX(CATEGORY_MASTER!$C$4:$C$30,MATCH(B11,CATEGORY_MASTER!$A$4:$A$30,0)),"") -> 🪪 | BD11: ="/services/"&AO11 -> /services/aadhaar-date-of-birth-update | BE11: =IF(AND(AH11="Yes",AG11="Active",I11<>"Not Available"),"LIVE","HIDDEN") -> LIVE | BF11: Correct Aadhaar details • Biometric-verified update • Acknowledgement slip | BG11: Check Documents | BH11: =B11&"|"&COUNTIF($B$4:B11,B11) -> Aadhaar Centre|8 | BI11: =IF(AND(AI11="Yes",BE11="LIVE"),COUNTIFS($AI$4:AI11,"Yes",$BE$4:BE11,"LIVE"),"") | BJ11: =IF(AND(AJ11="Yes",BE11="LIVE"),COUNTIFS($AJ$4:AJ11,"Yes",$BE$4:BE11,"LIVE"),"") | BK11: =IF(AND(AK11="Yes",BE11="LIVE"),COUNTIFS($AK$4:AK11,"Yes",$BE$4:BE11,"LIVE"),"") | BL11: =IF(I11="To Verify",COUNTIF($I$4:I11,"To Verify"),"")
A12: AAD-009 | B12: Aadhaar Centre | C12: Aadhaar Services | D12: Demographic Update | E12: Aadhaar Gender Update | F12: आधार लिंग अपडेट | G12: Get Aadhaar Gender Update done at our Aadhaar Centre. | H12: Update or correct the gender recorded in your Aadhaar through the Aadhaar Centre. | I12: Available | J12: =IFERROR(INDEX(AVAILABILITY_MASTER!$C$4:$C$10,MATCH(I12,AVAILABILITY_MASTER!$A$4:$A$10,0)),"To Be Confirmed") -> Available | K12: Yes | L12: To Verify | M12: =IFERROR(INDEX(SERVICE_DOCUMENTS!$S$4:$S$1000,MATCH(A12,SERVICE_DOCUMENTS!$A$4:$A$1000,0))&"","") -> ✓ Aadhaar Card | N12: =IFERROR(INDEX(SERVICE_DOCUMENTS!$T$4:$T$1000,MATCH(A12,SERVICE_DOCUMENTS!$A$4:$A$1000,0))&"","") -> • Identity Proof (To Verify) | O12: Aadhaar holders whose details need correction, subject to UIDAI update limits. | P12: Step 1 → Bring your Aadhaar card and identity proof (originals). Step 2 → Operator checks your current Aadhaar details and the document for the gender change. Step 3 → Aadhaar holder gives fingerprint / biometric authentication at the centre. Step 4 → New gender details are entered and shown to you for checking before submission. Step 5 → Pay the charge and collect the acknowledgement slip (URN) to track the update. | Q12: Depends on Department | R12: To Verify | S12: To Verify | T12: =IF(AND(OR(ISNUMBER(R12),R12="N/A"),OR(ISNUMBER(S12),S12="N/A"),OR(ISNUMBER(R12),ISNUMBER(S12))),N(R12)+N(S12),"To Verify") -> To Verify | U12: To Verify | V12: No | W12: Depends on Service | X12: Offline | Y12: No | AA12: Yes | AB12: Yes | AC12: To Verify | AD12: To Verify | AE12: No | AF12: To Verify | AG12: Active | AH12: Yes | AI12: No | AJ12: No | AK12: No | AL12: Aadhaar Centre | AM12: Demographic Update | AN12: =BA12&", "&AZ12 -> Aadhaar Gender Update, Aadhaar Centre, Devmobile Stores, आधार लिंग अपडेट, आधार सेंटर, सेवा | AO12: aadhaar-gender-update | AP12: ✏️ | AQ12: 90 | AR12: Q1: Do I need to come in person? A1: Yes, the Aadhaar holder normally gives biometric authentication at the centre. Q2: Is there a limit on changes? A2: UIDAI limits some updates. Ask the operator for the current rule. | AS12: Aadhaar services depend on UIDAI operator authorization. Please confirm with the shop before visiting. | AT12: Fees, documents and processing time are subject to change as per government / bank / portal rules. Final charges are confirmed at the shop before the service starts. | AV12: To Verify | AW12: UIDAI limits gender changes; verify current rule | Set to Available as per owner's example; authorization still To Verify. | AX12: Aadhaar Gender Update Service | Devmobile Stores | AY12: Aadhaar Gender Update (आधार लिंग अपडेट) at Devmobile Stores and Common Service Center & Aadhaar Centre. Check required documents, charges and process before you visit. | AZ12: आधार लिंग अपडेट, आधार सेंटर, सेवा | BA12: Aadhaar Gender Update, Aadhaar Centre, Devmobile Stores | BC12: =IFERROR(INDEX(CATEGORY_MASTER!$C$4:$C$30,MATCH(B12,CATEGORY_MASTER!$A$4:$A$30,0)),"") -> 🪪 | BD12: ="/services/"&AO12 -> /services/aadhaar-gender-update | BE12: =IF(AND(AH12="Yes",AG12="Active",I12<>"Not Available"),"LIVE","HIDDEN") -> LIVE | BF12: Correct Aadhaar details • Biometric-verified update • Acknowledgement slip | BG12: Check Documents | BH12: =B12&"|"&COUNTIF($B$4:B12,B12) -> Aadhaar Centre|9 | BI12: =IF(AND(AI12="Yes",BE12="LIVE"),COUNTIFS($AI$4:AI12,"Yes",$BE$4:BE12,"LIVE"),"") | BJ12: =IF(AND(AJ12="Yes",BE12="LIVE"),COUNTIFS($AJ$4:AJ12,"Yes",$BE$4:BE12,"LIVE"),"") | BK12: =IF(AND(AK12="Yes",BE12="LIVE"),COUNTIFS($AK$4:AK12,"Yes",$BE$4:BE12,"LIVE"),"") | BL12: =IF(I12="To Verify",COUNTIF($I$4:I12,"To Verify"),"")
A13: AAD-010 | B13: Aadhaar Centre | C13: Aadhaar Services | D13: Demographic Update | E13: Aadhaar Address Update (with Document) | F13: आधार पता अपडेट (दस्तावेज़ के साथ) | G13: Get Aadhaar Address Update (with Document) done at our Aadhaar Centre. | H13: Update or correct the address recorded in your Aadhaar through the Aadhaar Centre. | I13: Available | J13: =IFERROR(INDEX(AVAILABILITY_MASTER!$C$4:$C$10,MATCH(I13,AVAILABILITY_MASTER!$A$4:$A$10,0)),"To Be Confirmed") -> Available | K13: Yes | L13: To Verify | M13: =IFERROR(INDEX(SERVICE_DOCUMENTS!$S$4:$S$1000,MATCH(A13,SERVICE_DOCUMENTS!$A$4:$A$1000,0))&"","") -> ✓ Aadhaar Card ✓ Address Proof | N13: =IFERROR(INDEX(SERVICE_DOCUMENTS!$T$4:$T$1000,MATCH(A13,SERVICE_DOCUMENTS!$A$4:$A$1000,0))&"","") | O13: Aadhaar holders whose details need correction, subject to UIDAI update limits. | P13: Step 1 → Bring your Aadhaar card and address proof (originals). Step 2 → Operator checks your current Aadhaar details and the document for the address change. Step 3 → Aadhaar holder gives fingerprint / biometric authentication at the centre. Step 4 → New address details are entered and shown to you for checking before submission. Step 5 → Pay the charge and collect the acknowledgement slip (URN) to track the update. | Q13: Depends on Department | R13: To Verify | S13: To Verify | T13: =IF(AND(OR(ISNUMBER(R13),R13="N/A"),OR(ISNUMBER(S13),S13="N/A"),OR(ISNUMBER(R13),ISNUMBER(S13))),N(R13)+N(S13),"To Verify") -> To Verify | U13: To Verify | V13: No | W13: Depends on Service | X13: Offline | Y13: No | AA13: Yes | AB13: Yes | AC13: To Verify | AD13: To Verify | AE13: No | AF13: To Verify | AG13: Active | AH13: Yes | AI13: No | AJ13: No | AK13: No | AL13: Aadhaar Centre | AM13: Demographic Update | AN13: =BA13&", "&AZ13 -> Aadhaar Address Update (with Document), Aadhaar Centre, Devmobile Stores, आधार पता अपडेट (दस्तावेज़ के साथ), आधार सेंटर, सेवा | AO13: aadhaar-address-update-with-document | AP13: ✏️ | AQ13: 100 | AR13: Q1: Do I need to come in person? A1: Yes, the Aadhaar holder normally gives biometric authentication at the centre. Q2: Is there a limit on changes? A2: UIDAI limits some updates. Ask the operator for the current rule. | AS13: Aadhaar services depend on UIDAI operator authorization. Please confirm with the shop before visiting. | AT13: Fees, documents and processing time are subject to change as per government / bank / portal rules. Final charges are confirmed at the shop before the service starts. | AV13: To Verify | AW13: Valid address proof as per current UIDAI list | Set to Available as per owner's example; authorization still To Verify. | AX13: Aadhaar Address Update (with Document) Service | Devmobile Stores | AY13: Aadhaar Address Update (with Document) (आधार पता अपडेट (दस्तावेज़ के साथ)) at Devmobile Stores and Common Service Center & Aadhaar Centre. Check required documents, charges and process before you visit. | AZ13: आधार पता अपडेट (दस्तावेज़ के साथ), आधार सेंटर, सेवा | BA13: Aadhaar Address Update (with Document), Aadhaar Centre, Devmobile Stores | BC13: =IFERROR(INDEX(CATEGORY_MASTER!$C$4:$C$30,MATCH(B13,CATEGORY_MASTER!$A$4:$A$30,0)),"") -> 🪪 | BD13: ="/services/"&AO13 -> /services/aadhaar-address-update-with-document | BE13: =IF(AND(AH13="Yes",AG13="Active",I13<>"Not Available"),"LIVE","HIDDEN") -> LIVE | BF13: Correct Aadhaar details • Biometric-verified update • Acknowledgement slip | BG13: Check Documents | BH13: =B13&"|"&COUNTIF($B$4:B13,B13) -> Aadhaar Centre|10 | BI13: =IF(AND(AI13="Yes",BE13="LIVE"),COUNTIFS($AI$4:AI13,"Yes",$BE$4:BE13,"LIVE"),"") | BJ13: =IF(AND(AJ13="Yes",BE13="LIVE"),COUNTIFS($AJ$4:AJ13,"Yes",$BE$4:BE13,"LIVE"),"") | BK13: =IF(AND(AK13="Yes",BE13="LIVE"),COUNTIFS($AK$4:AK13,"Yes",$BE$4:BE13,"LIVE"),"") | BL13: =IF(I13="To Verify",COUNTIF($I$4:I13,"To Verify"),"")
A14: AAD-011 | B14: Aadhaar Centre | C14: Aadhaar Services | D14: Demographic Update | E14: Aadhaar Address Update – Online (SSUP) Assistance | F14: आधार पता अपडेट – ऑनलाइन (SSUP) सहायता | G14: Get Aadhaar Address Update – Online (SSUP) Assistance done at our Aadhaar Centre. | H14: Assistance to update Aadhaar address online through the UIDAI portal. | I14: Portal Dependent | J14: =IFERROR(INDEX(AVAILABILITY_MASTER!$C$4:$C$10,MATCH(I14,AVAILABILITY_MASTER!$A$4:$A$10,0)),"To Be Confirmed") -> Depends on Portal – Confirm at Shop | K14: Depends | L14: Portal Dependent | M14: =IFERROR(INDEX(SERVICE_DOCUMENTS!$S$4:$S$1000,MATCH(A14,SERVICE_DOCUMENTS!$A$4:$A$1000,0))&"","") -> ✓ Aadhaar Card ✓ Aadhaar-Linked Mobile Number ✓ Address Proof | N14: =IFERROR(INDEX(SERVICE_DOCUMENTS!$T$4:$T$1000,MATCH(A14,SERVICE_DOCUMENTS!$A$4:$A$1000,0))&"","") | O14: Aadhaar holders with a linked mobile number. | P14: Step 1 → Bring your Aadhaar number, the phone linked to Aadhaar and your address proof. Step 2 → Operator opens the UIDAI Self Service Update Portal and logs in with OTP. Step 3 → New address is entered and the address-proof file is uploaded. Step 4 → Payment is made online and an update request number (URN) is generated. Step 5 → Track the update with the URN. | Q14: Depends on Department | R14: To Verify | S14: To Verify | T14: =IF(AND(OR(ISNUMBER(R14),R14="N/A"),OR(ISNUMBER(S14),S14="N/A"),OR(ISNUMBER(R14),ISNUMBER(S14))),N(R14)+N(S14),"To Verify") -> To Verify | U14: To Verify | V14: No | W14: Depends on Service | X14: Online | Y14: Yes | Z14: UIDAI Self Service Update Portal (SSUP) | AA14: Depends | AB14: No | AC14: To Verify | AD14: To Verify | AE14: No | AF14: No | AG14: To Verify | AH14: No | AI14: No | AJ14: No | AK14: No | AL14: Aadhaar Centre | AM14: Demographic Update | AN14: =BA14&", "&AZ14 -> Aadhaar Address Update – Online (SSUP) Assistance, Aadhaar Centre, Devmobile Stores, आधार पता अपडेट – ऑनलाइन (SSUP) सहायता, आधार सेंटर, सेवा | AO14: aadhaar-address-update-online-ssup-assistance | AP14: ✏️ | AQ14: 110 | AR14: Q1: Where can I check the current charges? A1: Charges are confirmed at the shop and may change as per government / bank rules. | AS14: Needs a mobile number already linked to Aadhaar for OTP. | AT14: Fees, documents and processing time are subject to change as per government / bank / portal rules. Final charges are confirmed at the shop before the service starts. | AV14: To Verify | AW14: Needs mobile number linked to Aadhaar for OTP | AX14: Aadhaar Address Update – Online (SSUP) Assistance Service | Devmobile Stores | AY14: Aadhaar Address Update – Online (SSUP) Assistance (आधार पता अपडेट – ऑनलाइन (SSUP) सहायता) at Devmobile Stores and Common Service Center & Aadhaar Centre. Check required documents, charges and process before you visit. | AZ14: आधार पता अपडेट – ऑनलाइन (SSUP) सहायता, आधार सेंटर, सेवा | BA14: Aadhaar Address Update – Online (SSUP) Assistance, Aadhaar Centre, Devmobile Stores | BC14: =IFERROR(INDEX(CATEGORY_MASTER!$C$4:$C$30,MATCH(B14,CATEGORY_MASTER!$A$4:$A$30,0)),"") -> 🪪 | BD14: ="/services/"&AO14 -> /services/aadhaar-address-update-online-ssup-assistance | BE14: =IF(AND(AH14="Yes",AG14="Active",I14<>"Not Available"),"LIVE","HIDDEN") -> HIDDEN | BF14: In-person assistance at the shop • Help checking your documents • Receipt / acknowledgement where applicable | BG14: Book Service | BH14: =B14&"|"&COUNTIF($B$4:B14,B14) -> Aadhaar Centre|11 | BI14: =IF(AND(AI14="Yes",BE14="LIVE"),COUNTIFS($AI$4:AI14,"Yes",$BE$4:BE14,"LIVE"),"") | BJ14: =IF(AND(AJ14="Yes",BE14="LIVE"),COUNTIFS($AJ$4:AJ14,"Yes",$BE$4:BE14,"LIVE"),"") | BK14: =IF(AND(AK14="Yes",BE14="LIVE"),COUNTIFS($AK$4:AK14,"Yes",$BE$4:BE14,"LIVE"),"") | BL14: =IF(I14="To Verify",COUNTIF($I$4:I14,"To Verify"),"")
A15: AAD-012 | B15: Aadhaar Centre | C15: Aadhaar Services | D15: Demographic Update | E15: Aadhaar Mobile Number Update | F15: आधार मोबाइल नंबर अपडेट | G15: Get Aadhaar Mobile Number Update done at our Aadhaar Centre. | H15: Update or correct the mobile number recorded in your Aadhaar through the Aadhaar Centre. | I15: Available | J15: =IFERROR(INDEX(AVAILABILITY_MASTER!$C$4:$C$10,MATCH(I15,AVAILABILITY_MASTER!$A$4:$A$10,0)),"To Be Confirmed") -> Available | K15: Yes | L15: To Verify | M15: =IFERROR(INDEX(SERVICE_DOCUMENTS!$S$4:$S$1000,MATCH(A15,SERVICE_DOCUMENTS!$A$4:$A$1000,0))&"","") -> ✓ Aadhaar Card ✓ Active Mobile Number | N15: =IFERROR(INDEX(SERVICE_DOCUMENTS!$T$4:$T$1000,MATCH(A15,SERVICE_DOCUMENTS!$A$4:$A$1000,0))&"","") | O15: Aadhaar holders whose details need correction, subject to UIDAI update limits. | P15: Step 1 → Bring your Aadhaar card and the new mobile number (originals). Step 2 → Operator checks your current Aadhaar details and the document for the mobile number change. Step 3 → Aadhaar holder gives fingerprint / biometric authentication at the centre. Step 4 → New mobile number details are entered and shown to you for checking before submission. Step 5 → Pay the charge and collect the acknowledgement slip (URN) to track the update. | Q15: Depends on Department | R15: To Verify | S15: To Verify | T15: =IF(AND(OR(ISNUMBER(R15),R15="N/A"),OR(ISNUMBER(S15),S15="N/A"),OR(ISNUMBER(R15),ISNUMBER(S15))),N(R15)+N(S15),"To Verify") -> To Verify | U15: To Verify | V15: No | W15: Depends on Service | X15: Offline | Y15: No | AA15: Yes | AB15: Yes | AC15: To Verify | AD15: To Verify | AE15: No | AF15: To Verify | AG15: Active | AH15: Yes | AI15: No | AJ15: No | AK15: No | AL15: Aadhaar Centre | AM15: Demographic Update | AN15: =BA15&", "&AZ15 -> Aadhaar Mobile Number Update, Aadhaar Centre, Devmobile Stores, आधार मोबाइल नंबर अपडेट, आधार सेंटर, सेवा | AO15: aadhaar-mobile-number-update | AP15: ✏️ | AQ15: 120 | AR15: Q1: Do I need to come in person? A1: Yes, the Aadhaar holder normally gives biometric authentication at the centre. Q2: Is there a limit on changes? A2: UIDAI limits some updates. Ask the operator for the current rule. | AS15: Aadhaar services depend on UIDAI operator authorization. Please confirm with the shop before visiting. | AT15: Fees, documents and processing time are subject to change as per government / bank / portal rules. Final charges are confirmed at the shop before the service starts. | AV15: To Verify | AW15: Biometric authentication of resident required at centre | Set to Available as per owner's example; authorization still To Verify. | AX15: Aadhaar Mobile Number Update Service | Devmobile Stores | AY15: Aadhaar Mobile Number Update (आधार मोबाइल नंबर अपडेट) at Devmobile Stores and Common Service Center & Aadhaar Centre. Check required documents, charges and process before you visit. | AZ15: आधार मोबाइल नंबर अपडेट, आधार सेंटर, सेवा | BA15: Aadhaar Mobile Number Update, Aadhaar Centre, Devmobile Stores | BC15: =IFERROR(INDEX(CATEGORY_MASTER!$C$4:$C$30,MATCH(B15,CATEGORY_MASTER!$A$4:$A$30,0)),"") -> 🪪 | BD15: ="/services/"&AO15 -> /services/aadhaar-mobile-number-update | BE15: =IF(AND(AH15="Yes",AG15="Active",I15<>"Not Available"),"LIVE","HIDDEN") -> LIVE | BF15: Correct Aadhaar details • Biometric-verified update • Acknowledgement slip | BG15: Check Documents | BH15: =B15&"|"&COUNTIF($B$4:B15,B15) -> Aadhaar Centre|12 | BI15: =IF(AND(AI15="Yes",BE15="LIVE"),COUNTIFS($AI$4:AI15,"Yes",$BE$4:BE15,"LIVE"),"") | BJ15: =IF(AND(AJ15="Yes",BE15="LIVE"),COUNTIFS($AJ$4:AJ15,"Yes",$BE$4:BE15,"LIVE"),"") | BK15: =IF(AND(AK15="Yes",BE15="LIVE"),COUNTIFS($AK$4:AK15,"Yes",$BE$4:BE15,"LIVE"),"") | BL15: =IF(I15="To Verify",COUNTIF($I$4:I15,"To Verify"),"")
A16: AAD-013 | B16: Aadhaar Centre | C16: Aadhaar Services | D16: Demographic Update | E16: Aadhaar Email ID Update | F16: आधार ईमेल आईडी अपडेट | G16: Get Aadhaar Email ID Update done at our Aadhaar Centre. | H16: Update or correct the email id recorded in your Aadhaar through the Aadhaar Centre. | I16: Available | J16: =IFERROR(INDEX(AVAILABILITY_MASTER!$C$4:$C$10,MATCH(I16,AVAILABILITY_MASTER!$A$4:$A$10,0)),"To Be Confirmed") -> Available | K16: Yes | L16: To Verify | M16: =IFERROR(INDEX(SERVICE_DOCUMENTS!$S$4:$S$1000,MATCH(A16,SERVICE_DOCUMENTS!$A$4:$A$1000,0))&"","") -> ✓ Aadhaar Card ✓ Email ID | N16: =IFERROR(INDEX(SERVICE_DOCUMENTS!$T$4:$T$1000,MATCH(A16,SERVICE_DOCUMENTS!$A$4:$A$1000,0))&"","") | O16: Aadhaar holders whose details need correction, subject to UIDAI update limits. | P16: Step 1 → Bring your Aadhaar card and the email address (originals). Step 2 → Operator checks your current Aadhaar details and the document for the email id change. Step 3 → Aadhaar holder gives fingerprint / biometric authentication at the centre. Step 4 → New email id details are entered and shown to you for checking before submission. Step 5 → Pay the charge and collect the acknowledgement slip (URN) to track the update. | Q16: Depends on Department | R16: To Verify | S16: To Verify | T16: =IF(AND(OR(ISNUMBER(R16),R16="N/A"),OR(ISNUMBER(S16),S16="N/A"),OR(ISNUMBER(R16),ISNUMBER(S16))),N(R16)+N(S16),"To Verify") -> To Verify | U16: To Verify | V16: No | W16: Depends on Service | X16: Offline | Y16: No | AA16: Yes | AB16: Yes | AC16: To Verify | AD16: To Verify | AE16: No | AF16: To Verify | AG16: Active | AH16: Yes | AI16: No | AJ16: No | AK16: No | AL16: Aadhaar Centre | AM16: Demographic Update | AN16: =BA16&", "&AZ16 -> Aadhaar Email ID Update, Aadhaar Centre, Devmobile Stores, आधार ईमेल आईडी अपडेट, आधार सेंटर, सेवा | AO16: aadhaar-email-id-update | AP16: ✏️ | AQ16: 130 | AR16: Q1: Do I need to come in person? A1: Yes, the Aadhaar holder normally gives biometric authentication at the centre. Q2: Is there a limit on changes? A2: UIDAI limits some updates. Ask the operator for the current rule. | AS16: Aadhaar services depend on UIDAI operator authorization. Please confirm with the shop before visiting. | AT16: Fees, documents and processing time are subject to change as per government / bank / portal rules. Final charges are confirmed at the shop before the service starts. | AV16: To Verify | AW16: Set to Available as per owner's example; authorization still To Verify. | AX16: Aadhaar Email ID Update Service | Devmobile Stores | AY16: Aadhaar Email ID Update (आधार ईमेल आईडी अपडेट) at Devmobile Stores and Common Service Center & Aadhaar Centre. Check required documents, charges and process before you visit. | AZ16: आधार ईमेल आईडी अपडेट, आधार सेंटर, सेवा | BA16: Aadhaar Email ID Update, Aadhaar Centre, Devmobile Stores | BC16: =IFERROR(INDEX(CATEGORY_MASTER!$C$4:$C$30,MATCH(B16,CATEGORY_MASTER!$A$4:$A$30,0)),"") -> 🪪 | BD16: ="/services/"&AO16 -> /services/aadhaar-email-id-update | BE16: =IF(AND(AH16="Yes",AG16="Active",I16<>"Not Available"),"LIVE","HIDDEN") -> LIVE | BF16: Correct Aadhaar details • Biometric-verified update • Acknowledgement slip | BG16: Check Documents | BH16: =B16&"|"&COUNTIF($B$4:B16,B16) -> Aadhaar Centre|13 | BI16: =IF(AND(AI16="Yes",BE16="LIVE"),COUNTIFS($AI$4:AI16,"Yes",$BE$4:BE16,"LIVE"),"") | BJ16: =IF(AND(AJ16="Yes",BE16="LIVE"),COUNTIFS($AJ$4:AJ16,"Yes",$BE$4:BE16,"LIVE"),"") | BK16: =IF(AND(AK16="Yes",BE16="LIVE"),COUNTIFS($AK$4:AK16,"Yes",$BE$4:BE16,"LIVE"),"") | BL16: =IF(I16="To Verify",COUNTIF($I$4:I16,"To Verify"),"")
A17: AAD-014 | B17: Aadhaar Centre | C17: Aadhaar Services | D17: Demographic Update | E17: Aadhaar Relationship / Head of Family Detail Update | F17: आधार संबंध / परिवार मुखिया विवरण अपडेट | G17: Get Aadhaar Relationship / Head of Family Detail Update done at our Aadhaar Centre. | H17: Update or correct the relationship / head of family detail recorded in your Aadhaar through the Aadhaar Centre. | I17: To Verify | J17: =IFERROR(INDEX(AVAILABILITY_MASTER!$C$4:$C$10,MATCH(I17,AVAILABILITY_MASTER!$A$4:$A$10,0)),"To Be Confirmed") -> To Be Confirmed | K17: Depends | L17: To Verify | M17: =IFERROR(INDEX(SERVICE_DOCUMENTS!$S$4:$S$1000,MATCH(A17,SERVICE_DOCUMENTS!$A$4:$A$1000,0))&"","") -> ✓ Aadhaar Card | N17: =IFERROR(INDEX(SERVICE_DOCUMENTS!$T$4:$T$1000,MATCH(A17,SERVICE_DOCUMENTS!$A$4:$A$1000,0))&"","") -> • Identity Proof (To Verify) • Address Proof (To Verify) | O17: Aadhaar holders whose details need correction, subject to UIDAI update limits. | P17: Step 1 → Bring your Aadhaar card and the supporting document (originals). Step 2 → Operator checks your current Aadhaar details and the document for the relationship / head of family detail change. Step 3 → Aadhaar holder gives fingerprint / biometric authentication at the centre. Step 4 → New relationship / head of family detail details are entered and shown to you for checking before submission. Step 5 → Pay the charge and collect the acknowledgement slip (URN) to track the update. | Q17: Depends on Department | R17: To Verify | S17: To Verify | T17: =IF(AND(OR(ISNUMBER(R17),R17="N/A"),OR(ISNUMBER(S17),S17="N/A"),OR(ISNUMBER(R17),ISNUMBER(S17))),N(R17)+N(S17),"To Verify") -> To Verify | U17: To Verify | V17: No | W17: Depends on Service | X17: Offline | Y17: No | AA17: Yes | AB17: Yes | AC17: To Verify | AD17: To Verify | AE17: No | AF17: To Verify | AG17: To Verify | AH17: No | AI17: No | AJ17: No | AK17: No | AL17: Aadhaar Centre | AM17: Demographic Update | AN17: =BA17&", "&AZ17 -> Aadhaar Relationship / Head of Family Detail Update, Aadhaar Centre, Devmobile Stores, आधार संबंध / परिवार मुखिया विवरण अपडेट, आधार सेंटर, सेवा | AO17: aadhaar-relationship-head-of-family-detail-update | AP17: ✏️ | AQ17: 140 | AR17: Q1: Do I need to come in person? A1: Yes, the Aadhaar holder normally gives biometric authentication at the centre. Q2: Is there a limit on changes? A2: UIDAI limits some updates. Ask the operator for the current rule. | AS17: Aadhaar services depend on UIDAI operator authorization. Please confirm with the shop before visiting. | AT17: Fees, documents and processing time are subject to change as per government / bank / portal rules. Final charges are confirmed at the shop before the service starts. | AV17: To Verify | AW17: Confirm whether this field is updatable under your authorization | AX17: Aadhaar Relationship / Head of Family Detail Update Service | Devmobile Stores | AY17: Aadhaar Relationship / Head of Family Detail Update (आधार संबंध / परिवार मुखिया विवरण अपडेट) at Devmobile Stores and Common Service Center & Aadhaar Centre. Check required documents, charges and process before you visit. | AZ17: आधार संबंध / परिवार मुखिया विवरण अपडेट, आधार सेंटर, सेवा | BA17: Aadhaar Relationship / Head of Family Detail Update, Aadhaar Centre, Devmobile Stores | BC17: =IFERROR(INDEX(CATEGORY_MASTER!$C$4:$C$30,MATCH(B17,CATEGORY_MASTER!$A$4:$A$30,0)),"") -> 🪪 | BD17: ="/services/"&AO17 -> /services/aadhaar-relationship-head-of-family-detail-update | BE17: =IF(AND(AH17="Yes",AG17="Active",I17<>"Not Available"),"LIVE","HIDDEN") -> HIDDEN | BF17: Correct Aadhaar details • Biometric-verified update • Acknowledgement slip | BG17: Check Documents | BH17: =B17&"|"&COUNTIF($B$4:B17,B17) -> Aadhaar Centre|14 | BI17: =IF(AND(AI17="Yes",BE17="LIVE"),COUNTIFS($AI$4:AI17,"Yes",$BE$4:BE17,"LIVE"),"") | BJ17: =IF(AND(AJ17="Yes",BE17="LIVE"),COUNTIFS($AJ$4:AJ17,"Yes",$BE$4:BE17,"LIVE"),"") | BK17: =IF(AND(AK17="Yes",BE17="LIVE"),COUNTIFS($AK$4:AK17,"Yes",$BE$4:BE17,"LIVE"),"") | BL17: =IF(I17="To Verify",COUNTIF($I$4:I17,"To Verify"),"") -> 4
A18: AAD-015 | B18: Aadhaar Centre | C18: Aadhaar Services | D18: Demographic Update | E18: Aadhaar Combined Demographic Update (Multiple Fields) | F18: आधार संयुक्त डेमोग्राफिक अपडेट (कई जानकारियाँ) | G18: Get Aadhaar Combined Demographic Update (Multiple Fields) done at our Aadhaar Centre. | H18: Update or correct the combined demographic recorded in your Aadhaar through the Aadhaar Centre. | I18: Available | J18: =IFERROR(INDEX(AVAILABILITY_MASTER!$C$4:$C$10,MATCH(I18,AVAILABILITY_MASTER!$A$4:$A$10,0)),"To Be Confirmed") -> Available | K18: Yes | L18: To Verify | M18: =IFERROR(INDEX(SERVICE_DOCUMENTS!$S$4:$S$1000,MATCH(A18,SERVICE_DOCUMENTS!$A$4:$A$1000,0))&"","") -> ✓ Aadhaar Card | N18: =IFERROR(INDEX(SERVICE_DOCUMENTS!$T$4:$T$1000,MATCH(A18,SERVICE_DOCUMENTS!$A$4:$A$1000,0))&"","") -> • Identity Proof (To Verify) • Address Proof (To Verify) | O18: Aadhaar holders whose details need correction, subject to UIDAI update limits. | P18: Step 1 → Bring your Aadhaar card and the supporting document (originals). Step 2 → Operator checks your current Aadhaar details and the document for the combined demographic change. Step 3 → Aadhaar holder gives fingerprint / biometric authentication at the centre. Step 4 → New combined demographic details are entered and shown to you for checking before submission. Step 5 → Pay the charge and collect the acknowledgement slip (URN) to track the update. | Q18: Depends on Department | R18: To Verify | S18: To Verify | T18: =IF(AND(OR(ISNUMBER(R18),R18="N/A"),OR(ISNUMBER(S18),S18="N/A"),OR(ISNUMBER(R18),ISNUMBER(S18))),N(R18)+N(S18),"To Verify") -> To Verify | U18: To Verify | V18: No | W18: Depends on Service | X18: Offline | Y18: No | AA18: Yes | AB18: Yes | AC18: To Verify | AD18: To Verify | AE18: No | AF18: To Verify | AG18: Active | AH18: Yes | AI18: No | AJ18: No | AK18: No | AL18: Aadhaar Centre | AM18: Demographic Update | AN18: =BA18&", "&AZ18 -> Aadhaar Combined Demographic Update (Multiple Fields), Aadhaar Centre, Devmobile Stores, आधार संयुक्त डेमोग्राफिक अपडेट (कई जानकारियाँ), आधार सेंटर, सेवा | AO18: aadhaar-combined-demographic-update-multiple-fields | AP18: ✏️ | AQ18: 150 | AR18: Q1: Do I need to come in person? A1: Yes, the Aadhaar holder normally gives biometric authentication at the centre. Q2: Is there a limit on changes? A2: UIDAI limits some updates. Ask the operator for the current rule. | AS18: Aadhaar services depend on UIDAI operator authorization. Please confirm with the shop before visiting. | AT18: Fees, documents and processing time are subject to change as per government / bank / portal rules. Final charges are confirmed at the shop before the service starts. | AV18: To Verify | AW18: Set to Available as per owner's example; authorization still To Verify. | AX18: Aadhaar Combined Demographic Update (Multiple Fields) Service | Devmobile Stores | AY18: Aadhaar Combined Demographic Update (Multiple Fields) (आधार संयुक्त डेमोग्राफिक अपडेट (कई जानकारियाँ)) at Devmobile Stores and Common Service Center & Aadhaar Centre. Check required documents, charges and process before you visit. | AZ18: आधार संयुक्त डेमोग्राफिक अपडेट (कई जानकारियाँ), आधार सेंटर, सेवा | BA18: Aadhaar Combined Demographic Update (Multiple Fields), Aadhaar Centre, Devmobile Stores | BC18: =IFERROR(INDEX(CATEGORY_MASTER!$C$4:$C$30,MATCH(B18,CATEGORY_MASTER!$A$4:$A$30,0)),"") -> 🪪 | BD18: ="/services/"&AO18 -> /services/aadhaar-combined-demographic-update-multiple-fields | BE18: =IF(AND(AH18="Yes",AG18="Active",I18<>"Not Available"),"LIVE","HIDDEN") -> LIVE | BF18: Correct Aadhaar details • Biometric-verified update • Acknowledgement slip | BG18: Check Documents | BH18: =B18&"|"&COUNTIF($B$4:B18,B18) -> Aadhaar Centre|15 | BI18: =IF(AND(AI18="Yes",BE18="LIVE"),COUNTIFS($AI$4:AI18,"Yes",$BE$4:BE18,"LIVE"),"") | BJ18: =IF(AND(AJ18="Yes",BE18="LIVE"),COUNTIFS($AJ$4:AJ18,"Yes",$BE$4:BE18,"LIVE"),"") | BK18: =IF(AND(AK18="Yes",BE18="LIVE"),COUNTIFS($AK$4:AK18,"Yes",$BE$4:BE18,"LIVE"),"") | BL18: =IF(I18="To Verify",COUNTIF($I$4:I18,"To Verify"),"")
A19: AAD-016 | B19: Aadhaar Centre | C19: Aadhaar Services | D19: Biometric Update | E19: Aadhaar Fingerprint Update | F19: आधार फिंगरप्रिंट अपडेट | G19: Get Aadhaar Fingerprint Update done at our Aadhaar Centre. | H19: Aadhaar Fingerprint Update done at the Aadhaar Centre with fresh biometric capture. | I19: Available | J19: =IFERROR(INDEX(AVAILABILITY_MASTER!$C$4:$C$10,MATCH(I19,AVAILABILITY_MASTER!$A$4:$A$10,0)),"To Be Confirmed") -> Available | K19: Yes | L19: To Verify | M19: =IFERROR(INDEX(SERVICE_DOCUMENTS!$S$4:$S$1000,MATCH(A19,SERVICE_DOCUMENTS!$A$4:$A$1000,0))&"","") -> ✓ Aadhaar Card ✓ Customer Presence for Biometrics | N19: =IFERROR(INDEX(SERVICE_DOCUMENTS!$T$4:$T$1000,MATCH(A19,SERVICE_DOCUMENTS!$A$4:$A$1000,0))&"","") | O19: Aadhaar holders needing a biometric update (age-based mandatory update, poor quality or change). | P19: Step 1 → Bring your Aadhaar card. Step 2 → Operator checks the current biometric status in Aadhaar. Step 3 → New fingerprint are captured. Step 4 → Details are reviewed and submitted. Step 5 → Collect the acknowledgement slip (URN) and track the update. | Q19: Depends on Department | R19: To Verify | S19: To Verify | T19: =IF(AND(OR(ISNUMBER(R19),R19="N/A"),OR(ISNUMBER(S19),S19="N/A"),OR(ISNUMBER(R19),ISNUMBER(S19))),N(R19)+N(S19),"To Verify") -> To Verify | U19: To Verify | V19: No | W19: Depends on Service | X19: Offline | Y19: No | AA19: Yes | AB19: Yes | AC19: To Verify | AD19: To Verify | AE19: No | AF19: To Verify | AG19: Active | AH19: Yes | AI19: No | AJ19: No | AK19: No | AL19: Aadhaar Centre | AM19: Biometric Update | AN19: =BA19&", "&AZ19 -> Aadhaar Fingerprint Update, Aadhaar Centre, Devmobile Stores, आधार फिंगरप्रिंट अपडेट, आधार सेंटर, सेवा | AO19: aadhaar-fingerprint-update | AP19: 👆 | AQ19: 160 | AR19: Q1: Is the person required at the centre? A1: Yes, biometric capture needs the person present. | AS19: Aadhaar services depend on UIDAI operator authorization. Please confirm with the shop before visiting. | AT19: Fees, documents and processing time are subject to change as per government / bank / portal rules. Final charges are confirmed at the shop before the service starts. | AV19: To Verify | AW19: Set to Available as per owner's example; authorization still To Verify. | AX19: Aadhaar Fingerprint Update Service | Devmobile Stores | AY19: Aadhaar Fingerprint Update (आधार फिंगरप्रिंट अपडेट) at Devmobile Stores and Common Service Center & Aadhaar Centre. Check required documents, charges and process before you visit. | AZ19: आधार फिंगरप्रिंट अपडेट, आधार सेंटर, सेवा | BA19: Aadhaar Fingerprint Update, Aadhaar Centre, Devmobile Stores | BC19: =IFERROR(INDEX(CATEGORY_MASTER!$C$4:$C$30,MATCH(B19,CATEGORY_MASTER!$A$4:$A$30,0)),"") -> 🪪 | BD19: ="/services/"&AO19 -> /services/aadhaar-fingerprint-update | BE19: =IF(AND(AH19="Yes",AG19="Active",I19<>"Not Available"),"LIVE","HIDDEN") -> LIVE | BF19: Fix biometric problems • Keep Aadhaar working for authentication | BG19: Check Documents | BH19: =B19&"|"&COUNTIF($B$4:B19,B19) -> Aadhaar Centre|16 | BI19: =IF(AND(AI19="Yes",BE19="LIVE"),COUNTIFS($AI$4:AI19,"Yes",$BE$4:BE19,"LIVE"),"") | BJ19: =IF(AND(AJ19="Yes",BE19="LIVE"),COUNTIFS($AJ$4:AJ19,"Yes",$BE$4:BE19,"LIVE"),"") | BK19: =IF(AND(AK19="Yes",BE19="LIVE"),COUNTIFS($AK$4:AK19,"Yes",$BE$4:BE19,"LIVE"),"") | BL19: =IF(I19="To Verify",COUNTIF($I$4:I19,"To Verify"),"")
A20: AAD-017 | B20: Aadhaar Centre | C20: Aadhaar Services | D20: Biometric Update | E20: Aadhaar Iris Update | F20: आधार आइरिस अपडेट | G20: Get Aadhaar Iris Update done at our Aadhaar Centre. | H20: Aadhaar Iris Update done at the Aadhaar Centre with fresh biometric capture. | I20: Available | J20: =IFERROR(INDEX(AVAILABILITY_MASTER!$C$4:$C$10,MATCH(I20,AVAILABILITY_MASTER!$A$4:$A$10,0)),"To Be Confirmed") -> Available | K20: Yes | L20: To Verify | M20: =IFERROR(INDEX(SERVICE_DOCUMENTS!$S$4:$S$1000,MATCH(A20,SERVICE_DOCUMENTS!$A$4:$A$1000,0))&"","") -> ✓ Aadhaar Card ✓ Customer Presence for Biometrics | N20: =IFERROR(INDEX(SERVICE_DOCUMENTS!$T$4:$T$1000,MATCH(A20,SERVICE_DOCUMENTS!$A$4:$A$1000,0))&"","") | O20: Aadhaar holders needing a biometric update (age-based mandatory update, poor quality or change). | P20: Step 1 → Bring your Aadhaar card. Step 2 → Operator checks the current biometric status in Aadhaar. Step 3 → New iris are captured. Step 4 → Details are reviewed and submitted. Step 5 → Collect the acknowledgement slip (URN) and track the update. | Q20: Depends on Department | R20: To Verify | S20: To Verify | T20: =IF(AND(OR(ISNUMBER(R20),R20="N/A"),OR(ISNUMBER(S20),S20="N/A"),OR(ISNUMBER(R20),ISNUMBER(S20))),N(R20)+N(S20),"To Verify") -> To Verify | U20: To Verify | V20: No | W20: Depends on Service | X20: Offline | Y20: No | AA20: Yes | AB20: Yes | AC20: To Verify | AD20: To Verify | AE20: No | AF20: To Verify | AG20: Active | AH20: Yes | AI20: No | AJ20: No | AK20: No | AL20: Aadhaar Centre | AM20: Biometric Update | AN20: =BA20&", "&AZ20 -> Aadhaar Iris Update, Aadhaar Centre, Devmobile Stores, आधार आइरिस अपडेट, आधार सेंटर, सेवा | AO20: aadhaar-iris-update | AP20: 👆 | AQ20: 170 | AR20: Q1: Is the person required at the centre? A1: Yes, biometric capture needs the person present. | AS20: Aadhaar services depend on UIDAI operator authorization. Please confirm with the shop before visiting. | AT20: Fees, documents and processing time are subject to change as per government / bank / portal rules. Final charges are confirmed at the shop before the service starts. | AV20: To Verify | AW20: Set to Available as per owner's example; authorization still To Verify. | AX20: Aadhaar Iris Update Service | Devmobile Stores | AY20: Aadhaar Iris Update (आधार आइरिस अपडेट) at Devmobile Stores and Common Service Center & Aadhaar Centre. Check required documents, charges and process before you visit. | AZ20: आधार आइरिस अपडेट, आधार सेंटर, सेवा | BA20: Aadhaar Iris Update, Aadhaar Centre, Devmobile Stores | BC20: =IFERROR(INDEX(CATEGORY_MASTER!$C$4:$C$30,MATCH(B20,CATEGORY_MASTER!$A$4:$A$30,0)),"") -> 🪪 | BD20: ="/services/"&AO20 -> /services/aadhaar-iris-update | BE20: =IF(AND(AH20="Yes",AG20="Active",I20<>"Not Available"),"LIVE","HIDDEN") -> LIVE | BF20: Fix biometric problems • Keep Aadhaar working for authentication | BG20: Check Documents | BH20: =B20&"|"&COUNTIF($B$4:B20,B20) -> Aadhaar Centre|17 | BI20: =IF(AND(AI20="Yes",BE20="LIVE"),COUNTIFS($AI$4:AI20,"Yes",$BE$4:BE20,"LIVE"),"") | BJ20: =IF(AND(AJ20="Yes",BE20="LIVE"),COUNTIFS($AJ$4:AJ20,"Yes",$BE$4:BE20,"LIVE"),"") | BK20: =IF(AND(AK20="Yes",BE20="LIVE"),COUNTIFS($AK$4:AK20,"Yes",$BE$4:BE20,"LIVE"),"") | BL20: =IF(I20="To Verify",COUNTIF($I$4:I20,"To Verify"),"")
A21: AAD-018 | B21: Aadhaar Centre | C21: Aadhaar Services | D21: Biometric Update | E21: Aadhaar Photograph Update | F21: आधार फोटो अपडेट | G21: Get Aadhaar Photograph Update done at our Aadhaar Centre. | H21: Aadhaar Photograph Update done at the Aadhaar Centre with fresh biometric capture. | I21: Available | J21: =IFERROR(INDEX(AVAILABILITY_MASTER!$C$4:$C$10,MATCH(I21,AVAILABILITY_MASTER!$A$4:$A$10,0)),"To Be Confirmed") -> Available | K21: Yes | L21: To Verify | M21: =IFERROR(INDEX(SERVICE_DOCUMENTS!$S$4:$S$1000,MATCH(A21,SERVICE_DOCUMENTS!$A$4:$A$1000,0))&"","") -> ✓ Aadhaar Card ✓ Customer Presence for Biometrics | N21: =IFERROR(INDEX(SERVICE_DOCUMENTS!$T$4:$T$1000,MATCH(A21,SERVICE_DOCUMENTS!$A$4:$A$1000,0))&"","") | O21: Aadhaar holders needing a biometric update (age-based mandatory update, poor quality or change). | P21: Step 1 → Bring your Aadhaar card. Step 2 → Operator checks the current biometric status in Aadhaar. Step 3 → New photograph are captured. Step 4 → Details are reviewed and submitted. Step 5 → Collect the acknowledgement slip (URN) and track the update. | Q21: Depends on Department | R21: To Verify | S21: To Verify | T21: =IF(AND(OR(ISNUMBER(R21),R21="N/A"),OR(ISNUMBER(S21),S21="N/A"),OR(ISNUMBER(R21),ISNUMBER(S21))),N(R21)+N(S21),"To Verify") -> To Verify | U21: To Verify | V21: No | W21: Depends on Service | X21: Offline | Y21: No | AA21: Yes | AB21: Yes | AC21: To Verify | AD21: To Verify | AE21: No | AF21: To Verify | AG21: Active | AH21: Yes | AI21: No | AJ21: No | AK21: No | AL21: Aadhaar Centre | AM21: Biometric Update | AN21: =BA21&", "&AZ21 -> Aadhaar Photograph Update, Aadhaar Centre, Devmobile Stores, आधार फोटो अपडेट, आधार सेंटर, सेवा | AO21: aadhaar-photograph-update | AP21: 👆 | AQ21: 180 | AR21: Q1: Is the person required at the centre? A1: Yes, biometric capture needs the person present. | AS21: Aadhaar services depend on UIDAI operator authorization. Please confirm with the shop before visiting. | AT21: Fees, documents and processing time are subject to change as per government / bank / portal rules. Final charges are confirmed at the shop before the service starts. | AV21: To Verify | AW21: Set to Available as per owner's example; authorization still To Verify. | AX21: Aadhaar Photograph Update Service | Devmobile Stores | AY21: Aadhaar Photograph Update (आधार फोटो अपडेट) at Devmobile Stores and Common Service Center & Aadhaar Centre. Check required documents, charges and process before you visit. | AZ21: आधार फोटो अपडेट, आधार सेंटर, सेवा | BA21: Aadhaar Photograph Update, Aadhaar Centre, Devmobile Stores | BC21: =IFERROR(INDEX(CATEGORY_MASTER!$C$4:$C$30,MATCH(B21,CATEGORY_MASTER!$A$4:$A$30,0)),"") -> 🪪 | BD21: ="/services/"&AO21 -> /services/aadhaar-photograph-update | BE21: =IF(AND(AH21="Yes",AG21="Active",I21<>"Not Available"),"LIVE","HIDDEN") -> LIVE | BF21: Fix biometric problems • Keep Aadhaar working for authentication | BG21: Check Documents | BH21: =B21&"|"&COUNTIF($B$4:B21,B21) -> Aadhaar Centre|18 | BI21: =IF(AND(AI21="Yes",BE21="LIVE"),COUNTIFS($AI$4:AI21,"Yes",$BE$4:BE21,"LIVE"),"") | BJ21: =IF(AND(AJ21="Yes",BE21="LIVE"),COUNTIFS($AJ$4:AJ21,"Yes",$BE$4:BE21,"LIVE"),"") | BK21: =IF(AND(AK21="Yes",BE21="LIVE"),COUNTIFS($AK$4:AK21,"Yes",$BE$4:BE21,"LIVE"),"") | BL21: =IF(I21="To Verify",COUNTIF($I$4:I21,"To Verify"),"")
A22: AAD-019 | B22: Aadhaar Centre | C22: Aadhaar Services | D22: Biometric Update | E22: Aadhaar Biometric Update – Combined (Finger + Iris + Photo) | F22: आधार बायोमेट्रिक अपडेट – संयुक्त (उँगली + आँख + फोटो) | G22: Get Aadhaar Biometric Update – Combined (Finger + Iris + Photo) done at our Aadhaar Centre. | H22: Aadhaar Biometric Update – Combined (Finger + Iris + Photo) done at the Aadhaar Centre with fresh biometric capture. | I22: Available | J22: =IFERROR(INDEX(AVAILABILITY_MASTER!$C$4:$C$10,MATCH(I22,AVAILABILITY_MASTER!$A$4:$A$10,0)),"To Be Confirmed") -> Available | K22: Yes | L22: To Verify | M22: =IFERROR(INDEX(SERVICE_DOCUMENTS!$S$4:$S$1000,MATCH(A22,SERVICE_DOCUMENTS!$A$4:$A$1000,0))&"","") -> ✓ Aadhaar Card ✓ Customer Presence for Biometrics | N22: =IFERROR(INDEX(SERVICE_DOCUMENTS!$T$4:$T$1000,MATCH(A22,SERVICE_DOCUMENTS!$A$4:$A$1000,0))&"","") | O22: Aadhaar holders needing a biometric update (age-based mandatory update, poor quality or change). | P22: Step 1 → Bring your Aadhaar card. Step 2 → Operator checks the current biometric status in Aadhaar. Step 3 → New fingerprints, iris and photograph are captured. Step 4 → Details are reviewed and submitted. Step 5 → Collect the acknowledgement slip (URN) and track the update. | Q22: Depends on Department | R22: To Verify | S22: To Verify | T22: =IF(AND(OR(ISNUMBER(R22),R22="N/A"),OR(ISNUMBER(S22),S22="N/A"),OR(ISNUMBER(R22),ISNUMBER(S22))),N(R22)+N(S22),"To Verify") -> To Verify | U22: To Verify | V22: No | W22: Depends on Service | X22: Offline | Y22: No | AA22: Yes | AB22: Yes | AC22: To Verify | AD22: To Verify | AE22: No | AF22: To Verify | AG22: Active | AH22: Yes | AI22: No | AJ22: No | AK22: No | AL22: Aadhaar Centre | AM22: Biometric Update | AN22: =BA22&", "&AZ22 -> Aadhaar Biometric Update – Combined (Finger + Iris + Photo), Aadhaar Centre, Devmobile Stores, आधार बायोमेट्रिक अपडेट – संयुक्त (उँगली + आँख + फोटो), आधार सेंटर, सेवा | AO22: aadhaar-biometric-update-combined-finger-iris-photo | AP22: 👆 | AQ22: 190 | AR22: Q1: Is the person required at the centre? A1: Yes, biometric capture needs the person present. | AS22: Aadhaar services depend on UIDAI operator authorization. Please confirm with the shop before visiting. | AT22: Fees, documents and processing time are subject to change as per government / bank / portal rules. Final charges are confirmed at the shop before the service starts. | AV22: To Verify | AW22: Set to Available as per owner's example; authorization still To Verify. | AX22: Aadhaar Biometric Update – Combined (Finger + Iris + Photo) Service | Devmobile Stores | AY22: Aadhaar Biometric Update – Combined (Finger + Iris + Photo) (आधार बायोमेट्रिक अपडेट – संयुक्त (उँगली + आँख + फोटो)) at Devmobile Stores and Common Service Center & Aadhaar Centre. Check required documents, charges and process before you visit. | AZ22: आधार बायोमेट्रिक अपडेट – संयुक्त (उँगली + आँख + फोटो), आधार सेंटर, सेवा | BA22: Aadhaar Biometric Update – Combined (Finger + Iris + Photo), Aadhaar Centre, Devmobile Stores | BC22: =IFERROR(INDEX(CATEGORY_MASTER!$C$4:$C$30,MATCH(B22,CATEGORY_MASTER!$A$4:$A$30,0)),"") -> 🪪 | BD22: ="/services/"&AO22 -> /services/aadhaar-biometric-update-combined-finger-iris-photo | BE22: =IF(AND(AH22="Yes",AG22="Active",I22<>"Not Available"),"LIVE","HIDDEN") -> LIVE | BF22: Fix biometric problems • Keep Aadhaar working for authentication | BG22: Check Documents | BH22: =B22&"|"&COUNTIF($B$4:B22,B22) -> Aadhaar Centre|19 | BI22: =IF(AND(AI22="Yes",BE22="LIVE"),COUNTIFS($AI$4:AI22,"Yes",$BE$4:BE22,"LIVE"),"") | BJ22: =IF(AND(AJ22="Yes",BE22="LIVE"),COUNTIFS($AJ$4:AJ22,"Yes",$BE$4:BE22,"LIVE"),"") | BK22: =IF(AND(AK22="Yes",BE22="LIVE"),COUNTIFS($AK$4:AK22,"Yes",$BE$4:BE22,"LIVE"),"") | BL22: =IF(I22="To Verify",COUNTIF($I$4:I22,"To Verify"),"")
A23: AAD-020 | B23: Aadhaar Centre | C23: Aadhaar Services | D23: Biometric Update | E23: Mandatory Biometric Update – Child at Age 5 | F23: अनिवार्य बायोमेट्रिक अपडेट – बच्चा (5 वर्ष) | G23: Get Mandatory Biometric Update – Child at Age 5 done at our Aadhaar Centre. | H23: Mandatory Biometric Update – Child at Age 5 done at the Aadhaar Centre with fresh biometric capture. | I23: Available | J23: =IFERROR(INDEX(AVAILABILITY_MASTER!$C$4:$C$10,MATCH(I23,AVAILABILITY_MASTER!$A$4:$A$10,0)),"To Be Confirmed") -> Available | K23: Yes | L23: To Verify | M23: =IFERROR(INDEX(SERVICE_DOCUMENTS!$S$4:$S$1000,MATCH(A23,SERVICE_DOCUMENTS!$A$4:$A$1000,0))&"","") -> ✓ Aadhaar Card ✓ Customer Presence for Biometrics ✓ Parent / Guardian Aadhaar | N23: =IFERROR(INDEX(SERVICE_DOCUMENTS!$T$4:$T$1000,MATCH(A23,SERVICE_DOCUMENTS!$A$4:$A$1000,0))&"","") | O23: Aadhaar holders needing a biometric update (age-based mandatory update, poor quality or change). | P23: Step 1 → Bring your Aadhaar card and the child with a parent / guardian. Step 2 → Operator checks the current biometric status in Aadhaar. Step 3 → New mandatory biometric – child at age 5 are captured. Step 4 → Details are reviewed and submitted. Step 5 → Collect the acknowledgement slip (URN) and track the update. | Q23: Depends on Department | R23: To Verify | S23: To Verify | T23: =IF(AND(OR(ISNUMBER(R23),R23="N/A"),OR(ISNUMBER(S23),S23="N/A"),OR(ISNUMBER(R23),ISNUMBER(S23))),N(R23)+N(S23),"To Verify") -> To Verify | U23: To Verify | V23: No | W23: Depends on Service | X23: Offline | Y23: No | AA23: Yes | AB23: Yes | AC23: To Verify | AD23: To Verify | AE23: No | AF23: To Verify | AG23: Active | AH23: Yes | AI23: No | AJ23: No | AK23: No | AL23: Aadhaar Centre | AM23: Biometric Update | AN23: =BA23&", "&AZ23 -> Mandatory Biometric Update – Child at Age 5, Aadhaar Centre, Devmobile Stores, अनिवार्य बायोमेट्रिक अपडेट – बच्चा (5 वर्ष), आधार सेंटर, सेवा | AO23: mandatory-biometric-update-child-at-age-5 | AP23: 👆 | AQ23: 200 | AR23: Q1: Is the person required at the centre? A1: Yes, biometric capture needs the person present. | AS23: Aadhaar services depend on UIDAI operator authorization. Please confirm with the shop before visiting. | AT23: Fees, documents and processing time are subject to change as per government / bank / portal rules. Final charges are confirmed at the shop before the service starts. | AV23: To Verify | AW23: Check current UIDAI fee-waiver rule for child mandatory updates | Set to Available as per owner's example; authorization still To Verify. | AX23: Mandatory Biometric Update – Child at Age 5 Service | Devmobile Stores | AY23: Mandatory Biometric Update – Child at Age 5 (अनिवार्य बायोमेट्रिक अपडेट – बच्चा (5 वर्ष)) at Devmobile Stores and Common Service Center & Aadhaar Centre. Check required documents, charges and process before you visit. | AZ23: अनिवार्य बायोमेट्रिक अपडेट – बच्चा (5 वर्ष), आधार सेंटर, सेवा | BA23: Mandatory Biometric Update – Child at Age 5, Aadhaar Centre, Devmobile Stores | BC23: =IFERROR(INDEX(CATEGORY_MASTER!$C$4:$C$30,MATCH(B23,CATEGORY_MASTER!$A$4:$A$30,0)),"") -> 🪪 | BD23: ="/services/"&AO23 -> /services/mandatory-biometric-update-child-at-age-5 | BE23: =IF(AND(AH23="Yes",AG23="Active",I23<>"Not Available"),"LIVE","HIDDEN") -> LIVE | BF23: Fix biometric problems • Keep Aadhaar working for authentication | BG23: Check Documents | BH23: =B23&"|"&COUNTIF($B$4:B23,B23) -> Aadhaar Centre|20 | BI23: =IF(AND(AI23="Yes",BE23="LIVE"),COUNTIFS($AI$4:AI23,"Yes",$BE$4:BE23,"LIVE"),"") | BJ23: =IF(AND(AJ23="Yes",BE23="LIVE"),COUNTIFS($AJ$4:AJ23,"Yes",$BE$4:BE23,"LIVE"),"") | BK23: =IF(AND(AK23="Yes",BE23="LIVE"),COUNTIFS($AK$4:AK23,"Yes",$BE$4:BE23,"LIVE"),"") | BL23: =IF(I23="To Verify",COUNTIF($I$4:I23,"To Verify"),"")
A24: AAD-021 | B24: Aadhaar Centre | C24: Aadhaar Services | D24: Biometric Update | E24: Mandatory Biometric Update – Child at Age 15 | F24: अनिवार्य बायोमेट्रिक अपडेट – बच्चा (15 वर्ष) | G24: Get Mandatory Biometric Update – Child at Age 15 done at our Aadhaar Centre. | H24: Mandatory Biometric Update – Child at Age 15 done at the Aadhaar Centre with fresh biometric capture. | I24: Available | J24: =IFERROR(INDEX(AVAILABILITY_MASTER!$C$4:$C$10,MATCH(I24,AVAILABILITY_MASTER!$A$4:$A$10,0)),"To Be Confirmed") -> Available | K24: Yes | L24: To Verify | M24: =IFERROR(INDEX(SERVICE_DOCUMENTS!$S$4:$S$1000,MATCH(A24,SERVICE_DOCUMENTS!$A$4:$A$1000,0))&"","") -> ✓ Aadhaar Card ✓ Customer Presence for Biometrics ✓ Parent / Guardian Aadhaar | N24: =IFERROR(INDEX(SERVICE_DOCUMENTS!$T$4:$T$1000,MATCH(A24,SERVICE_DOCUMENTS!$A$4:$A$1000,0))&"","") | O24: Aadhaar holders needing a biometric update (age-based mandatory update, poor quality or change). | P24: Step 1 → Bring your Aadhaar card and the child with a parent / guardian. Step 2 → Operator checks the current biometric status in Aadhaar. Step 3 → New mandatory biometric – child at age 15 are captured. Step 4 → Details are reviewed and submitted. Step 5 → Collect the acknowledgement slip (URN) and track the update. | Q24: Depends on Department | R24: To Verify | S24: To Verify | T24: =IF(AND(OR(ISNUMBER(R24),R24="N/A"),OR(ISNUMBER(S24),S24="N/A"),OR(ISNUMBER(R24),ISNUMBER(S24))),N(R24)+N(S24),"To Verify") -> To Verify | U24: To Verify | V24: No | W24: Depends on Service | X24: Offline | Y24: No | AA24: Yes | AB24: Yes | AC24: To Verify | AD24: To Verify | AE24: No | AF24: To Verify | AG24: Active | AH24: Yes | AI24: No | AJ24: No | AK24: No | AL24: Aadhaar Centre | AM24: Biometric Update | AN24: =BA24&", "&AZ24 -> Mandatory Biometric Update – Child at Age 15, Aadhaar Centre, Devmobile Stores, अनिवार्य बायोमेट्रिक अपडेट – बच्चा (15 वर्ष), आधार सेंटर, सेवा | AO24: mandatory-biometric-update-child-at-age-15 | AP24: 👆 | AQ24: 210 | AR24: Q1: Is the person required at the centre? A1: Yes, biometric capture needs the person present. | AS24: Aadhaar services depend on UIDAI operator authorization. Please confirm with the shop before visiting. | AT24: Fees, documents and processing time are subject to change as per government / bank / portal rules. Final charges are confirmed at the shop before the service starts. | AV24: To Verify | AW24: Check current UIDAI fee-waiver rule for child mandatory updates | Set to Available as per owner's example; authorization still To Verify. | AX24: Mandatory Biometric Update – Child at Age 15 Service | Devmobile Stores | AY24: Mandatory Biometric Update – Child at Age 15 (अनिवार्य बायोमेट्रिक अपडेट – बच्चा (15 वर्ष)) at Devmobile Stores and Common Service Center & Aadhaar Centre. Check required documents, charges and process before you visit. | AZ24: अनिवार्य बायोमेट्रिक अपडेट – बच्चा (15 वर्ष), आधार सेंटर, सेवा | BA24: Mandatory Biometric Update – Child at Age 15, Aadhaar Centre, Devmobile Stores | BC24: =IFERROR(INDEX(CATEGORY_MASTER!$C$4:$C$30,MATCH(B24,CATEGORY_MASTER!$A$4:$A$30,0)),"") -> 🪪 | BD24: ="/services/"&AO24 -> /services/mandatory-biometric-update-child-at-age-15 | BE24: =IF(AND(AH24="Yes",AG24="Active",I24<>"Not Available"),"LIVE","HIDDEN") -> LIVE | BF24: Fix biometric problems • Keep Aadhaar working for authentication | BG24: Check Documents | BH24: =B24&"|"&COUNTIF($B$4:B24,B24) -> Aadhaar Centre|21 | BI24: =IF(AND(AI24="Yes",BE24="LIVE"),COUNTIFS($AI$4:AI24,"Yes",$BE$4:BE24,"LIVE"),"") | BJ24: =IF(AND(AJ24="Yes",BE24="LIVE"),COUNTIFS($AJ$4:AJ24,"Yes",$BE$4:BE24,"LIVE"),"") | BK24: =IF(AND(AK24="Yes",BE24="LIVE"),COUNTIFS($AK$4:AK24,"Yes",$BE$4:BE24,"LIVE"),"") | BL24: =IF(I24="To Verify",COUNTIF($I$4:I24,"To Verify"),"")
A25: AAD-022 | B25: Aadhaar Centre | C25: Aadhaar Services | D25: Biometric Update | E25: Aadhaar Biometric Update – Adult (Quality / Periodic) | F25: आधार बायोमेट्रिक अपडेट – वयस्क (क्वालिटी / आवधिक) | G25: Get Aadhaar Biometric Update – Adult (Quality / Periodic) done at our Aadhaar Centre. | H25: Aadhaar Biometric Update – Adult (Quality / Periodic) done at the Aadhaar Centre with fresh biometric capture. | I25: Available | J25: =IFERROR(INDEX(AVAILABILITY_MASTER!$C$4:$C$10,MATCH(I25,AVAILABILITY_MASTER!$A$4:$A$10,0)),"To Be Confirmed") -> Available | K25: Yes | L25: To Verify | M25: =IFERROR(INDEX(SERVICE_DOCUMENTS!$S$4:$S$1000,MATCH(A25,SERVICE_DOCUMENTS!$A$4:$A$1000,0))&"","") -> ✓ Aadhaar Card ✓ Customer Presence for Biometrics | N25: =IFERROR(INDEX(SERVICE_DOCUMENTS!$T$4:$T$1000,MATCH(A25,SERVICE_DOCUMENTS!$A$4:$A$1000,0))&"","") | O25: Aadhaar holders needing a biometric update (age-based mandatory update, poor quality or change). | P25: Step 1 → Bring your Aadhaar card. Step 2 → Operator checks the current biometric status in Aadhaar. Step 3 → New biometric – adult (quality / periodic) are captured. Step 4 → Details are reviewed and submitted. Step 5 → Collect the acknowledgement slip (URN) and track the update. | Q25: Depends on Department | R25: To Verify | S25: To Verify | T25: =IF(AND(OR(ISNUMBER(R25),R25="N/A"),OR(ISNUMBER(S25),S25="N/A"),OR(ISNUMBER(R25),ISNUMBER(S25))),N(R25)+N(S25),"To Verify") -> To Verify | U25: To Verify | V25: No | W25: Depends on Service | X25: Offline | Y25: No | AA25: Yes | AB25: Yes | AC25: To Verify | AD25: To Verify | AE25: No | AF25: To Verify | AG25: Active | AH25: Yes | AI25: No | AJ25: No | AK25: No | AL25: Aadhaar Centre | AM25: Biometric Update | AN25: =BA25&", "&AZ25 -> Aadhaar Biometric Update – Adult (Quality / Periodic), Aadhaar Centre, Devmobile Stores, आधार बायोमेट्रिक अपडेट – वयस्क (क्वालिटी / आवधिक), आधार सेंटर, सेवा | AO25: aadhaar-biometric-update-adult-quality-periodic | AP25: 👆 | AQ25: 220 | AR25: Q1: Is the person required at the centre? A1: Yes, biometric capture needs the person present. | AS25: Aadhaar services depend on UIDAI operator authorization. Please confirm with the shop before visiting. | AT25: Fees, documents and processing time are subject to change as per government / bank / portal rules. Final charges are confirmed at the shop before the service starts. | AV25: To Verify | AW25: Set to Available as per owner's example; authorization still To Verify. | AX25: Aadhaar Biometric Update – Adult (Quality / Periodic) Service | Devmobile Stores | AY25: Aadhaar Biometric Update – Adult (Quality / Periodic) (आधार बायोमेट्रिक अपडेट – वयस्क (क्वालिटी / आवधिक)) at Devmobile Stores and Common Service Center & Aadhaar Centre. Check required documents, charges and process before you visit. | AZ25: आधार बायोमेट्रिक अपडेट – वयस्क (क्वालिटी / आवधिक), आधार सेंटर, सेवा | BA25: Aadhaar Biometric Update – Adult (Quality / Periodic), Aadhaar Centre, Devmobile Stores | BC25: =IFERROR(INDEX(CATEGORY_MASTER!$C$4:$C$30,MATCH(B25,CATEGORY_MASTER!$A$4:$A$30,0)),"") -> 🪪 | BD25: ="/services/"&AO25 -> /services/aadhaar-biometric-update-adult-quality-periodic | BE25: =IF(AND(AH25="Yes",AG25="Active",I25<>"Not Available"),"LIVE","HIDDEN") -> LIVE | BF25: Fix biometric problems • Keep Aadhaar working for authentication | BG25: Check Documents | BH25: =B25&"|"&COUNTIF($B$4:B25,B25) -> Aadhaar Centre|22 | BI25: =IF(AND(AI25="Yes",BE25="LIVE"),COUNTIFS($AI$4:AI25,"Yes",$BE$4:BE25,"LIVE"),"") | BJ25: =IF(AND(AJ25="Yes",BE25="LIVE"),COUNTIFS($AJ$4:AJ25,"Yes",$BE$4:BE25,"LIVE"),"") | BK25: =IF(AND(AK25="Yes",BE25="LIVE"),COUNTIFS($AK$4:AK25,"Yes",$BE$4:BE25,"LIVE"),"") | BL25: =IF(I25="To Verify",COUNTIF($I$4:I25,"To Verify"),"")
A26: AAD-023 | B26: Aadhaar Centre | C26: Aadhaar Services | D26: Biometric Update | E26: Aadhaar Biometric Lock / Unlock Assistance | F26: आधार बायोमेट्रिक लॉक / अनलॉक सहायता | G26: Get Aadhaar Biometric Lock / Unlock Assistance done at our Aadhaar Centre. | H26: Assistance with aadhaar biometric lock / unlock assistance through the UIDAI portal. | I26: Portal Dependent | J26: =IFERROR(INDEX(AVAILABILITY_MASTER!$C$4:$C$10,MATCH(I26,AVAILABILITY_MASTER!$A$4:$A$10,0)),"To Be Confirmed") -> Depends on Portal – Confirm at Shop | K26: Depends | L26: Portal Dependent | M26: =IFERROR(INDEX(SERVICE_DOCUMENTS!$S$4:$S$1000,MATCH(A26,SERVICE_DOCUMENTS!$A$4:$A$1000,0))&"","") -> ✓ Aadhaar Card ✓ Aadhaar-Linked Mobile Number | N26: =IFERROR(INDEX(SERVICE_DOCUMENTS!$T$4:$T$1000,MATCH(A26,SERVICE_DOCUMENTS!$A$4:$A$1000,0))&"","") | O26: Aadhaar holders with a mobile number linked to Aadhaar. | P26: Step 1 → Bring your Aadhaar number and the mobile number linked with Aadhaar. Step 2 → Operator opens the UIDAI service for 'Aadhaar Biometric Lock / Unlock Assistance'. Step 3 → OTP is sent to your linked mobile and entered. Step 4 → Service is completed and the result is downloaded / shown to you. Step 5 → Pay the assistance charge. | Q26: 15–30 Minutes | R26: To Verify | S26: To Verify | T26: =IF(AND(OR(ISNUMBER(R26),R26="N/A"),OR(ISNUMBER(S26),S26="N/A"),OR(ISNUMBER(R26),ISNUMBER(S26))),N(R26)+N(S26),"To Verify") -> To Verify | U26: To Verify | V26: No | W26: Depends on Service | X26: Portal Dependent | Y26: Yes | Z26: UIDAI portal / mAadhaar | AA26: Depends | AB26: Yes | AC26: To Verify | AD26: To Verify | AE26: To Verify | AF26: To Verify | AG26: To Verify | AH26: No | AI26: No | AJ26: No | AK26: No | AL26: Aadhaar Centre | AM26: Biometric Update | AN26: =BA26&", "&AZ26 -> Aadhaar Biometric Lock / Unlock Assistance, Aadhaar Centre, Devmobile Stores, आधार बायोमेट्रिक लॉक / अनलॉक सहायता, आधार सेंटर, सेवा | AO26: aadhaar-biometric-lock-unlock-assistance | AP26: 👆 | AQ26: 230 | AR26: Q1: What if my mobile is not linked? A1: Some online services need OTP; the mobile must first be updated at an Aadhaar Centre. | AS26: Portal availability and OTP delivery depend on UIDAI. | AT26: Fees, documents and processing time are subject to change as per government / bank / portal rules. Final charges are confirmed at the shop before the service starts. | AV26: To Verify | AW26: Done via UIDAI portal / mAadhaar with OTP | AX26: Aadhaar Biometric Lock / Unlock Assistance Service | Devmobile Stores | AY26: Aadhaar Biometric Lock / Unlock Assistance (आधार बायोमेट्रिक लॉक / अनलॉक सहायता) at Devmobile Stores and Common Service Center & Aadhaar Centre. Check required documents, charges and process before you visit. | AZ26: आधार बायोमेट्रिक लॉक / अनलॉक सहायता, आधार सेंटर, सेवा | BA26: Aadhaar Biometric Lock / Unlock Assistance, Aadhaar Centre, Devmobile Stores | BC26: =IFERROR(INDEX(CATEGORY_MASTER!$C$4:$C$30,MATCH(B26,CATEGORY_MASTER!$A$4:$A$30,0)),"") -> 🪪 | BD26: ="/services/"&AO26 -> /services/aadhaar-biometric-lock-unlock-assistance | BE26: =IF(AND(AH26="Yes",AG26="Active",I26<>"Not Available"),"LIVE","HIDDEN") -> HIDDEN | BF26: In-person assistance at the shop • Help checking your documents • Receipt / acknowledgement where applicable | BG26: Check Documents | BH26: =B26&"|"&COUNTIF($B$4:B26,B26) -> Aadhaar Centre|23 | BI26: =IF(AND(AI26="Yes",BE26="LIVE"),COUNTIFS($AI$4:AI26,"Yes",$BE$4:BE26,"LIVE"),"") | BJ26: =IF(AND(AJ26="Yes",BE26="LIVE"),COUNTIFS($AJ$4:AJ26,"Yes",$BE$4:BE26,"LIVE"),"") | BK26: =IF(AND(AK26="Yes",BE26="LIVE"),COUNTIFS($AK$4:AK26,"Yes",$BE$4:BE26,"LIVE"),"") | BL26: =IF(I26="To Verify",COUNTIF($I$4:I26,"To Verify"),"")
A27: AAD-024 | B27: Aadhaar Centre | C27: Aadhaar Services | D27: Document Update | E27: Aadhaar Document Update (Identity & Address Proof) | F27: आधार दस्तावेज़ अपडेट (पहचान व पता प्रमाण) | G27: Get Aadhaar Document Update (Identity & Address Proof) done at our Aadhaar Centre. | H27: Update the supporting identity and address documents linked to your Aadhaar. | I27: Available | J27: =IFERROR(INDEX(AVAILABILITY_MASTER!$C$4:$C$10,MATCH(I27,AVAILABILITY_MASTER!$A$4:$A$10,0)),"To Be Confirmed") -> Available | K27: Yes | L27: To Verify | M27: =IFERROR(INDEX(SERVICE_DOCUMENTS!$S$4:$S$1000,MATCH(A27,SERVICE_DOCUMENTS!$A$4:$A$1000,0))&"","") -> ✓ Aadhaar Card ✓ Identity Proof ✓ Address Proof | N27: =IFERROR(INDEX(SERVICE_DOCUMENTS!$T$4:$T$1000,MATCH(A27,SERVICE_DOCUMENTS!$A$4:$A$1000,0))&"","") | O27: Aadhaar holders updating identity / address documents (e.g. older Aadhaar). | P27: Step 1 → Bring Aadhaar card with original identity and address proof. Step 2 → Operator scans the documents. Step 3 → Biometric authentication of the Aadhaar holder. Step 4 → Submit and collect the acknowledgement (URN). | Q27: Depends on Department | R27: To Verify | S27: To Verify | T27: =IF(AND(OR(ISNUMBER(R27),R27="N/A"),OR(ISNUMBER(S27),S27="N/A"),OR(ISNUMBER(R27),ISNUMBER(S27))),N(R27)+N(S27),"To Verify") -> To Verify | U27: To Verify | V27: No | W27: Depends on Service | X27: Offline | Y27: No | AA27: Yes | AB27: Yes | AC27: To Verify | AD27: To Verify | AE27: No | AF27: To Verify | AG27: Active | AH27: Yes | AI27: No | AJ27: No | AK27: No | AL27: Aadhaar Centre | AM27: Document Update | AN27: =BA27&", "&AZ27 -> Aadhaar Document Update (Identity & Address Proof), Aadhaar Centre, Devmobile Stores, आधार दस्तावेज़ अपडेट (पहचान व पता प्रमाण), आधार सेंटर, सेवा | AO27: aadhaar-document-update-identity-address-proof | AP27: 📄 | AQ27: 240 | AR27: Q1: Where can I check the current charges? A1: Charges are confirmed at the shop and may change as per government / bank rules. | AS27: Aadhaar services depend on UIDAI operator authorization. Please confirm with the shop before visiting. | AT27: Fees, documents and processing time are subject to change as per government / bank / portal rules. Final charges are confirmed at the shop before the service starts. | AV27: To Verify | AW27: Can also be done online via myAadhaar portal if the customer prefers | Set to Available as per owner's example; authorization still To Verify. | AX27: Aadhaar Document Update (Identity & Address Proof) Service | Devmobile Stores | AY27: Aadhaar Document Update (Identity & Address Proof) (आधार दस्तावेज़ अपडेट (पहचान व पता प्रमाण)) at Devmobile Stores and Common Service Center & Aadhaar Centre. Check required documents, charges and process before you visit. | AZ27: आधार दस्तावेज़ अपडेट (पहचान व पता प्रमाण), आधार सेंटर, सेवा | BA27: Aadhaar Document Update (Identity & Address Proof), Aadhaar Centre, Devmobile Stores | BC27: =IFERROR(INDEX(CATEGORY_MASTER!$C$4:$C$30,MATCH(B27,CATEGORY_MASTER!$A$4:$A$30,0)),"") -> 🪪 | BD27: ="/services/"&AO27 -> /services/aadhaar-document-update-identity-address-proof | BE27: =IF(AND(AH27="Yes",AG27="Active",I27<>"Not Available"),"LIVE","HIDDEN") -> LIVE | BF27: In-person assistance at the shop • Help checking your documents • Receipt / acknowledgement where applicable | BG27: Check Documents | BH27: =B27&"|"&COUNTIF($B$4:B27,B27) -> Aadhaar Centre|24 | BI27: =IF(AND(AI27="Yes",BE27="LIVE"),COUNTIFS($AI$4:AI27,"Yes",$BE$4:BE27,"LIVE"),"") | BJ27: =IF(AND(AJ27="Yes",BE27="LIVE"),COUNTIFS($AJ$4:AJ27,"Yes",$BE$4:BE27,"LIVE"),"") | BK27: =IF(AND(AK27="Yes",BE27="LIVE"),COUNTIFS($AK$4:AK27,"Yes",$BE$4:BE27,"LIVE"),"") | BL27: =IF(I27="To Verify",COUNTIF($I$4:I27,"To Verify"),"")
A28: AAD-025 | B28: Aadhaar Centre | C28: Aadhaar Services | D28: Document Update | E28: Aadhaar Document Update – Online Assistance | F28: आधार दस्तावेज़ अपडेट – ऑनलाइन सहायता | G28: Get Aadhaar Document Update – Online Assistance done at our Aadhaar Centre. | H28: Assistance with aadhaar document update – online assistance through the UIDAI portal. | I28: Portal Dependent | J28: =IFERROR(INDEX(AVAILABILITY_MASTER!$C$4:$C$10,MATCH(I28,AVAILABILITY_MASTER!$A$4:$A$10,0)),"To Be Confirmed") -> Depends on Portal – Confirm at Shop | K28: Depends | L28: Portal Dependent | M28: =IFERROR(INDEX(SERVICE_DOCUMENTS!$S$4:$S$1000,MATCH(A28,SERVICE_DOCUMENTS!$A$4:$A$1000,0))&"","") -> ✓ Aadhaar Card ✓ Aadhaar-Linked Mobile Number | N28: =IFERROR(INDEX(SERVICE_DOCUMENTS!$T$4:$T$1000,MATCH(A28,SERVICE_DOCUMENTS!$A$4:$A$1000,0))&"","") | O28: Aadhaar holders with a mobile number linked to Aadhaar. | P28: Step 1 → Bring your Aadhaar number and the mobile number linked with Aadhaar. Step 2 → Operator opens the UIDAI service for 'Aadhaar Document Update – Online Assistance'. Step 3 → OTP is sent to your linked mobile and entered. Step 4 → Service is completed and the result is downloaded / shown to you. Step 5 → Pay the assistance charge. | Q28: 15–30 Minutes | R28: To Verify | S28: To Verify | T28: =IF(AND(OR(ISNUMBER(R28),R28="N/A"),OR(ISNUMBER(S28),S28="N/A"),OR(ISNUMBER(R28),ISNUMBER(S28))),N(R28)+N(S28),"To Verify") -> To Verify | U28: To Verify | V28: No | W28: Depends on Service | X28: Portal Dependent | Y28: Yes | Z28: UIDAI portal / mAadhaar | AA28: Depends | AB28: Yes | AC28: To Verify | AD28: To Verify | AE28: To Verify | AF28: To Verify | AG28: To Verify | AH28: No | AI28: No | AJ28: No | AK28: No | AL28: Aadhaar Centre | AM28: Document Update | AN28: =BA28&", "&AZ28 -> Aadhaar Document Update – Online Assistance, Aadhaar Centre, Devmobile Stores, आधार दस्तावेज़ अपडेट – ऑनलाइन सहायता, आधार सेंटर, सेवा | AO28: aadhaar-document-update-online-assistance | AP28: 📄 | AQ28: 250 | AR28: Q1: What if my mobile is not linked? A1: Some online services need OTP; the mobile must first be updated at an Aadhaar Centre. | AS28: Portal availability and OTP delivery depend on UIDAI. | AT28: Fees, documents and processing time are subject to change as per government / bank / portal rules. Final charges are confirmed at the shop before the service starts. | AV28: To Verify | AW28: Needs mobile number linked to Aadhaar for OTP | AX28: Aadhaar Document Update – Online Assistance Service | Devmobile Stores | AY28: Aadhaar Document Update – Online Assistance (आधार दस्तावेज़ अपडेट – ऑनलाइन सहायता) at Devmobile Stores and Common Service Center & Aadhaar Centre. Check required documents, charges and process before you visit. | AZ28: आधार दस्तावेज़ अपडेट – ऑनलाइन सहायता, आधार सेंटर, सेवा | BA28: Aadhaar Document Update – Online Assistance, Aadhaar Centre, Devmobile Stores | BC28: =IFERROR(INDEX(CATEGORY_MASTER!$C$4:$C$30,MATCH(B28,CATEGORY_MASTER!$A$4:$A$30,0)),"") -> 🪪 | BD28: ="/services/"&AO28 -> /services/aadhaar-document-update-online-assistance | BE28: =IF(AND(AH28="Yes",AG28="Active",I28<>"Not Available"),"LIVE","HIDDEN") -> HIDDEN | BF28: In-person assistance at the shop • Help checking your documents • Receipt / acknowledgement where applicable | BG28: Check Documents | BH28: =B28&"|"&COUNTIF($B$4:B28,B28) -> Aadhaar Centre|25 | BI28: =IF(AND(AI28="Yes",BE28="LIVE"),COUNTIFS($AI$4:AI28,"Yes",$BE$4:BE28,"LIVE"),"") | BJ28: =IF(AND(AJ28="Yes",BE28="LIVE"),COUNTIFS($AJ$4:AJ28,"Yes",$BE$4:BE28,"LIVE"),"") | BK28: =IF(AND(AK28="Yes",BE28="LIVE"),COUNTIFS($AK$4:AK28,"Yes",$BE$4:BE28,"LIVE"),"") | BL28: =IF(I28="To Verify",COUNTIF($I$4:I28,"To Verify"),"")
A29: AAD-026 | B29: Aadhaar Centre | C29: Aadhaar Services | D29: Download, Print & Status | E29: Aadhaar Download Assistance (e-Aadhaar) | F29: आधार डाउनलोड सहायता (e-Aadhaar) | G29: Get Aadhaar Download Assistance (e-Aadhaar) done at our Aadhaar Centre. | H29: Assistance with aadhaar download assistance (e-aadhaar) through the UIDAI portal. | I29: Portal Dependent | J29: =IFERROR(INDEX(AVAILABILITY_MASTER!$C$4:$C$10,MATCH(I29,AVAILABILITY_MASTER!$A$4:$A$10,0)),"To Be Confirmed") -> Depends on Portal – Confirm at Shop | K29: Depends | L29: Portal Dependent | M29: =IFERROR(INDEX(SERVICE_DOCUMENTS!$S$4:$S$1000,MATCH(A29,SERVICE_DOCUMENTS!$A$4:$A$1000,0))&"","") -> ✓ Aadhaar Card ✓ Aadhaar-Linked Mobile Number | N29: =IFERROR(INDEX(SERVICE_DOCUMENTS!$T$4:$T$1000,MATCH(A29,SERVICE_DOCUMENTS!$A$4:$A$1000,0))&"","") | O29: Aadhaar holders with a mobile number linked to Aadhaar. | P29: Step 1 → Bring your Aadhaar number and the mobile number linked with Aadhaar. Step 2 → Operator opens the UIDAI service for 'Aadhaar Download Assistance (e-Aadhaar)'. Step 3 → OTP is sent to your linked mobile and entered. Step 4 → Service is completed and the result is downloaded / shown to you. Step 5 → Pay the assistance charge. | Q29: 15–30 Minutes | R29: To Verify | S29: To Verify | T29: =IF(AND(OR(ISNUMBER(R29),R29="N/A"),OR(ISNUMBER(S29),S29="N/A"),OR(ISNUMBER(R29),ISNUMBER(S29))),N(R29)+N(S29),"To Verify") -> To Verify | U29: To Verify | V29: No | W29: Depends on Service | X29: Portal Dependent | Y29: Yes | Z29: UIDAI portal / mAadhaar | AA29: Depends | AB29: Yes | AC29: To Verify | AD29: To Verify | AE29: To Verify | AF29: To Verify | AG29: To Verify | AH29: No | AI29: No | AJ29: No | AK29: No | AL29: Aadhaar Centre | AM29: Download, Print & Status | AN29: =BA29&", "&AZ29 -> Aadhaar Download Assistance (e-Aadhaar), Aadhaar Centre, Devmobile Stores, आधार डाउनलोड सहायता (e-Aadhaar), आधार सेंटर, सेवा | AO29: aadhaar-download-assistance-e-aadhaar | AP29: 🖨️ | AQ29: 260 | AR29: Q1: What if my mobile is not linked? A1: Some online services need OTP; the mobile must first be updated at an Aadhaar Centre. | AS29: Portal availability and OTP delivery depend on UIDAI. | AT29: Fees, documents and processing time are subject to change as per government / bank / portal rules. Final charges are confirmed at the shop before the service starts. | AV29: To Verify | AW29: Needs registered mobile OTP or biometric route as per UIDAI portal | AX29: Aadhaar Download Assistance (e-Aadhaar) Service | Devmobile Stores | AY29: Aadhaar Download Assistance (e-Aadhaar) (आधार डाउनलोड सहायता (e-Aadhaar)) at Devmobile Stores and Common Service Center & Aadhaar Centre. Check required documents, charges and process before you visit. | AZ29: आधार डाउनलोड सहायता (e-Aadhaar), आधार सेंटर, सेवा | BA29: Aadhaar Download Assistance (e-Aadhaar), Aadhaar Centre, Devmobile Stores | BC29: =IFERROR(INDEX(CATEGORY_MASTER!$C$4:$C$30,MATCH(B29,CATEGORY_MASTER!$A$4:$A$30,0)),"") -> 🪪 | BD29: ="/services/"&AO29 -> /services/aadhaar-download-assistance-e-aadhaar | BE29: =IF(AND(AH29="Yes",AG29="Active",I29<>"Not Available"),"LIVE","HIDDEN") -> HIDDEN | BF29: In-person assistance at the shop • Help checking your documents • Receipt / acknowledgement where applicable | BG29: Check Documents | BH29: =B29&"|"&COUNTIF($B$4:B29,B29) -> Aadhaar Centre|26 | BI29: =IF(AND(AI29="Yes",BE29="LIVE"),COUNTIFS($AI$4:AI29,"Yes",$BE$4:BE29,"LIVE"),"") | BJ29: =IF(AND(AJ29="Yes",BE29="LIVE"),COUNTIFS($AJ$4:AJ29,"Yes",$BE$4:BE29,"LIVE"),"") | BK29: =IF(AND(AK29="Yes",BE29="LIVE"),COUNTIFS($AK$4:AK29,"Yes",$BE$4:BE29,"LIVE"),"") | BL29: =IF(I29="To Verify",COUNTIF($I$4:I29,"To Verify"),"")
A30: AAD-027 | B30: Aadhaar Centre | C30: Aadhaar Services | D30: Download, Print & Status | E30: Masked Aadhaar Download | F30: मास्क्ड आधार डाउनलोड | G30: Get Masked Aadhaar Download done at our Aadhaar Centre. | H30: Assistance with masked aadhaar download through the UIDAI portal. | I30: Portal Dependent | J30: =IFERROR(INDEX(AVAILABILITY_MASTER!$C$4:$C$10,MATCH(I30,AVAILABILITY_MASTER!$A$4:$A$10,0)),"To Be Confirmed") -> Depends on Portal – Confirm at Shop | K30: Depends | L30: Portal Dependent | M30: =IFERROR(INDEX(SERVICE_DOCUMENTS!$S$4:$S$1000,MATCH(A30,SERVICE_DOCUMENTS!$A$4:$A$1000,0))&"","") -> ✓ Aadhaar Card ✓ Aadhaar-Linked Mobile Number | N30: =IFERROR(INDEX(SERVICE_DOCUMENTS!$T$4:$T$1000,MATCH(A30,SERVICE_DOCUMENTS!$A$4:$A$1000,0))&"","") | O30: Aadhaar holders with a mobile number linked to Aadhaar. | P30: Step 1 → Bring your Aadhaar number and the mobile number linked with Aadhaar. Step 2 → Operator opens the UIDAI service for 'Masked Aadhaar Download'. Step 3 → OTP is sent to your linked mobile and entered. Step 4 → Service is completed and the result is downloaded / shown to you. Step 5 → Pay the assistance charge. | Q30: 15–30 Minutes | R30: To Verify | S30: To Verify | T30: =IF(AND(OR(ISNUMBER(R30),R30="N/A"),OR(ISNUMBER(S30),S30="N/A"),OR(ISNUMBER(R30),ISNUMBER(S30))),N(R30)+N(S30),"To Verify") -> To Verify | U30: To Verify | V30: No | W30: Depends on Service | X30: Portal Dependent | Y30: Yes | Z30: UIDAI portal / mAadhaar | AA30: Depends | AB30: Yes | AC30: To Verify | AD30: To Verify | AE30: To Verify | AF30: To Verify | AG30: To Verify | AH30: No | AI30: No | AJ30: No | AK30: No | AL30: Aadhaar Centre | AM30: Download, Print & Status | AN30: =BA30&", "&AZ30 -> Masked Aadhaar Download, Aadhaar Centre, Devmobile Stores, मास्क्ड आधार डाउनलोड, आधार सेंटर, सेवा | AO30: masked-aadhaar-download | AP30: 🖨️ | AQ30: 270 | AR30: Q1: What if my mobile is not linked? A1: Some online services need OTP; the mobile must first be updated at an Aadhaar Centre. | AS30: Portal availability and OTP delivery depend on UIDAI. | AT30: Fees, documents and processing time are subject to change as per government / bank / portal rules. Final charges are confirmed at the shop before the service starts. | AV30: To Verify | AX30: Masked Aadhaar Download Service | Devmobile Stores | AY30: Masked Aadhaar Download (मास्क्ड आधार डाउनलोड) at Devmobile Stores and Common Service Center & Aadhaar Centre. Check required documents, charges and process before you visit. | AZ30: मास्क्ड आधार डाउनलोड, आधार सेंटर, सेवा | BA30: Masked Aadhaar Download, Aadhaar Centre, Devmobile Stores | BC30: =IFERROR(INDEX(CATEGORY_MASTER!$C$4:$C$30,MATCH(B30,CATEGORY_MASTER!$A$4:$A$30,0)),"") -> 🪪 | BD30: ="/services/"&AO30 -> /services/masked-aadhaar-download | BE30: =IF(AND(AH30="Yes",AG30="Active",I30<>"Not Available"),"LIVE","HIDDEN") -> HIDDEN | BF30: In-person assistance at the shop • Help checking your documents • Receipt / acknowledgement where applicable | BG30: Check Documents | BH30: =B30&"|"&COUNTIF($B$4:B30,B30) -> Aadhaar Centre|27 | BI30: =IF(AND(AI30="Yes",BE30="LIVE"),COUNTIFS($AI$4:AI30,"Yes",$BE$4:BE30,"LIVE"),"") | BJ30: =IF(AND(AJ30="Yes",BE30="LIVE"),COUNTIFS($AJ$4:AJ30,"Yes",$BE$4:BE30,"LIVE"),"") | BK30: =IF(AND(AK30="Yes",BE30="LIVE"),COUNTIFS($AK$4:AK30,"Yes",$BE$4:BE30,"LIVE"),"") | BL30: =IF(I30="To Verify",COUNTIF($I$4:I30,"To Verify"),"")
A31: AAD-028 | B31: Aadhaar Centre | C31: Aadhaar Services | D31: Download, Print & Status | E31: Aadhaar Print (Paper – Colour / B&W Printout) | F31: आधार प्रिंट (पेपर – रंगीन / सादा) | G31: Get Aadhaar Print (Paper – Colour / B&W Printout) done at our Aadhaar Centre. | H31: Printout of your e-Aadhaar in colour or black & white. | I31: Available | J31: =IFERROR(INDEX(AVAILABILITY_MASTER!$C$4:$C$10,MATCH(I31,AVAILABILITY_MASTER!$A$4:$A$10,0)),"To Be Confirmed") -> Available | K31: No | L31: Not Applicable | M31: =IFERROR(INDEX(SERVICE_DOCUMENTS!$S$4:$S$1000,MATCH(A31,SERVICE_DOCUMENTS!$A$4:$A$1000,0))&"","") -> ✓ Aadhaar Card | N31: =IFERROR(INDEX(SERVICE_DOCUMENTS!$T$4:$T$1000,MATCH(A31,SERVICE_DOCUMENTS!$A$4:$A$1000,0))&"","") -> • Aadhaar-Linked Mobile Number (If Applicable) | O31: Any Aadhaar holder. | P31: Step 1 → Share your Aadhaar number (or e-Aadhaar file). Step 2 → If download is needed, OTP is sent to your linked mobile. Step 3 → e-Aadhaar is opened and printed in colour or black & white. Step 4 → Pay the print charge and collect the printout. | Q31: 5–10 Minutes | R31: N/A | S31: To Verify | T31: =IF(AND(OR(ISNUMBER(R31),R31="N/A"),OR(ISNUMBER(S31),S31="N/A"),OR(ISNUMBER(R31),ISNUMBER(S31))),N(R31)+N(S31),"To Verify") -> To Verify | U31: Shop Charge Only | V31: No | W31: Depends on Service | X31: Both | Y31: No | AA31: Yes | AB31: No | AC31: To Verify | AD31: To Verify | AE31: No | AF31: No | AG31: Active | AH31: Yes | AI31: No | AJ31: No | AK31: No | AL31: Aadhaar Centre | AM31: Download, Print & Status | AN31: =BA31&", "&AZ31 -> Aadhaar Print (Paper – Colour / B&W Printout), Aadhaar Centre, Devmobile Stores, आधार प्रिंट (पेपर – रंगीन / सादा), आधार सेंटर, सेवा | AO31: aadhaar-print-paper-colour-b-w-printout | AP31: 🖨️ | AQ31: 280 | AR31: Q1: Is the printout valid? A1: e-Aadhaar is valid as per UIDAI rules; ask if you need a masked copy. | AT31: Fees, documents and processing time are subject to change as per government / bank / portal rules. Final charges are confirmed at the shop before the service starts. | AV31: To Verify | AW31: Printing part is shop work; charge as per your Printing rate | AX31: Aadhaar Print (Paper – Colour / B&W Printout) Service | Devmobile Stores | AY31: Aadhaar Print (Paper – Colour / B&W Printout) (आधार प्रिंट (पेपर – रंगीन / सादा)) at Devmobile Stores and Common Service Center & Aadhaar Centre. Check required documents, charges and process before you visit. | AZ31: आधार प्रिंट (पेपर – रंगीन / सादा), आधार सेंटर, सेवा | BA31: Aadhaar Print (Paper – Colour / B&W Printout), Aadhaar Centre, Devmobile Stores | BC31: =IFERROR(INDEX(CATEGORY_MASTER!$C$4:$C$30,MATCH(B31,CATEGORY_MASTER!$A$4:$A$30,0)),"") -> 🪪 | BD31: ="/services/"&AO31 -> /services/aadhaar-print-paper-colour-b-w-printout | BE31: =IF(AND(AH31="Yes",AG31="Active",I31<>"Not Available"),"LIVE","HIDDEN") -> LIVE | BF31: Quick printout • Colour or B&W | BG31: Visit Shop | BH31: =B31&"|"&COUNTIF($B$4:B31,B31) -> Aadhaar Centre|28 | BI31: =IF(AND(AI31="Yes",BE31="LIVE"),COUNTIFS($AI$4:AI31,"Yes",$BE$4:BE31,"LIVE"),"") | BJ31: =IF(AND(AJ31="Yes",BE31="LIVE"),COUNTIFS($AJ$4:AJ31,"Yes",$BE$4:BE31,"LIVE"),"") | BK31: =IF(AND(AK31="Yes",BE31="LIVE"),COUNTIFS($AK$4:AK31,"Yes",$BE$4:BE31,"LIVE"),"") | BL31: =IF(I31="To Verify",COUNTIF($I$4:I31,"To Verify"),"")
A32: AAD-029 | B32: Aadhaar Centre | C32: Aadhaar Services | D32: Download, Print & Status | E32: Aadhaar PVC Card Order Assistance | F32: आधार PVC कार्ड ऑर्डर सहायता | G32: Get Aadhaar PVC Card Order Assistance done at our Aadhaar Centre. | H32: Assistance with aadhaar pvc card order assistance through the UIDAI portal. | I32: Portal Dependent | J32: =IFERROR(INDEX(AVAILABILITY_MASTER!$C$4:$C$10,MATCH(I32,AVAILABILITY_MASTER!$A$4:$A$10,0)),"To Be Confirmed") -> Depends on Portal – Confirm at Shop | K32: Depends | L32: Portal Dependent | M32: =IFERROR(INDEX(SERVICE_DOCUMENTS!$S$4:$S$1000,MATCH(A32,SERVICE_DOCUMENTS!$A$4:$A$1000,0))&"","") -> ✓ Aadhaar Card ✓ Aadhaar-Linked Mobile Number | N32: =IFERROR(INDEX(SERVICE_DOCUMENTS!$T$4:$T$1000,MATCH(A32,SERVICE_DOCUMENTS!$A$4:$A$1000,0))&"","") | O32: Aadhaar holders with a mobile number linked to Aadhaar. | P32: Step 1 → Bring your Aadhaar number and the mobile number linked with Aadhaar. Step 2 → Operator opens the UIDAI service for 'Aadhaar PVC Card Order Assistance'. Step 3 → OTP is sent to your linked mobile and entered. Step 4 → Service is completed and the result is downloaded / shown to you. Step 5 → Pay the assistance charge. | Q32: 15–30 Minutes | R32: To Verify | S32: To Verify | T32: =IF(AND(OR(ISNUMBER(R32),R32="N/A"),OR(ISNUMBER(S32),S32="N/A"),OR(ISNUMBER(R32),ISNUMBER(S32))),N(R32)+N(S32),"To Verify") -> To Verify | U32: To Verify | V32: No | W32: Depends on Service | X32: Portal Dependent | Y32: Yes | Z32: UIDAI portal / mAadhaar | AA32: Depends | AB32: Yes | AC32: To Verify | AD32: To Verify | AE32: To Verify | AF32: To Verify | AG32: To Verify | AH32: No | AI32: No | AJ32: No | AK32: No | AL32: Aadhaar Centre | AM32: Download, Print & Status | AN32: =BA32&", "&AZ32 -> Aadhaar PVC Card Order Assistance, Aadhaar Centre, Devmobile Stores, आधार PVC कार्ड ऑर्डर सहायता, आधार सेंटर, सेवा | AO32: aadhaar-pvc-card-order-assistance | AP32: 🖨️ | AQ32: 290 | AR32: Q1: What if my mobile is not linked? A1: Some online services need OTP; the mobile must first be updated at an Aadhaar Centre. | AS32: Portal availability and OTP delivery depend on UIDAI. | AT32: Fees, documents and processing time are subject to change as per government / bank / portal rules. Final charges are confirmed at the shop before the service starts. | AV32: To Verify | AW32: Fee is paid to UIDAI on portal; verify current amount | AX32: Aadhaar PVC Card Order Assistance Service | Devmobile Stores | AY32: Aadhaar PVC Card Order Assistance (आधार PVC कार्ड ऑर्डर सहायता) at Devmobile Stores and Common Service Center & Aadhaar Centre. Check required documents, charges and process before you visit. | AZ32: आधार PVC कार्ड ऑर्डर सहायता, आधार सेंटर, सेवा | BA32: Aadhaar PVC Card Order Assistance, Aadhaar Centre, Devmobile Stores | BC32: =IFERROR(INDEX(CATEGORY_MASTER!$C$4:$C$30,MATCH(B32,CATEGORY_MASTER!$A$4:$A$30,0)),"") -> 🪪 | BD32: ="/services/"&AO32 -> /services/aadhaar-pvc-card-order-assistance | BE32: =IF(AND(AH32="Yes",AG32="Active",I32<>"Not Available"),"LIVE","HIDDEN") -> HIDDEN | BF32: In-person assistance at the shop • Help checking your documents • Receipt / acknowledgement where applicable | BG32: Check Documents | BH32: =B32&"|"&COUNTIF($B$4:B32,B32) -> Aadhaar Centre|29 | BI32: =IF(AND(AI32="Yes",BE32="LIVE"),COUNTIFS($AI$4:AI32,"Yes",$BE$4:BE32,"LIVE"),"") | BJ32: =IF(AND(AJ32="Yes",BE32="LIVE"),COUNTIFS($AJ$4:AJ32,"Yes",$BE$4:BE32,"LIVE"),"") | BK32: =IF(AND(AK32="Yes",BE32="LIVE"),COUNTIFS($AK$4:AK32,"Yes",$BE$4:BE32,"LIVE"),"") | BL32: =IF(I32="To Verify",COUNTIF($I$4:I32,"To Verify"),"")
A33: AAD-030 | B33: Aadhaar Centre | C33: Aadhaar Services | D33: Download, Print & Status | E33: Aadhaar Enrolment Status Check (EID) | F33: आधार नामांकन स्थिति जाँच (EID) | G33: Get Aadhaar Enrolment Status Check (EID) done at our Aadhaar Centre. | H33: Aadhaar Enrolment Status Check (EID) using the UIDAI portal. | I33: Portal Dependent | J33: =IFERROR(INDEX(AVAILABILITY_MASTER!$C$4:$C$10,MATCH(I33,AVAILABILITY_MASTER!$A$4:$A$10,0)),"To Be Confirmed") -> Depends on Portal – Confirm at Shop | K33: Depends | L33: Portal Dependent | M33: =IFERROR(INDEX(SERVICE_DOCUMENTS!$S$4:$S$1000,MATCH(A33,SERVICE_DOCUMENTS!$A$4:$A$1000,0))&"","") -> ✓ Enrolment / Acknowledgement Number | N33: =IFERROR(INDEX(SERVICE_DOCUMENTS!$T$4:$T$1000,MATCH(A33,SERVICE_DOCUMENTS!$A$4:$A$1000,0))&"","") -> • Aadhaar-Linked Mobile Number (If Applicable) | O33: Anyone with an EID / URN slip. | P33: Step 1 → Share the enrolment (EID) or update (URN) number from your slip. Step 2 → Operator checks the status on the UIDAI portal. Step 3 → Result is shown or printed for you. | Q33: 5–10 Minutes | R33: To Verify | S33: To Verify | T33: =IF(AND(OR(ISNUMBER(R33),R33="N/A"),OR(ISNUMBER(S33),S33="N/A"),OR(ISNUMBER(R33),ISNUMBER(S33))),N(R33)+N(S33),"To Verify") -> To Verify | U33: To Verify | V33: No | W33: Depends on Service | X33: Portal Dependent | Y33: Yes | Z33: UIDAI portal | AA33: Depends | AB33: Yes | AC33: To Verify | AD33: To Verify | AE33: To Verify | AF33: To Verify | AG33: To Verify | AH33: No | AI33: No | AJ33: No | AK33: No | AL33: Aadhaar Centre | AM33: Download, Print & Status | AN33: =BA33&", "&AZ33 -> Aadhaar Enrolment Status Check (EID), Aadhaar Centre, Devmobile Stores, आधार नामांकन स्थिति जाँच (EID), आधार सेंटर, सेवा | AO33: aadhaar-enrolment-status-check-eid | AP33: 🖨️ | AQ33: 300 | AR33: Q1: Where can I check the current charges? A1: Charges are confirmed at the shop and may change as per government / bank rules. | AS33: Please confirm availability with the shop before visiting. | AT33: Fees, documents and processing time are subject to change as per government / bank / portal rules. Final charges are confirmed at the shop before the service starts. | AV33: To Verify | AX33: Aadhaar Enrolment Status Check (EID) Service | Devmobile Stores | AY33: Aadhaar Enrolment Status Check (EID) (आधार नामांकन स्थिति जाँच (EID)) at Devmobile Stores and Common Service Center & Aadhaar Centre. Check required documents, charges and process before you visit. | AZ33: आधार नामांकन स्थिति जाँच (EID), आधार सेंटर, सेवा | BA33: Aadhaar Enrolment Status Check (EID), Aadhaar Centre, Devmobile Stores | BC33: =IFERROR(INDEX(CATEGORY_MASTER!$C$4:$C$30,MATCH(B33,CATEGORY_MASTER!$A$4:$A$30,0)),"") -> 🪪 | BD33: ="/services/"&AO33 -> /services/aadhaar-enrolment-status-check-eid | BE33: =IF(AND(AH33="Yes",AG33="Active",I33<>"Not Available"),"LIVE","HIDDEN") -> HIDDEN | BF33: In-person assistance at the shop • Help checking your documents • Receipt / acknowledgement where applicable | BG33: Check Documents | BH33: =B33&"|"&COUNTIF($B$4:B33,B33) -> Aadhaar Centre|30 | BI33: =IF(AND(AI33="Yes",BE33="LIVE"),COUNTIFS($AI$4:AI33,"Yes",$BE$4:BE33,"LIVE"),"") | BJ33: =IF(AND(AJ33="Yes",BE33="LIVE"),COUNTIFS($AJ$4:AJ33,"Yes",$BE$4:BE33,"LIVE"),"") | BK33: =IF(AND(AK33="Yes",BE33="LIVE"),COUNTIFS($AK$4:AK33,"Yes",$BE$4:BE33,"LIVE"),"") | BL33: =IF(I33="To Verify",COUNTIF($I$4:I33,"To Verify"),"")
A34: AAD-031 | B34: Aadhaar Centre | C34: Aadhaar Services | D34: Download, Print & Status | E34: Aadhaar Update Request Status Check (URN) | F34: आधार अपडेट रिक्वेस्ट स्थिति जाँच (URN) | G34: Get Aadhaar Update Request Status Check (URN) done at our Aadhaar Centre. | H34: Aadhaar Update Request Status Check (URN) using the UIDAI portal. | I34: Portal Dependent | J34: =IFERROR(INDEX(AVAILABILITY_MASTER!$C$4:$C$10,MATCH(I34,AVAILABILITY_MASTER!$A$4:$A$10,0)),"To Be Confirmed") -> Depends on Portal – Confirm at Shop | K34: Depends | L34: Portal Dependent | M34: =IFERROR(INDEX(SERVICE_DOCUMENTS!$S$4:$S$1000,MATCH(A34,SERVICE_DOCUMENTS!$A$4:$A$1000,0))&"","") -> ✓ Enrolment / Acknowledgement Number | N34: =IFERROR(INDEX(SERVICE_DOCUMENTS!$T$4:$T$1000,MATCH(A34,SERVICE_DOCUMENTS!$A$4:$A$1000,0))&"","") -> • Aadhaar-Linked Mobile Number (If Applicable) | O34: Anyone with an EID / URN slip. | P34: Step 1 → Share the enrolment (EID) or update (URN) number from your slip. Step 2 → Operator checks the status on the UIDAI portal. Step 3 → Result is shown or printed for you. | Q34: 5–10 Minutes | R34: To Verify | S34: To Verify | T34: =IF(AND(OR(ISNUMBER(R34),R34="N/A"),OR(ISNUMBER(S34),S34="N/A"),OR(ISNUMBER(R34),ISNUMBER(S34))),N(R34)+N(S34),"To Verify") -> To Verify | U34: To Verify | V34: No | W34: Depends on Service | X34: Portal Dependent | Y34: Yes | Z34: UIDAI portal | AA34: Depends | AB34: Yes | AC34: To Verify | AD34: To Verify | AE34: To Verify | AF34: To Verify | AG34: To Verify | AH34: No | AI34: No | AJ34: No | AK34: No | AL34: Aadhaar Centre | AM34: Download, Print & Status | AN34: =BA34&", "&AZ34 -> Aadhaar Update Request Status Check (URN), Aadhaar Centre, Devmobile Stores, आधार अपडेट रिक्वेस्ट स्थिति जाँच (URN), आधार सेंटर, सेवा | AO34: aadhaar-update-request-status-check-urn | AP34: 🖨️ | AQ34: 310 | AR34: Q1: Where can I check the current charges? A1: Charges are confirmed at the shop and may change as per government / bank rules. | AS34: Please confirm availability with the shop before visiting. | AT34: Fees, documents and processing time are subject to change as per government / bank / portal rules. Final charges are confirmed at the shop before the service starts. | AV34: To Verify | AX34: Aadhaar Update Request Status Check (URN) Service | Devmobile Stores | AY34: Aadhaar Update Request Status Check (URN) (आधार अपडेट रिक्वेस्ट स्थिति जाँच (URN)) at Devmobile Stores and Common Service Center & Aadhaar Centre. Check required documents, charges and process before you visit. | AZ34: आधार अपडेट रिक्वेस्ट स्थिति जाँच (URN), आधार सेंटर, सेवा | BA34: Aadhaar Update Request Status Check (URN), Aadhaar Centre, Devmobile Stores | BC34: =IFERROR(INDEX(CATEGORY_MASTER!$C$4:$C$30,MATCH(B34,CATEGORY_MASTER!$A$4:$A$30,0)),"") -> 🪪 | BD34: ="/services/"&AO34 -> /services/aadhaar-update-request-status-check-urn | BE34: =IF(AND(AH34="Yes",AG34="Active",I34<>"Not Available"),"LIVE","HIDDEN") -> HIDDEN | BF34: In-person assistance at the shop • Help checking your documents • Receipt / acknowledgement where applicable | BG34: Check Documents | BH34: =B34&"|"&COUNTIF($B$4:B34,B34) -> Aadhaar Centre|31 | BI34: =IF(AND(AI34="Yes",BE34="LIVE"),COUNTIFS($AI$4:AI34,"Yes",$BE$4:BE34,"LIVE"),"") | BJ34: =IF(AND(AJ34="Yes",BE34="LIVE"),COUNTIFS($AJ$4:AJ34,"Yes",$BE$4:BE34,"LIVE"),"") | BK34: =IF(AND(AK34="Yes",BE34="LIVE"),COUNTIFS($AK$4:AK34,"Yes",$BE$4:BE34,"LIVE"),"") | BL34: =IF(I34="To Verify",COUNTIF($I$4:I34,"To Verify"),"")
A35: AAD-032 | B35: Aadhaar Centre | C35: Aadhaar Services | D35: Download, Print & Status | E35: Aadhaar Lost UID / EID Retrieval Assistance | F35: खोया आधार नंबर / EID पुनः प्राप्ति सहायता | G35: Get Aadhaar Lost UID / EID Retrieval Assistance done at our Aadhaar Centre. | H35: Assistance with aadhaar lost uid / eid retrieval assistance through the UIDAI portal. | I35: Portal Dependent | J35: =IFERROR(INDEX(AVAILABILITY_MASTER!$C$4:$C$10,MATCH(I35,AVAILABILITY_MASTER!$A$4:$A$10,0)),"To Be Confirmed") -> Depends on Portal – Confirm at Shop | K35: Depends | L35: Portal Dependent | M35: =IFERROR(INDEX(SERVICE_DOCUMENTS!$S$4:$S$1000,MATCH(A35,SERVICE_DOCUMENTS!$A$4:$A$1000,0))&"","") -> ✓ Aadhaar Card ✓ Aadhaar-Linked Mobile Number | N35: =IFERROR(INDEX(SERVICE_DOCUMENTS!$T$4:$T$1000,MATCH(A35,SERVICE_DOCUMENTS!$A$4:$A$1000,0))&"","") | O35: Aadhaar holders with a mobile number linked to Aadhaar. | P35: Step 1 → Bring your Aadhaar number and the mobile number linked with Aadhaar. Step 2 → Operator opens the UIDAI service for 'Aadhaar Lost UID / EID Retrieval Assistance'. Step 3 → OTP is sent to your linked mobile and entered. Step 4 → Service is completed and the result is downloaded / shown to you. Step 5 → Pay the assistance charge. | Q35: 15–30 Minutes | R35: To Verify | S35: To Verify | T35: =IF(AND(OR(ISNUMBER(R35),R35="N/A"),OR(ISNUMBER(S35),S35="N/A"),OR(ISNUMBER(R35),ISNUMBER(S35))),N(R35)+N(S35),"To Verify") -> To Verify | U35: To Verify | V35: No | W35: Depends on Service | X35: Portal Dependent | Y35: Yes | Z35: UIDAI portal / mAadhaar | AA35: Depends | AB35: Yes | AC35: To Verify | AD35: To Verify | AE35: To Verify | AF35: To Verify | AG35: To Verify | AH35: No | AI35: No | AJ35: No | AK35: No | AL35: Aadhaar Centre | AM35: Download, Print & Status | AN35: =BA35&", "&AZ35 -> Aadhaar Lost UID / EID Retrieval Assistance, Aadhaar Centre, Devmobile Stores, खोया आधार नंबर / EID पुनः प्राप्ति सहायता, आधार सेंटर, सेवा | AO35: aadhaar-lost-uid-eid-retrieval-assistance | AP35: 🖨️ | AQ35: 320 | AR35: Q1: What if my mobile is not linked? A1: Some online services need OTP; the mobile must first be updated at an Aadhaar Centre. | AS35: Portal availability and OTP delivery depend on UIDAI. | AT35: Fees, documents and processing time are subject to change as per government / bank / portal rules. Final charges are confirmed at the shop before the service starts. | AV35: To Verify | AW35: Needs registered mobile or email | AX35: Aadhaar Lost UID / EID Retrieval Assistance Service | Devmobile Stores | AY35: Aadhaar Lost UID / EID Retrieval Assistance (खोया आधार नंबर / EID पुनः प्राप्ति सहायता) at Devmobile Stores and Common Service Center & Aadhaar Centre. Check required documents, charges and process before you visit. | AZ35: खोया आधार नंबर / EID पुनः प्राप्ति सहायता, आधार सेंटर, सेवा | BA35: Aadhaar Lost UID / EID Retrieval Assistance, Aadhaar Centre, Devmobile Stores | BC35: =IFERROR(INDEX(CATEGORY_MASTER!$C$4:$C$30,MATCH(B35,CATEGORY_MASTER!$A$4:$A$30,0)),"") -> 🪪 | BD35: ="/services/"&AO35 -> /services/aadhaar-lost-uid-eid-retrieval-assistance | BE35: =IF(AND(AH35="Yes",AG35="Active",I35<>"Not Available"),"LIVE","HIDDEN") -> HIDDEN | BF35: In-person assistance at the shop • Help checking your documents • Receipt / acknowledgement where applicable | BG35: Check Documents | BH35: =B35&"|"&COUNTIF($B$4:B35,B35) -> Aadhaar Centre|32 | BI35: =IF(AND(AI35="Yes",BE35="LIVE"),COUNTIFS($AI$4:AI35,"Yes",$BE$4:BE35,"LIVE"),"") | BJ35: =IF(AND(AJ35="Yes",BE35="LIVE"),COUNTIFS($AJ$4:AJ35,"Yes",$BE$4:BE35,"LIVE"),"") | BK35: =IF(AND(AK35="Yes",BE35="LIVE"),COUNTIFS($AK$4:AK35,"Yes",$BE$4:BE35,"LIVE"),"") | BL35: =IF(I35="To Verify",COUNTIF($I$4:I35,"To Verify"),"")
A36: AAD-033 | B36: Aadhaar Centre | C36: Aadhaar Services | D36: Download, Print & Status | E36: Aadhaar Virtual ID (VID) Generation Assistance | F36: आधार वर्चुअल ID (VID) निर्माण सहायता | G36: Get Aadhaar Virtual ID (VID) Generation Assistance done at our Aadhaar Centre. | H36: Assistance with aadhaar virtual id (vid) generation assistance through the UIDAI portal. | I36: Portal Dependent | J36: =IFERROR(INDEX(AVAILABILITY_MASTER!$C$4:$C$10,MATCH(I36,AVAILABILITY_MASTER!$A$4:$A$10,0)),"To Be Confirmed") -> Depends on Portal – Confirm at Shop | K36: Depends | L36: Portal Dependent | M36: =IFERROR(INDEX(SERVICE_DOCUMENTS!$S$4:$S$1000,MATCH(A36,SERVICE_DOCUMENTS!$A$4:$A$1000,0))&"","") -> ✓ Aadhaar Card ✓ Aadhaar-Linked Mobile Number | N36: =IFERROR(INDEX(SERVICE_DOCUMENTS!$T$4:$T$1000,MATCH(A36,SERVICE_DOCUMENTS!$A$4:$A$1000,0))&"","") | O36: Aadhaar holders with a mobile number linked to Aadhaar. | P36: Step 1 → Bring your Aadhaar number and the mobile number linked with Aadhaar. Step 2 → Operator opens the UIDAI service for 'Aadhaar Virtual ID (VID) Generation Assistance'. Step 3 → OTP is sent to your linked mobile and entered. Step 4 → Service is completed and the result is downloaded / shown to you. Step 5 → Pay the assistance charge. | Q36: 15–30 Minutes | R36: To Verify | S36: To Verify | T36: =IF(AND(OR(ISNUMBER(R36),R36="N/A"),OR(ISNUMBER(S36),S36="N/A"),OR(ISNUMBER(R36),ISNUMBER(S36))),N(R36)+N(S36),"To Verify") -> To Verify | U36: To Verify | V36: No | W36: Depends on Service | X36: Portal Dependent | Y36: Yes | Z36: UIDAI portal / mAadhaar | AA36: Depends | AB36: Yes | AC36: To Verify | AD36: To Verify | AE36: To Verify | AF36: To Verify | AG36: To Verify | AH36: No | AI36: No | AJ36: No | AK36: No | AL36: Aadhaar Centre | AM36: Download, Print & Status | AN36: =BA36&", "&AZ36 -> Aadhaar Virtual ID (VID) Generation Assistance, Aadhaar Centre, Devmobile Stores, आधार वर्चुअल ID (VID) निर्माण सहायता, आधार सेंटर, सेवा | AO36: aadhaar-virtual-id-vid-generation-assistance | AP36: 🖨️ | AQ36: 330 | AR36: Q1: What if my mobile is not linked? A1: Some online services need OTP; the mobile must first be updated at an Aadhaar Centre. | AS36: Portal availability and OTP delivery depend on UIDAI. | AT36: Fees, documents and processing time are subject to change as per government / bank / portal rules. Final charges are confirmed at the shop before the service starts. | AV36: To Verify | AX36: Aadhaar Virtual ID (VID) Generation Assistance Service | Devmobile Stores | AY36: Aadhaar Virtual ID (VID) Generation Assistance (आधार वर्चुअल ID (VID) निर्माण सहायता) at Devmobile Stores and Common Service Center & Aadhaar Centre. Check required documents, charges and process before you visit. | AZ36: आधार वर्चुअल ID (VID) निर्माण सहायता, आधार सेंटर, सेवा | BA36: Aadhaar Virtual ID (VID) Generation Assistance, Aadhaar Centre, Devmobile Stores | BC36: =IFERROR(INDEX(CATEGORY_MASTER!$C$4:$C$30,MATCH(B36,CATEGORY_MASTER!$A$4:$A$30,0)),"") -> 🪪 | BD36: ="/services/"&AO36 -> /services/aadhaar-virtual-id-vid-generation-assistance | BE36: =IF(AND(AH36="Yes",AG36="Active",I36<>"Not Available"),"LIVE","HIDDEN") -> HIDDEN | BF36: In-person assistance at the shop • Help checking your documents • Receipt / acknowledgement where applicable | BG36: Check Documents | BH36: =B36&"|"&COUNTIF($B$4:B36,B36) -> Aadhaar Centre|33 | BI36: =IF(AND(AI36="Yes",BE36="LIVE"),COUNTIFS($AI$4:AI36,"Yes",$BE$4:BE36,"LIVE"),"") | BJ36: =IF(AND(AJ36="Yes",BE36="LIVE"),COUNTIFS($AJ$4:AJ36,"Yes",$BE$4:BE36,"LIVE"),"") | BK36: =IF(AND(AK36="Yes",BE36="LIVE"),COUNTIFS($AK$4:AK36,"Yes",$BE$4:BE36,"LIVE"),"") | BL36: =IF(I36="To Verify",COUNTIF($I$4:I36,"To Verify"),"")
A37: AAD-034 | B37: Aadhaar Centre | C37: Aadhaar Services | D37: Download, Print & Status | E37: Aadhaar Lock / Unlock Assistance | F37: आधार लॉक / अनलॉक सहायता | G37: Get Aadhaar Lock / Unlock Assistance done at our Aadhaar Centre. | H37: Assistance with aadhaar lock / unlock assistance through the UIDAI portal. | I37: Portal Dependent | J37: =IFERROR(INDEX(AVAILABILITY_MASTER!$C$4:$C$10,MATCH(I37,AVAILABILITY_MASTER!$A$4:$A$10,0)),"To Be Confirmed") -> Depends on Portal – Confirm at Shop | K37: Depends | L37: Portal Dependent | M37: =IFERROR(INDEX(SERVICE_DOCUMENTS!$S$4:$S$1000,MATCH(A37,SERVICE_DOCUMENTS!$A$4:$A$1000,0))&"","") -> ✓ Aadhaar Card ✓ Aadhaar-Linked Mobile Number | N37: =IFERROR(INDEX(SERVICE_DOCUMENTS!$T$4:$T$1000,MATCH(A37,SERVICE_DOCUMENTS!$A$4:$A$1000,0))&"","") | O37: Aadhaar holders with a mobile number linked to Aadhaar. | P37: Step 1 → Bring your Aadhaar number and the mobile number linked with Aadhaar. Step 2 → Operator opens the UIDAI service for 'Aadhaar Lock / Unlock Assistance'. Step 3 → OTP is sent to your linked mobile and entered. Step 4 → Service is completed and the result is downloaded / shown to you. Step 5 → Pay the assistance charge. | Q37: 15–30 Minutes | R37: To Verify | S37: To Verify | T37: =IF(AND(OR(ISNUMBER(R37),R37="N/A"),OR(ISNUMBER(S37),S37="N/A"),OR(ISNUMBER(R37),ISNUMBER(S37))),N(R37)+N(S37),"To Verify") -> To Verify | U37: To Verify | V37: No | W37: Depends on Service | X37: Portal Dependent | Y37: Yes | Z37: UIDAI portal / mAadhaar | AA37: Depends | AB37: Yes | AC37: To Verify | AD37: To Verify | AE37: To Verify | AF37: To Verify | AG37: To Verify | AH37: No | AI37: No | AJ37: No | AK37: No | AL37: Aadhaar Centre | AM37: Download, Print & Status | AN37: =BA37&", "&AZ37 -> Aadhaar Lock / Unlock Assistance, Aadhaar Centre, Devmobile Stores, आधार लॉक / अनलॉक सहायता, आधार सेंटर, सेवा | AO37: aadhaar-lock-unlock-assistance | AP37: 🖨️ | AQ37: 340 | AR37: Q1: What if my mobile is not linked? A1: Some online services need OTP; the mobile must first be updated at an Aadhaar Centre. | AS37: Portal availability and OTP delivery depend on UIDAI. | AT37: Fees, documents and processing time are subject to change as per government / bank / portal rules. Final charges are confirmed at the shop before the service starts. | AV37: To Verify | AX37: Aadhaar Lock / Unlock Assistance Service | Devmobile Stores | AY37: Aadhaar Lock / Unlock Assistance (आधार लॉक / अनलॉक सहायता) at Devmobile Stores and Common Service Center & Aadhaar Centre. Check required documents, charges and process before you visit. | AZ37: आधार लॉक / अनलॉक सहायता, आधार सेंटर, सेवा | BA37: Aadhaar Lock / Unlock Assistance, Aadhaar Centre, Devmobile Stores | BC37: =IFERROR(INDEX(CATEGORY_MASTER!$C$4:$C$30,MATCH(B37,CATEGORY_MASTER!$A$4:$A$30,0)),"") -> 🪪 | BD37: ="/services/"&AO37 -> /services/aadhaar-lock-unlock-assistance | BE37: =IF(AND(AH37="Yes",AG37="Active",I37<>"Not Available"),"LIVE","HIDDEN") -> HIDDEN | BF37: In-person assistance at the shop • Help checking your documents • Receipt / acknowledgement where applicable | BG37: Check Documents | BH37: =B37&"|"&COUNTIF($B$4:B37,B37) -> Aadhaar Centre|34 | BI37: =IF(AND(AI37="Yes",BE37="LIVE"),COUNTIFS($AI$4:AI37,"Yes",$BE$4:BE37,"LIVE"),"") | BJ37: =IF(AND(AJ37="Yes",BE37="LIVE"),COUNTIFS($AJ$4:AJ37,"Yes",$BE$4:BE37,"LIVE"),"") | BK37: =IF(AND(AK37="Yes",BE37="LIVE"),COUNTIFS($AK$4:AK37,"Yes",$BE$4:BE37,"LIVE"),"") | BL37: =IF(I37="To Verify",COUNTIF($I$4:I37,"To Verify"),"")
A38: AAD-035 | B38: Aadhaar Centre | C38: Aadhaar Services | D38: Download, Print & Status | E38: Aadhaar Authentication History Check | F38: आधार ऑथेंटिकेशन हिस्ट्री जाँच | G38: Get Aadhaar Authentication History Check done at our Aadhaar Centre. | H38: Assistance with aadhaar authentication history check through the UIDAI portal. | I38: Portal Dependent | J38: =IFERROR(INDEX(AVAILABILITY_MASTER!$C$4:$C$10,MATCH(I38,AVAILABILITY_MASTER!$A$4:$A$10,0)),"To Be Confirmed") -> Depends on Portal – Confirm at Shop | K38: Depends | L38: Portal Dependent | M38: =IFERROR(INDEX(SERVICE_DOCUMENTS!$S$4:$S$1000,MATCH(A38,SERVICE_DOCUMENTS!$A$4:$A$1000,0))&"","") -> ✓ Aadhaar Card ✓ Aadhaar-Linked Mobile Number | N38: =IFERROR(INDEX(SERVICE_DOCUMENTS!$T$4:$T$1000,MATCH(A38,SERVICE_DOCUMENTS!$A$4:$A$1000,0))&"","") | O38: Aadhaar holders with a mobile number linked to Aadhaar. | P38: Step 1 → Bring your Aadhaar number and the mobile number linked with Aadhaar. Step 2 → Operator opens the UIDAI service for 'Aadhaar Authentication History Check'. Step 3 → OTP is sent to your linked mobile and entered. Step 4 → Service is completed and the result is downloaded / shown to you. Step 5 → Pay the assistance charge. | Q38: 15–30 Minutes | R38: To Verify | S38: To Verify | T38: =IF(AND(OR(ISNUMBER(R38),R38="N/A"),OR(ISNUMBER(S38),S38="N/A"),OR(ISNUMBER(R38),ISNUMBER(S38))),N(R38)+N(S38),"To Verify") -> To Verify | U38: To Verify | V38: No | W38: Depends on Service | X38: Portal Dependent | Y38: Yes | Z38: UIDAI portal / mAadhaar | AA38: Depends | AB38: Yes | AC38: To Verify | AD38: To Verify | AE38: To Verify | AF38: To Verify | AG38: To Verify | AH38: No | AI38: No | AJ38: No | AK38: No | AL38: Aadhaar Centre | AM38: Download, Print & Status | AN38: =BA38&", "&AZ38 -> Aadhaar Authentication History Check, Aadhaar Centre, Devmobile Stores, आधार ऑथेंटिकेशन हिस्ट्री जाँच, आधार सेंटर, सेवा | AO38: aadhaar-authentication-history-check | AP38: 🖨️ | AQ38: 350 | AR38: Q1: What if my mobile is not linked? A1: Some online services need OTP; the mobile must first be updated at an Aadhaar Centre. | AS38: Portal availability and OTP delivery depend on UIDAI. | AT38: Fees, documents and processing time are subject to change as per government / bank / portal rules. Final charges are confirmed at the shop before the service starts. | AV38: To Verify | AX38: Aadhaar Authentication History Check Service | Devmobile Stores | AY38: Aadhaar Authentication History Check (आधार ऑथेंटिकेशन हिस्ट्री जाँच) at Devmobile Stores and Common Service Center & Aadhaar Centre. Check required documents, charges and process before you visit. | AZ38: आधार ऑथेंटिकेशन हिस्ट्री जाँच, आधार सेंटर, सेवा | BA38: Aadhaar Authentication History Check, Aadhaar Centre, Devmobile Stores | BC38: =IFERROR(INDEX(CATEGORY_MASTER!$C$4:$C$30,MATCH(B38,CATEGORY_MASTER!$A$4:$A$30,0)),"") -> 🪪 | BD38: ="/services/"&AO38 -> /services/aadhaar-authentication-history-check | BE38: =IF(AND(AH38="Yes",AG38="Active",I38<>"Not Available"),"LIVE","HIDDEN") -> HIDDEN | BF38: In-person assistance at the shop • Help checking your documents • Receipt / acknowledgement where applicable | BG38: Check Documents | BH38: =B38&"|"&COUNTIF($B$4:B38,B38) -> Aadhaar Centre|35 | BI38: =IF(AND(AI38="Yes",BE38="LIVE"),COUNTIFS($AI$4:AI38,"Yes",$BE$4:BE38,"LIVE"),"") | BJ38: =IF(AND(AJ38="Yes",BE38="LIVE"),COUNTIFS($AJ$4:AJ38,"Yes",$BE$4:BE38,"LIVE"),"") | BK38: =IF(AND(AK38="Yes",BE38="LIVE"),COUNTIFS($AK$4:AK38,"Yes",$BE$4:BE38,"LIVE"),"") | BL38: =IF(I38="To Verify",COUNTIF($I$4:I38,"To Verify"),"")
A39: AAD-036 | B39: Aadhaar Centre | C39: Aadhaar Services | D39: Download, Print & Status | E39: Aadhaar Mobile / Email Link Check | F39: आधार मोबाइल / ईमेल लिंक जाँच | G39: Get Aadhaar Mobile / Email Link Check done at our Aadhaar Centre. | H39: Assistance with aadhaar mobile / email link check through the UIDAI portal. | I39: Portal Dependent | J39: =IFERROR(INDEX(AVAILABILITY_MASTER!$C$4:$C$10,MATCH(I39,AVAILABILITY_MASTER!$A$4:$A$10,0)),"To Be Confirmed") -> Depends on Portal – Confirm at Shop | K39: Depends | L39: Portal Dependent | M39: =IFERROR(INDEX(SERVICE_DOCUMENTS!$S$4:$S$1000,MATCH(A39,SERVICE_DOCUMENTS!$A$4:$A$1000,0))&"","") -> ✓ Aadhaar Card ✓ Aadhaar-Linked Mobile Number | N39: =IFERROR(INDEX(SERVICE_DOCUMENTS!$T$4:$T$1000,MATCH(A39,SERVICE_DOCUMENTS!$A$4:$A$1000,0))&"","") | O39: Aadhaar holders with a mobile number linked to Aadhaar. | P39: Step 1 → Bring your Aadhaar number and the mobile number linked with Aadhaar. Step 2 → Operator opens the UIDAI service for 'Aadhaar Mobile / Email Link Check'. Step 3 → OTP is sent to your linked mobile and entered. Step 4 → Service is completed and the result is downloaded / shown to you. Step 5 → Pay the assistance charge. | Q39: 15–30 Minutes | R39: To Verify | S39: To Verify | T39: =IF(AND(OR(ISNUMBER(R39),R39="N/A"),OR(ISNUMBER(S39),S39="N/A"),OR(ISNUMBER(R39),ISNUMBER(S39))),N(R39)+N(S39),"To Verify") -> To Verify | U39: To Verify | V39: No | W39: Depends on Service | X39: Portal Dependent | Y39: Yes | Z39: UIDAI portal / mAadhaar | AA39: Depends | AB39: Yes | AC39: To Verify | AD39: To Verify | AE39: To Verify | AF39: To Verify | AG39: To Verify | AH39: No | AI39: No | AJ39: No | AK39: No | AL39: Aadhaar Centre | AM39: Download, Print & Status | AN39: =BA39&", "&AZ39 -> Aadhaar Mobile / Email Link Check, Aadhaar Centre, Devmobile Stores, आधार मोबाइल / ईमेल लिंक जाँच, आधार सेंटर, सेवा | AO39: aadhaar-mobile-email-link-check | AP39: 🖨️ | AQ39: 360 | AR39: Q1: What if my mobile is not linked? A1: Some online services need OTP; the mobile must first be updated at an Aadhaar Centre. | AS39: Portal availability and OTP delivery depend on UIDAI. | AT39: Fees, documents and processing time are subject to change as per government / bank / portal rules. Final charges are confirmed at the shop before the service starts. | AV39: To Verify | AX39: Aadhaar Mobile / Email Link Check Service | Devmobile Stores | AY39: Aadhaar Mobile / Email Link Check (आधार मोबाइल / ईमेल लिंक जाँच) at Devmobile Stores and Common Service Center & Aadhaar Centre. Check required documents, charges and process before you visit. | AZ39: आधार मोबाइल / ईमेल लिंक जाँच, आधार सेंटर, सेवा | BA39: Aadhaar Mobile / Email Link Check, Aadhaar Centre, Devmobile Stores | BC39: =IFERROR(INDEX(CATEGORY_MASTER!$C$4:$C$30,MATCH(B39,CATEGORY_MASTER!$A$4:$A$30,0)),"") -> 🪪 | BD39: ="/services/"&AO39 -> /services/aadhaar-mobile-email-link-check | BE39: =IF(AND(AH39="Yes",AG39="Active",I39<>"Not Available"),"LIVE","HIDDEN") -> HIDDEN | BF39: In-person assistance at the shop • Help checking your documents • Receipt / acknowledgement where applicable | BG39: Check Documents | BH39: =B39&"|"&COUNTIF($B$4:B39,B39) -> Aadhaar Centre|36 | BI39: =IF(AND(AI39="Yes",BE39="LIVE"),COUNTIFS($AI$4:AI39,"Yes",$BE$4:BE39,"LIVE"),"") | BJ39: =IF(AND(AJ39="Yes",BE39="LIVE"),COUNTIFS($AJ$4:AJ39,"Yes",$BE$4:BE39,"LIVE"),"") | BK39: =IF(AND(AK39="Yes",BE39="LIVE"),COUNTIFS($AK$4:AK39,"Yes",$BE$4:BE39,"LIVE"),"") | BL39: =IF(I39="To Verify",COUNTIF($I$4:I39,"To Verify"),"")
A40: AAD-037 | B40: Aadhaar Centre | C40: Aadhaar Services | D40: Download, Print & Status | E40: Aadhaar Number Verification | F40: आधार नंबर सत्यापन | G40: Get Aadhaar Number Verification done at our Aadhaar Centre. | H40: Assistance with aadhaar number verification through the UIDAI portal. | I40: Portal Dependent | J40: =IFERROR(INDEX(AVAILABILITY_MASTER!$C$4:$C$10,MATCH(I40,AVAILABILITY_MASTER!$A$4:$A$10,0)),"To Be Confirmed") -> Depends on Portal – Confirm at Shop | K40: Depends | L40: Portal Dependent | M40: =IFERROR(INDEX(SERVICE_DOCUMENTS!$S$4:$S$1000,MATCH(A40,SERVICE_DOCUMENTS!$A$4:$A$1000,0))&"","") -> ✓ Aadhaar Card ✓ Aadhaar-Linked Mobile Number | N40: =IFERROR(INDEX(SERVICE_DOCUMENTS!$T$4:$T$1000,MATCH(A40,SERVICE_DOCUMENTS!$A$4:$A$1000,0))&"","") | O40: Aadhaar holders with a mobile number linked to Aadhaar. | P40: Step 1 → Bring your Aadhaar number and the mobile number linked with Aadhaar. Step 2 → Operator opens the UIDAI service for 'Aadhaar Number Verification'. Step 3 → OTP is sent to your linked mobile and entered. Step 4 → Service is completed and the result is downloaded / shown to you. Step 5 → Pay the assistance charge. | Q40: 15–30 Minutes | R40: To Verify | S40: To Verify | T40: =IF(AND(OR(ISNUMBER(R40),R40="N/A"),OR(ISNUMBER(S40),S40="N/A"),OR(ISNUMBER(R40),ISNUMBER(S40))),N(R40)+N(S40),"To Verify") -> To Verify | U40: To Verify | V40: No | W40: Depends on Service | X40: Portal Dependent | Y40: Yes | Z40: UIDAI portal / mAadhaar | AA40: Depends | AB40: Yes | AC40: To Verify | AD40: To Verify | AE40: To Verify | AF40: To Verify | AG40: To Verify | AH40: No | AI40: No | AJ40: No | AK40: No | AL40: Aadhaar Centre | AM40: Download, Print & Status | AN40: =BA40&", "&AZ40 -> Aadhaar Number Verification, Aadhaar Centre, Devmobile Stores, आधार नंबर सत्यापन, आधार सेंटर, सेवा | AO40: aadhaar-number-verification | AP40: 🖨️ | AQ40: 370 | AR40: Q1: What if my mobile is not linked? A1: Some online services need OTP; the mobile must first be updated at an Aadhaar Centre. | AS40: Portal availability and OTP delivery depend on UIDAI. | AT40: Fees, documents and processing time are subject to change as per government / bank / portal rules. Final charges are confirmed at the shop before the service starts. | AV40: To Verify | AX40: Aadhaar Number Verification Service | Devmobile Stores | AY40: Aadhaar Number Verification (आधार नंबर सत्यापन) at Devmobile Stores and Common Service Center & Aadhaar Centre. Check required documents, charges and process before you visit. | AZ40: आधार नंबर सत्यापन, आधार सेंटर, सेवा | BA40: Aadhaar Number Verification, Aadhaar Centre, Devmobile Stores | BC40: =IFERROR(INDEX(CATEGORY_MASTER!$C$4:$C$30,MATCH(B40,CATEGORY_MASTER!$A$4:$A$30,0)),"") -> 🪪 | BD40: ="/services/"&AO40 -> /services/aadhaar-number-verification | BE40: =IF(AND(AH40="Yes",AG40="Active",I40<>"Not Available"),"LIVE","HIDDEN") -> HIDDEN | BF40: In-person assistance at the shop • Help checking your documents • Receipt / acknowledgement where applicable | BG40: Check Documents | BH40: =B40&"|"&COUNTIF($B$4:B40,B40) -> Aadhaar Centre|37 | BI40: =IF(AND(AI40="Yes",BE40="LIVE"),COUNTIFS($AI$4:AI40,"Yes",$BE$4:BE40,"LIVE"),"") | BJ40: =IF(AND(AJ40="Yes",BE40="LIVE"),COUNTIFS($AJ$4:AJ40,"Yes",$BE$4:BE40,"LIVE"),"") | BK40: =IF(AND(AK40="Yes",BE40="LIVE"),COUNTIFS($AK$4:AK40,"Yes",$BE$4:BE40,"LIVE"),"") | BL40: =IF(I40="To Verify",COUNTIF($I$4:I40,"To Verify"),"")
A41: AAD-038 | B41: Aadhaar Centre | C41: Aadhaar Services | D41: Download, Print & Status | E41: Aadhaar Offline eKYC (XML / QR) Download Assistance | F41: आधार Offline eKYC (XML / QR) डाउनलोड सहायता | G41: Get Aadhaar Offline eKYC (XML / QR) Download Assistance done at our Aadhaar Centre. | H41: Assistance with aadhaar offline ekyc (xml / qr) download assistance through the UIDAI portal. | I41: Portal Dependent | J41: =IFERROR(INDEX(AVAILABILITY_MASTER!$C$4:$C$10,MATCH(I41,AVAILABILITY_MASTER!$A$4:$A$10,0)),"To Be Confirmed") -> Depends on Portal – Confirm at Shop | K41: Depends | L41: Portal Dependent | M41: =IFERROR(INDEX(SERVICE_DOCUMENTS!$S$4:$S$1000,MATCH(A41,SERVICE_DOCUMENTS!$A$4:$A$1000,0))&"","") -> ✓ Aadhaar Card ✓ Aadhaar-Linked Mobile Number | N41: =IFERROR(INDEX(SERVICE_DOCUMENTS!$T$4:$T$1000,MATCH(A41,SERVICE_DOCUMENTS!$A$4:$A$1000,0))&"","") | O41: Aadhaar holders with a mobile number linked to Aadhaar. | P41: Step 1 → Bring your Aadhaar number and the mobile number linked with Aadhaar. Step 2 → Operator opens the UIDAI service for 'Aadhaar Offline eKYC (XML / QR) Download Assistance'. Step 3 → OTP is sent to your linked mobile and entered. Step 4 → Service is completed and the result is downloaded / shown to you. Step 5 → Pay the assistance charge. | Q41: 15–30 Minutes | R41: To Verify | S41: To Verify | T41: =IF(AND(OR(ISNUMBER(R41),R41="N/A"),OR(ISNUMBER(S41),S41="N/A"),OR(ISNUMBER(R41),ISNUMBER(S41))),N(R41)+N(S41),"To Verify") -> To Verify | U41: To Verify | V41: No | W41: Depends on Service | X41: Portal Dependent | Y41: Yes | Z41: UIDAI portal / mAadhaar | AA41: Depends | AB41: Yes | AC41: To Verify | AD41: To Verify | AE41: To Verify | AF41: To Verify | AG41: To Verify | AH41: No | AI41: No | AJ41: No | AK41: No | AL41: Aadhaar Centre | AM41: Download, Print & Status | AN41: =BA41&", "&AZ41 -> Aadhaar Offline eKYC (XML / QR) Download Assistance, Aadhaar Centre, Devmobile Stores, आधार Offline eKYC (XML / QR) डाउनलोड सहायता, आधार सेंटर, सेवा | AO41: aadhaar-offline-ekyc-xml-qr-download-assistance | AP41: 🖨️ | AQ41: 380 | AR41: Q1: What if my mobile is not linked? A1: Some online services need OTP; the mobile must first be updated at an Aadhaar Centre. | AS41: Portal availability and OTP delivery depend on UIDAI. | AT41: Fees, documents and processing time are subject to change as per government / bank / portal rules. Final charges are confirmed at the shop before the service starts. | AV41: To Verify | AX41: Aadhaar Offline eKYC (XML / QR) Download Assistance Service | Devmobile Stores | AY41: Aadhaar Offline eKYC (XML / QR) Download Assistance (आधार Offline eKYC (XML / QR) डाउनलोड सहायता) at Devmobile Stores and Common Service Center & Aadhaar Centre. Check required documents, charges and process before you visit. | AZ41: आधार Offline eKYC (XML / QR) डाउनलोड सहायता, आधार सेंटर, सेवा | BA41: Aadhaar Offline eKYC (XML / QR) Download Assistance, Aadhaar Centre, Devmobile Stores | BC41: =IFERROR(INDEX(CATEGORY_MASTER!$C$4:$C$30,MATCH(B41,CATEGORY_MASTER!$A$4:$A$30,0)),"") -> 🪪 | BD41: ="/services/"&AO41 -> /services/aadhaar-offline-ekyc-xml-qr-download-assistance | BE41: =IF(AND(AH41="Yes",AG41="Active",I41<>"Not Available"),"LIVE","HIDDEN") -> HIDDEN | BF41: In-person assistance at the shop • Help checking your documents • Receipt / acknowledgement where applicable | BG41: Check Documents | BH41: =B41&"|"&COUNTIF($B$4:B41,B41) -> Aadhaar Centre|38 | BI41: =IF(AND(AI41="Yes",BE41="LIVE"),COUNTIFS($AI$4:AI41,"Yes",$BE$4:BE41,"LIVE"),"") | BJ41: =IF(AND(AJ41="Yes",BE41="LIVE"),COUNTIFS($AJ$4:AJ41,"Yes",$BE$4:BE41,"LIVE"),"") | BK41: =IF(AND(AK41="Yes",BE41="LIVE"),COUNTIFS($AK$4:AK41,"Yes",$BE$4:BE41,"LIVE"),"") | BL41: =IF(I41="To Verify",COUNTIF($I$4:I41,"To Verify"),"")
A42: AAD-039 | B42: Aadhaar Centre | C42: Aadhaar Services | D42: Download, Print & Status | E42: Aadhaar–Bank Seeding Status Check (NPCI) | F42: आधार–बैंक सीडिंग स्थिति जाँच (NPCI) | G42: Get Aadhaar–Bank Seeding Status Check (NPCI) done at our Aadhaar Centre. | H42: Aadhaar–Bank Seeding Status Check (NPCI) using the UIDAI portal. | I42: Portal Dependent | J42: =IFERROR(INDEX(AVAILABILITY_MASTER!$C$4:$C$10,MATCH(I42,AVAILABILITY_MASTER!$A$4:$A$10,0)),"To Be Confirmed") -> Depends on Portal – Confirm at Shop | K42: Depends | L42: Portal Dependent | M42: =IFERROR(INDEX(SERVICE_DOCUMENTS!$S$4:$S$1000,MATCH(A42,SERVICE_DOCUMENTS!$A$4:$A$1000,0))&"","") -> ✓ Enrolment / Acknowledgement Number | N42: =IFERROR(INDEX(SERVICE_DOCUMENTS!$T$4:$T$1000,MATCH(A42,SERVICE_DOCUMENTS!$A$4:$A$1000,0))&"","") -> • Aadhaar-Linked Mobile Number (If Applicable) | O42: Anyone with an EID / URN slip. | P42: Step 1 → Share the enrolment (EID) or update (URN) number from your slip. Step 2 → Operator checks the status on the UIDAI portal. Step 3 → Result is shown or printed for you. | Q42: 5–10 Minutes | R42: To Verify | S42: To Verify | T42: =IF(AND(OR(ISNUMBER(R42),R42="N/A"),OR(ISNUMBER(S42),S42="N/A"),OR(ISNUMBER(R42),ISNUMBER(S42))),N(R42)+N(S42),"To Verify") -> To Verify | U42: To Verify | V42: No | W42: Depends on Service | X42: Portal Dependent | Y42: Yes | Z42: UIDAI portal | AA42: Depends | AB42: Yes | AC42: To Verify | AD42: To Verify | AE42: To Verify | AF42: To Verify | AG42: To Verify | AH42: No | AI42: No | AJ42: No | AK42: No | AL42: Aadhaar Centre | AM42: Download, Print & Status | AN42: =BA42&", "&AZ42 -> Aadhaar–Bank Seeding Status Check (NPCI), Aadhaar Centre, Devmobile Stores, आधार–बैंक सीडिंग स्थिति जाँच (NPCI), आधार सेंटर, सेवा | AO42: aadhaar-bank-seeding-status-check-npci | AP42: 🖨️ | AQ42: 390 | AR42: Q1: Where can I check the current charges? A1: Charges are confirmed at the shop and may change as per government / bank rules. | AS42: Please confirm availability with the shop before visiting. | AT42: Fees, documents and processing time are subject to change as per government / bank / portal rules. Final charges are confirmed at the shop before the service starts. | AV42: To Verify | AX42: Aadhaar–Bank Seeding Status Check (NPCI) Service | Devmobile Stores | AY42: Aadhaar–Bank Seeding Status Check (NPCI) (आधार–बैंक सीडिंग स्थिति जाँच (NPCI)) at Devmobile Stores and Common Service Center & Aadhaar Centre. Check required documents, charges and process before you visit. | AZ42: आधार–बैंक सीडिंग स्थिति जाँच (NPCI), आधार सेंटर, सेवा | BA42: Aadhaar–Bank Seeding Status Check (NPCI), Aadhaar Centre, Devmobile Stores | BC42: =IFERROR(INDEX(CATEGORY_MASTER!$C$4:$C$30,MATCH(B42,CATEGORY_MASTER!$A$4:$A$30,0)),"") -> 🪪 | BD42: ="/services/"&AO42 -> /services/aadhaar-bank-seeding-status-check-npci | BE42: =IF(AND(AH42="Yes",AG42="Active",I42<>"Not Available"),"LIVE","HIDDEN") -> HIDDEN | BF42: In-person assistance at the shop • Help checking your documents • Receipt / acknowledgement where applicable | BG42: Check Documents | BH42: =B42&"|"&COUNTIF($B$4:B42,B42) -> Aadhaar Centre|39 | BI42: =IF(AND(AI42="Yes",BE42="LIVE"),COUNTIFS($AI$4:AI42,"Yes",$BE$4:BE42,"LIVE"),"") | BJ42: =IF(AND(AJ42="Yes",BE42="LIVE"),COUNTIFS($AJ$4:AJ42,"Yes",$BE$4:BE42,"LIVE"),"") | BK42: =IF(AND(AK42="Yes",BE42="LIVE"),COUNTIFS($AK$4:AK42,"Yes",$BE$4:BE42,"LIVE"),"") | BL42: =IF(I42="To Verify",COUNTIF($I$4:I42,"To Verify"),"")
A43: AAD-040 | B43: Aadhaar Centre | C43: Aadhaar Services | D43: Download, Print & Status | E43: Aadhaar Update Appointment Booking Assistance | F43: आधार अपडेट अपॉइंटमेंट बुकिंग सहायता | G43: Get Aadhaar Update Appointment Booking Assistance done at our Aadhaar Centre. | H43: Assistance with aadhaar update appointment booking assistance through the UIDAI portal. | I43: Portal Dependent | J43: =IFERROR(INDEX(AVAILABILITY_MASTER!$C$4:$C$10,MATCH(I43,AVAILABILITY_MASTER!$A$4:$A$10,0)),"To Be Confirmed") -> Depends on Portal – Confirm at Shop | K43: Depends | L43: Portal Dependent | M43: =IFERROR(INDEX(SERVICE_DOCUMENTS!$S$4:$S$1000,MATCH(A43,SERVICE_DOCUMENTS!$A$4:$A$1000,0))&"","") -> ✓ Aadhaar Card ✓ Aadhaar-Linked Mobile Number | N43: =IFERROR(INDEX(SERVICE_DOCUMENTS!$T$4:$T$1000,MATCH(A43,SERVICE_DOCUMENTS!$A$4:$A$1000,0))&"","") | O43: Aadhaar holders with a mobile number linked to Aadhaar. | P43: Step 1 → Bring your Aadhaar number and the mobile number linked with Aadhaar. Step 2 → Operator opens the UIDAI service for 'Aadhaar Update Appointment Booking Assistance'. Step 3 → OTP is sent to your linked mobile and entered. Step 4 → Service is completed and the result is downloaded / shown to you. Step 5 → Pay the assistance charge. | Q43: 15–30 Minutes | R43: To Verify | S43: To Verify | T43: =IF(AND(OR(ISNUMBER(R43),R43="N/A"),OR(ISNUMBER(S43),S43="N/A"),OR(ISNUMBER(R43),ISNUMBER(S43))),N(R43)+N(S43),"To Verify") -> To Verify | U43: To Verify | V43: No | W43: Depends on Service | X43: Portal Dependent | Y43: Yes | Z43: UIDAI portal / mAadhaar | AA43: Depends | AB43: Yes | AC43: To Verify | AD43: To Verify | AE43: To Verify | AF43: To Verify | AG43: To Verify | AH43: No | AI43: No | AJ43: No | AK43: No | AL43: Aadhaar Centre | AM43: Download, Print & Status | AN43: =BA43&", "&AZ43 -> Aadhaar Update Appointment Booking Assistance, Aadhaar Centre, Devmobile Stores, आधार अपडेट अपॉइंटमेंट बुकिंग सहायता, आधार सेंटर, सेवा | AO43: aadhaar-update-appointment-booking-assistance | AP43: 🖨️ | AQ43: 400 | AR43: Q1: What if my mobile is not linked? A1: Some online services need OTP; the mobile must first be updated at an Aadhaar Centre. | AS43: Portal availability and OTP delivery depend on UIDAI. | AT43: Fees, documents and processing time are subject to change as per government / bank / portal rules. Final charges are confirmed at the shop before the service starts. | AV43: To Verify | AX43: Aadhaar Update Appointment Booking Assistance Service | Devmobile Stores | AY43: Aadhaar Update Appointment Booking Assistance (आधार अपडेट अपॉइंटमेंट बुकिंग सहायता) at Devmobile Stores and Common Service Center & Aadhaar Centre. Check required documents, charges and process before you visit. | AZ43: आधार अपडेट अपॉइंटमेंट बुकिंग सहायता, आधार सेंटर, सेवा | BA43: Aadhaar Update Appointment Booking Assistance, Aadhaar Centre, Devmobile Stores | BC43: =IFERROR(INDEX(CATEGORY_MASTER!$C$4:$C$30,MATCH(B43,CATEGORY_MASTER!$A$4:$A$30,0)),"") -> 🪪 | BD43: ="/services/"&AO43 -> /services/aadhaar-update-appointment-booking-assistance | BE43: =IF(AND(AH43="Yes",AG43="Active",I43<>"Not Available"),"LIVE","HIDDEN") -> HIDDEN | BF43: In-person assistance at the shop • Help checking your documents • Receipt / acknowledgement where applicable | BG43: Check Documents | BH43: =B43&"|"&COUNTIF($B$4:B43,B43) -> Aadhaar Centre|40 | BI43: =IF(AND(AI43="Yes",BE43="LIVE"),COUNTIFS($AI$4:AI43,"Yes",$BE$4:BE43,"LIVE"),"") | BJ43: =IF(AND(AJ43="Yes",BE43="LIVE"),COUNTIFS($AJ$4:AJ43,"Yes",$BE$4:BE43,"LIVE"),"") | BK43: =IF(AND(AK43="Yes",BE43="LIVE"),COUNTIFS($AK$4:AK43,"Yes",$BE$4:BE43,"LIVE"),"") | BL43: =IF(I43="To Verify",COUNTIF($I$4:I43,"To Verify"),"")
A44: AAD-041 | B44: Aadhaar Centre | C44: Aadhaar Services | D44: Download, Print & Status | E44: mAadhaar App Setup Assistance | F44: mAadhaar ऐप सेटअप सहायता | G44: Get mAadhaar App Setup Assistance done at our Aadhaar Centre. | H44: Assistance with maadhaar app setup assistance through the UIDAI portal. | I44: Portal Dependent | J44: =IFERROR(INDEX(AVAILABILITY_MASTER!$C$4:$C$10,MATCH(I44,AVAILABILITY_MASTER!$A$4:$A$10,0)),"To Be Confirmed") -> Depends on Portal – Confirm at Shop | K44: Depends | L44: Portal Dependent | M44: =IFERROR(INDEX(SERVICE_DOCUMENTS!$S$4:$S$1000,MATCH(A44,SERVICE_DOCUMENTS!$A$4:$A$1000,0))&"","") -> ✓ Aadhaar Card ✓ Aadhaar-Linked Mobile Number | N44: =IFERROR(INDEX(SERVICE_DOCUMENTS!$T$4:$T$1000,MATCH(A44,SERVICE_DOCUMENTS!$A$4:$A$1000,0))&"","") | O44: Aadhaar holders with a mobile number linked to Aadhaar. | P44: Step 1 → Bring your Aadhaar number and the mobile number linked with Aadhaar. Step 2 → Operator opens the UIDAI service for 'mAadhaar App Setup Assistance'. Step 3 → OTP is sent to your linked mobile and entered. Step 4 → Service is completed and the result is downloaded / shown to you. Step 5 → Pay the assistance charge. | Q44: 15–30 Minutes | R44: To Verify | S44: To Verify | T44: =IF(AND(OR(ISNUMBER(R44),R44="N/A"),OR(ISNUMBER(S44),S44="N/A"),OR(ISNUMBER(R44),ISNUMBER(S44))),N(R44)+N(S44),"To Verify") -> To Verify | U44: To Verify | V44: No | W44: Depends on Service | X44: Portal Dependent | Y44: Yes | Z44: UIDAI portal / mAadhaar | AA44: Depends | AB44: Yes | AC44: To Verify | AD44: To Verify | AE44: To Verify | AF44: To Verify | AG44: To Verify | AH44: No | AI44: No | AJ44: No | AK44: No | AL44: Aadhaar Centre | AM44: Download, Print & Status | AN44: =BA44&", "&AZ44 -> mAadhaar App Setup Assistance, Aadhaar Centre, Devmobile Stores, mAadhaar ऐप सेटअप सहायता, आधार सेंटर, सेवा | AO44: maadhaar-app-setup-assistance | AP44: 🖨️ | AQ44: 410 | AR44: Q1: What if my mobile is not linked? A1: Some online services need OTP; the mobile must first be updated at an Aadhaar Centre. | AS44: Portal availability and OTP delivery depend on UIDAI. | AT44: Fees, documents and processing time are subject to change as per government / bank / portal rules. Final charges are confirmed at the shop before the service starts. | AV44: To Verify | AX44: mAadhaar App Setup Assistance Service | Devmobile Stores | AY44: mAadhaar App Setup Assistance (mAadhaar ऐप सेटअप सहायता) at Devmobile Stores and Common Service Center & Aadhaar Centre. Check required documents, charges and process before you visit. | AZ44: mAadhaar ऐप सेटअप सहायता, आधार सेंटर, सेवा | BA44: mAadhaar App Setup Assistance, Aadhaar Centre, Devmobile Stores | BC44: =IFERROR(INDEX(CATEGORY_MASTER!$C$4:$C$30,MATCH(B44,CATEGORY_MASTER!$A$4:$A$30,0)),"") -> 🪪 | BD44: ="/services/"&AO44 -> /services/maadhaar-app-setup-assistance | BE44: =IF(AND(AH44="Yes",AG44="Active",I44<>"Not Available"),"LIVE","HIDDEN") -> HIDDEN | BF44: In-person assistance at the shop • Help checking your documents • Receipt / acknowledgement where applicable | BG44: Check Documents | BH44: =B44&"|"&COUNTIF($B$4:B44,B44) -> Aadhaar Centre|41 | BI44: =IF(AND(AI44="Yes",BE44="LIVE"),COUNTIFS($AI$4:AI44,"Yes",$BE$4:BE44,"LIVE"),"") | BJ44: =IF(AND(AJ44="Yes",BE44="LIVE"),COUNTIFS($AJ$4:AJ44,"Yes",$BE$4:BE44,"LIVE"),"") | BK44: =IF(AND(AK44="Yes",BE44="LIVE"),COUNTIFS($AK$4:AK44,"Yes",$BE$4:BE44,"LIVE"),"") | BL44: =IF(I44="To Verify",COUNTIF($I$4:I44,"To Verify"),"")
A45: AAD-042 | B45: Aadhaar Centre | C45: Aadhaar Services | D45: Download, Print & Status | E45: Aadhaar Complaint / Grievance Filing Assistance | F45: आधार शिकायत दर्ज करने में सहायता | G45: Get Aadhaar Complaint / Grievance Filing Assistance done at our Aadhaar Centre. | H45: Assistance with aadhaar complaint / grievance filing assistance through the UIDAI portal. | I45: Portal Dependent | J45: =IFERROR(INDEX(AVAILABILITY_MASTER!$C$4:$C$10,MATCH(I45,AVAILABILITY_MASTER!$A$4:$A$10,0)),"To Be Confirmed") -> Depends on Portal – Confirm at Shop | K45: Depends | L45: Portal Dependent | M45: =IFERROR(INDEX(SERVICE_DOCUMENTS!$S$4:$S$1000,MATCH(A45,SERVICE_DOCUMENTS!$A$4:$A$1000,0))&"","") -> ✓ Aadhaar Card ✓ Aadhaar-Linked Mobile Number | N45: =IFERROR(INDEX(SERVICE_DOCUMENTS!$T$4:$T$1000,MATCH(A45,SERVICE_DOCUMENTS!$A$4:$A$1000,0))&"","") | O45: Aadhaar holders with a mobile number linked to Aadhaar. | P45: Step 1 → Bring your Aadhaar number and the mobile number linked with Aadhaar. Step 2 → Operator opens the UIDAI service for 'Aadhaar Complaint / Grievance Filing Assistance'. Step 3 → OTP is sent to your linked mobile and entered. Step 4 → Service is completed and the result is downloaded / shown to you. Step 5 → Pay the assistance charge. | Q45: 15–30 Minutes | R45: To Verify | S45: To Verify | T45: =IF(AND(OR(ISNUMBER(R45),R45="N/A"),OR(ISNUMBER(S45),S45="N/A"),OR(ISNUMBER(R45),ISNUMBER(S45))),N(R45)+N(S45),"To Verify") -> To Verify | U45: To Verify | V45: No | W45: Depends on Service | X45: Portal Dependent | Y45: Yes | Z45: UIDAI portal / mAadhaar | AA45: Depends | AB45: Yes | AC45: To Verify | AD45: To Verify | AE45: To Verify | AF45: To Verify | AG45: To Verify | AH45: No | AI45: No | AJ45: No | AK45: No | AL45: Aadhaar Centre | AM45: Download, Print & Status | AN45: =BA45&", "&AZ45 -> Aadhaar Complaint / Grievance Filing Assistance, Aadhaar Centre, Devmobile Stores, आधार शिकायत दर्ज करने में सहायता, आधार सेंटर, सेवा | AO45: aadhaar-complaint-grievance-filing-assistance | AP45: 🖨️ | AQ45: 420 | AR45: Q1: What if my mobile is not linked? A1: Some online services need OTP; the mobile must first be updated at an Aadhaar Centre. | AS45: Portal availability and OTP delivery depend on UIDAI. | AT45: Fees, documents and processing time are subject to change as per government / bank / portal rules. Final charges are confirmed at the shop before the service starts. | AV45: To Verify | AX45: Aadhaar Complaint / Grievance Filing Assistance Service | Devmobile Stores | AY45: Aadhaar Complaint / Grievance Filing Assistance (आधार शिकायत दर्ज करने में सहायता) at Devmobile Stores and Common Service Center & Aadhaar Centre. Check required documents, charges and process before you visit. | AZ45: आधार शिकायत दर्ज करने में सहायता, आधार सेंटर, सेवा | BA45: Aadhaar Complaint / Grievance Filing Assistance, Aadhaar Centre, Devmobile Stores | BC45: =IFERROR(INDEX(CATEGORY_MASTER!$C$4:$C$30,MATCH(B45,CATEGORY_MASTER!$A$4:$A$30,0)),"") -> 🪪 | BD45: ="/services/"&AO45 -> /services/aadhaar-complaint-grievance-filing-assistance | BE45: =IF(AND(AH45="Yes",AG45="Active",I45<>"Not Available"),"LIVE","HIDDEN") -> HIDDEN | BF45: In-person assistance at the shop • Help checking your documents • Receipt / acknowledgement where applicable | BG45: Check Documents | BH45: =B45&"|"&COUNTIF($B$4:B45,B45) -> Aadhaar Centre|42 | BI45: =IF(AND(AI45="Yes",BE45="LIVE"),COUNTIFS($AI$4:AI45,"Yes",$BE$4:BE45,"LIVE"),"") | BJ45: =IF(AND(AJ45="Yes",BE45="LIVE"),COUNTIFS($AJ$4:AJ45,"Yes",$BE$4:BE45,"LIVE"),"") | BK45: =IF(AND(AK45="Yes",BE45="LIVE"),COUNTIFS($AK$4:AK45,"Yes",$BE$4:BE45,"LIVE"),"") | BL45: =IF(I45="To Verify",COUNTIF($I$4:I45,"To Verify"),"")
A46: HDF-001 | B46: HDFC Bank BC Point | C46: Banking Services | D46: Cash & Balance Services | E46: HDFC BC – Cash Deposit | F46: HDFC BC – नकद जमा | G46: HDFC BC – Cash Deposit at our HDFC Bank BC Point. | H46: Deposit cash into a HDFC Bank account through our BC Point. | I46: Authorization Required | J46: =IFERROR(INDEX(AVAILABILITY_MASTER!$C$4:$C$10,MATCH(I46,AVAILABILITY_MASTER!$A$4:$A$10,0)),"To Be Confirmed") -> Please Confirm at Shop | K46: Yes | L46: To Verify | M46: =IFERROR(INDEX(SERVICE_DOCUMENTS!$S$4:$S$1000,MATCH(A46,SERVICE_DOCUMENTS!$A$4:$A$1000,0))&"","") -> ✓ Bank Account Number ✓ Cash Amount | N46: =IFERROR(INDEX(SERVICE_DOCUMENTS!$T$4:$T$1000,MATCH(A46,SERVICE_DOCUMENTS!$A$4:$A$1000,0))&"","") -> • Aadhaar Card (If Applicable) | O46: HDFC Bank account holders (rules as per bank). | P46: Step 1 → Give the account number / details and the cash amount. Step 2 → Operator enters the details on the BC device. Step 3 → Customer verifies the amount and gives authentication if asked. Step 4 → Cash is accepted and a receipt / SMS is generated. | Q46: 5–10 Minutes | R46: To Verify | S46: To Verify | T46: =IF(AND(OR(ISNUMBER(R46),R46="N/A"),OR(ISNUMBER(S46),S46="N/A"),OR(ISNUMBER(R46),ISNUMBER(S46))),N(R46)+N(S46),"To Verify") -> To Verify | U46: To Verify | V46: No | W46: Depends on Service | X46: Offline | Y46: No | AA46: Yes | AB46: Yes | AC46: To Verify | AD46: To Verify | AE46: No | AF46: No | AG46: To Verify | AH46: No | AI46: No | AJ46: No | AK46: No | AL46: HDFC Bank BC Point | AM46: Cash & Balance Services | AN46: =BA46&", "&AZ46 -> HDFC BC – Cash Deposit, HDFC Bank BC Point, Devmobile Stores, HDFC BC – नकद जमा, HDFC बैंक BC पॉइंट, सेवा | AO46: hdfc-bc-cash-deposit | AP46: 💵 | AQ46: 10 | AR46: Q1: Is there a deposit limit? A1: Limits are set by the bank; ask at the counter. | AS46: Depends on your HDFC Bank BC agreement and activated services. Confirm with the shop before visiting. | AT46: Fees, documents and processing time are subject to change as per government / bank / portal rules. Final charges are confirmed at the shop before the service starts. | AV46: To Verify | AX46: HDFC BC – Cash Deposit Service | Devmobile Stores | AY46: HDFC BC – Cash Deposit (HDFC BC – नकद जमा) at Devmobile Stores and Common Service Center & Aadhaar Centre. Check required documents, charges and process before you visit. | AZ46: HDFC BC – नकद जमा, HDFC बैंक BC पॉइंट, सेवा | BA46: HDFC BC – Cash Deposit, HDFC Bank BC Point, Devmobile Stores | BC46: =IFERROR(INDEX(CATEGORY_MASTER!$C$4:$C$30,MATCH(B46,CATEGORY_MASTER!$A$4:$A$30,0)),"") -> 🏦 | BD46: ="/services/"&AO46 -> /services/hdfc-bc-cash-deposit | BE46: =IF(AND(AH46="Yes",AG46="Active",I46<>"Not Available"),"LIVE","HIDDEN") -> HIDDEN | BF46: In-person assistance at the shop • Help checking your documents • Receipt / acknowledgement where applicable | BG46: Check Documents | BH46: =B46&"|"&COUNTIF($B$4:B46,B46) -> HDFC Bank BC Point|1 | BI46: =IF(AND(AI46="Yes",BE46="LIVE"),COUNTIFS($AI$4:AI46,"Yes",$BE$4:BE46,"LIVE"),"") | BJ46: =IF(AND(AJ46="Yes",BE46="LIVE"),COUNTIFS($AJ$4:AJ46,"Yes",$BE$4:BE46,"LIVE"),"") | BK46: =IF(AND(AK46="Yes",BE46="LIVE"),COUNTIFS($AK$4:AK46,"Yes",$BE$4:BE46,"LIVE"),"") | BL46: =IF(I46="To Verify",COUNTIF($I$4:I46,"To Verify"),"")
A47: HDF-002 | B47: HDFC Bank BC Point | C47: Banking Services | D47: Cash & Balance Services | E47: HDFC BC – Cash Withdrawal | F47: HDFC BC – नकद निकासी | G47: HDFC BC – Cash Withdrawal at our HDFC Bank BC Point. | H47: Withdraw cash from a HDFC Bank account at our BC Point. | I47: Authorization Required | J47: =IFERROR(INDEX(AVAILABILITY_MASTER!$C$4:$C$10,MATCH(I47,AVAILABILITY_MASTER!$A$4:$A$10,0)),"To Be Confirmed") -> Please Confirm at Shop | K47: Yes | L47: To Verify | M47: =IFERROR(INDEX(SERVICE_DOCUMENTS!$S$4:$S$1000,MATCH(A47,SERVICE_DOCUMENTS!$A$4:$A$1000,0))&"","") -> ✓ Aadhaar Card ✓ Customer Presence for Biometrics | N47: =IFERROR(INDEX(SERVICE_DOCUMENTS!$T$4:$T$1000,MATCH(A47,SERVICE_DOCUMENTS!$A$4:$A$1000,0))&"","") -> • Bank Account Number (If Applicable) | O47: HDFC Bank account holders (rules as per bank). | P47: Step 1 → Tell the amount and give Aadhaar / account details. Step 2 → Operator initiates the withdrawal on the BC device. Step 3 → Customer authenticates (fingerprint / PIN as applicable). Step 4 → Cash is handed over with receipt / SMS. | Q47: 5–10 Minutes | R47: To Verify | S47: To Verify | T47: =IF(AND(OR(ISNUMBER(R47),R47="N/A"),OR(ISNUMBER(S47),S47="N/A"),OR(ISNUMBER(R47),ISNUMBER(S47))),N(R47)+N(S47),"To Verify") -> To Verify | U47: To Verify | V47: No | W47: Depends on Service | X47: Offline | Y47: No | AA47: Yes | AB47: Yes | AC47: To Verify | AD47: To Verify | AE47: No | AF47: No | AG47: To Verify | AH47: No | AI47: No | AJ47: No | AK47: No | AL47: HDFC Bank BC Point | AM47: Cash & Balance Services | AN47: =BA47&", "&AZ47 -> HDFC BC – Cash Withdrawal, HDFC Bank BC Point, Devmobile Stores, HDFC BC – नकद निकासी, HDFC बैंक BC पॉइंट, सेवा | AO47: hdfc-bc-cash-withdrawal | AP47: 💵 | AQ47: 20 | AR47: Q1: Is there a daily limit? A1: Yes, limits are set by the bank. | AS47: Depends on your HDFC Bank BC agreement and activated services. Confirm with the shop before visiting. | AT47: Fees, documents and processing time are subject to change as per government / bank / portal rules. Final charges are confirmed at the shop before the service starts. | AV47: To Verify | AX47: HDFC BC – Cash Withdrawal Service | Devmobile Stores | AY47: HDFC BC – Cash Withdrawal (HDFC BC – नकद निकासी) at Devmobile Stores and Common Service Center & Aadhaar Centre. Check required documents, charges and process before you visit. | AZ47: HDFC BC – नकद निकासी, HDFC बैंक BC पॉइंट, सेवा | BA47: HDFC BC – Cash Withdrawal, HDFC Bank BC Point, Devmobile Stores | BC47: =IFERROR(INDEX(CATEGORY_MASTER!$C$4:$C$30,MATCH(B47,CATEGORY_MASTER!$A$4:$A$30,0)),"") -> 🏦 | BD47: ="/services/"&AO47 -> /services/hdfc-bc-cash-withdrawal | BE47: =IF(AND(AH47="Yes",AG47="Active",I47<>"Not Available"),"LIVE","HIDDEN") -> HIDDEN | BF47: In-person assistance at the shop • Help checking your documents • Receipt / acknowledgement where applicable | BG47: Check Documents | BH47: =B47&"|"&COUNTIF($B$4:B47,B47) -> HDFC Bank BC Point|2 | BI47: =IF(AND(AI47="Yes",BE47="LIVE"),COUNTIFS($AI$4:AI47,"Yes",$BE$4:BE47,"LIVE"),"") | BJ47: =IF(AND(AJ47="Yes",BE47="LIVE"),COUNTIFS($AJ$4:AJ47,"Yes",$BE$4:BE47,"LIVE"),"") | BK47: =IF(AND(AK47="Yes",BE47="LIVE"),COUNTIFS($AK$4:AK47,"Yes",$BE$4:BE47,"LIVE"),"") | BL47: =IF(I47="To Verify",COUNTIF($I$4:I47,"To Verify"),"")
A48: HDF-003 | B48: HDFC Bank BC Point | C48: Banking Services | D48: Cash & Balance Services | E48: HDFC BC – Balance Enquiry | F48: HDFC BC – बैलेंस पूछताछ | G48: HDFC BC – Balance Enquiry at our HDFC Bank BC Point. | H48: Assistance with hdfc bc – balance enquiry. | I48: Authorization Required | J48: =IFERROR(INDEX(AVAILABILITY_MASTER!$C$4:$C$10,MATCH(I48,AVAILABILITY_MASTER!$A$4:$A$10,0)),"To Be Confirmed") -> Please Confirm at Shop | K48: Yes | L48: To Verify | M48: =IFERROR(INDEX(SERVICE_DOCUMENTS!$S$4:$S$1000,MATCH(A48,SERVICE_DOCUMENTS!$A$4:$A$1000,0))&"","") -> ✓ Aadhaar Card ✓ Bank Account Number ✓ Active Mobile Number | N48: =IFERROR(INDEX(SERVICE_DOCUMENTS!$T$4:$T$1000,MATCH(A48,SERVICE_DOCUMENTS!$A$4:$A$1000,0))&"","") | O48: Any customer who can provide the listed documents. | P48: Step 1 → Bring your account details and Aadhaar. Step 2 → Operator checks how 'HDFC BC – Balance Enquiry' can be handled through the BC. Step 3 → Request is submitted through the BC channel or the bank branch is advised. Step 4 → Collect the acknowledgement. | Q48: Depends on Department | R48: To Verify | S48: To Verify | T48: =IF(AND(OR(ISNUMBER(R48),R48="N/A"),OR(ISNUMBER(S48),S48="N/A"),OR(ISNUMBER(R48),ISNUMBER(S48))),N(R48)+N(S48),"To Verify") -> To Verify | U48: To Verify | V48: No | W48: Depends on Service | X48: Offline | Y48: No | AA48: Yes | AB48: Yes | AC48: To Verify | AD48: To Verify | AE48: No | AF48: No | AG48: To Verify | AH48: No | AI48: No | AJ48: No | AK48: No | AL48: HDFC Bank BC Point | AM48: Cash & Balance Services | AN48: =BA48&", "&AZ48 -> HDFC BC – Balance Enquiry, HDFC Bank BC Point, Devmobile Stores, HDFC BC – बैलेंस पूछताछ, HDFC बैंक BC पॉइंट, सेवा | AO48: hdfc-bc-balance-enquiry | AP48: 💵 | AQ48: 30 | AR48: Q1: Where can I check the current charges? A1: Charges are confirmed at the shop and may change as per government / bank rules. | AS48: Depends on your HDFC Bank BC agreement and activated services. Confirm with the shop before visiting. | AT48: Fees, documents and processing time are subject to change as per government / bank / portal rules. Final charges are confirmed at the shop before the service starts. | AV48: To Verify | AX48: HDFC BC – Balance Enquiry Service | Devmobile Stores | AY48: HDFC BC – Balance Enquiry (HDFC BC – बैलेंस पूछताछ) at Devmobile Stores and Common Service Center & Aadhaar Centre. Check required documents, charges and process before you visit. | AZ48: HDFC BC – बैलेंस पूछताछ, HDFC बैंक BC पॉइंट, सेवा | BA48: HDFC BC – Balance Enquiry, HDFC Bank BC Point, Devmobile Stores | BC48: =IFERROR(INDEX(CATEGORY_MASTER!$C$4:$C$30,MATCH(B48,CATEGORY_MASTER!$A$4:$A$30,0)),"") -> 🏦 | BD48: ="/services/"&AO48 -> /services/hdfc-bc-balance-enquiry | BE48: =IF(AND(AH48="Yes",AG48="Active",I48<>"Not Available"),"LIVE","HIDDEN") -> HIDDEN | BF48: In-person assistance at the shop • Help checking your documents • Receipt / acknowledgement where applicable | BG48: Check Documents | BH48: =B48&"|"&COUNTIF($B$4:B48,B48) -> HDFC Bank BC Point|3 | BI48: =IF(AND(AI48="Yes",BE48="LIVE"),COUNTIFS($AI$4:AI48,"Yes",$BE$4:BE48,"LIVE"),"") | BJ48: =IF(AND(AJ48="Yes",BE48="LIVE"),COUNTIFS($AJ$4:AJ48,"Yes",$BE$4:BE48,"LIVE"),"") | BK48: =IF(AND(AK48="Yes",BE48="LIVE"),COUNTIFS($AK$4:AK48,"Yes",$BE$4:BE48,"LIVE"),"") | BL48: =IF(I48="To Verify",COUNTIF($I$4:I48,"To Verify"),"")
A49: HDF-004 | B49: HDFC Bank BC Point | C49: Banking Services | D49: Cash & Balance Services | E49: HDFC BC – Mini Statement | F49: HDFC BC – मिनी स्टेटमेंट | G49: HDFC BC – Mini Statement at our HDFC Bank BC Point. | H49: Assistance with hdfc bc – mini statement. | I49: Authorization Required | J49: =IFERROR(INDEX(AVAILABILITY_MASTER!$C$4:$C$10,MATCH(I49,AVAILABILITY_MASTER!$A$4:$A$10,0)),"To Be Confirmed") -> Please Confirm at Shop | K49: Yes | L49: To Verify | M49: =IFERROR(INDEX(SERVICE_DOCUMENTS!$S$4:$S$1000,MATCH(A49,SERVICE_DOCUMENTS!$A$4:$A$1000,0))&"","") -> ✓ Aadhaar Card ✓ Bank Account Number ✓ Active Mobile Number | N49: =IFERROR(INDEX(SERVICE_DOCUMENTS!$T$4:$T$1000,MATCH(A49,SERVICE_DOCUMENTS!$A$4:$A$1000,0))&"","") | O49: Any customer who can provide the listed documents. | P49: Step 1 → Bring your account details and Aadhaar. Step 2 → Operator checks how 'HDFC BC – Mini Statement' can be handled through the BC. Step 3 → Request is submitted through the BC channel or the bank branch is advised. Step 4 → Collect the acknowledgement. | Q49: Depends on Department | R49: To Verify | S49: To Verify | T49: =IF(AND(OR(ISNUMBER(R49),R49="N/A"),OR(ISNUMBER(S49),S49="N/A"),OR(ISNUMBER(R49),ISNUMBER(S49))),N(R49)+N(S49),"To Verify") -> To Verify | U49: To Verify | V49: No | W49: Depends on Service | X49: Offline | Y49: No | AA49: Yes | AB49: Yes | AC49: To Verify | AD49: To Verify | AE49: No | AF49: No | AG49: To Verify | AH49: No | AI49: No | AJ49: No | AK49: No | AL49: HDFC Bank BC Point | AM49: Cash & Balance Services | AN49: =BA49&", "&AZ49 -> HDFC BC – Mini Statement, HDFC Bank BC Point, Devmobile Stores, HDFC BC – मिनी स्टेटमेंट, HDFC बैंक BC पॉइंट, सेवा | AO49: hdfc-bc-mini-statement | AP49: 💵 | AQ49: 40 | AR49: Q1: Where can I check the current charges? A1: Charges are confirmed at the shop and may change as per government / bank rules. | AS49: Depends on your HDFC Bank BC agreement and activated services. Confirm with the shop before visiting. | AT49: Fees, documents and processing time are subject to change as per government / bank / portal rules. Final charges are confirmed at the shop before the service starts. | AV49: To Verify | AX49: HDFC BC – Mini Statement Service | Devmobile Stores | AY49: HDFC BC – Mini Statement (HDFC BC – मिनी स्टेटमेंट) at Devmobile Stores and Common Service Center & Aadhaar Centre. Check required documents, charges and process before you visit. | AZ49: HDFC BC – मिनी स्टेटमेंट, HDFC बैंक BC पॉइंट, सेवा | BA49: HDFC BC – Mini Statement, HDFC Bank BC Point, Devmobile Stores | BC49: =IFERROR(INDEX(CATEGORY_MASTER!$C$4:$C$30,MATCH(B49,CATEGORY_MASTER!$A$4:$A$30,0)),"") -> 🏦 | BD49: ="/services/"&AO49 -> /services/hdfc-bc-mini-statement | BE49: =IF(AND(AH49="Yes",AG49="Active",I49<>"Not Available"),"LIVE","HIDDEN") -> HIDDEN | BF49: In-person assistance at the shop • Help checking your documents • Receipt / acknowledgement where applicable | BG49: Check Documents | BH49: =B49&"|"&COUNTIF($B$4:B49,B49) -> HDFC Bank BC Point|4 | BI49: =IF(AND(AI49="Yes",BE49="LIVE"),COUNTIFS($AI$4:AI49,"Yes",$BE$4:BE49,"LIVE"),"") | BJ49: =IF(AND(AJ49="Yes",BE49="LIVE"),COUNTIFS($AJ$4:AJ49,"Yes",$BE$4:BE49,"LIVE"),"") | BK49: =IF(AND(AK49="Yes",BE49="LIVE"),COUNTIFS($AK$4:AK49,"Yes",$BE$4:BE49,"LIVE"),"") | BL49: =IF(I49="To Verify",COUNTIF($I$4:I49,"To Verify"),"")
A50: HDF-005 | B50: HDFC Bank BC Point | C50: Banking Services | D50: AEPS / Biometric Banking | E50: HDFC BC – AEPS Cash Withdrawal | F50: HDFC BC – AEPS नकद निकासी | G50: HDFC BC – AEPS Cash Withdrawal at our HDFC Bank BC Point. | H50: AEPS cash withdrawal using Aadhaar and fingerprint. | I50: Authorization Required | J50: =IFERROR(INDEX(AVAILABILITY_MASTER!$C$4:$C$10,MATCH(I50,AVAILABILITY_MASTER!$A$4:$A$10,0)),"To Be Confirmed") -> Please Confirm at Shop | K50: Yes | L50: To Verify | M50: =IFERROR(INDEX(SERVICE_DOCUMENTS!$S$4:$S$1000,MATCH(A50,SERVICE_DOCUMENTS!$A$4:$A$1000,0))&"","") -> ✓ Aadhaar Card ✓ Customer Presence for Biometrics | N50: =IFERROR(INDEX(SERVICE_DOCUMENTS!$T$4:$T$1000,MATCH(A50,SERVICE_DOCUMENTS!$A$4:$A$1000,0))&"","") | O50: Customers with an Aadhaar-linked bank account. | P50: Step 1 → Give your Aadhaar number and select your bank. Step 2 → Place your finger for biometric authentication. Step 3 → Operator completes the cash withdrawal. Step 4 → Collect cash / receipt as applicable. | Q50: 5–10 Minutes | R50: To Verify | S50: To Verify | T50: =IF(AND(OR(ISNUMBER(R50),R50="N/A"),OR(ISNUMBER(S50),S50="N/A"),OR(ISNUMBER(R50),ISNUMBER(S50))),N(R50)+N(S50),"To Verify") -> To Verify | U50: To Verify | V50: No | W50: Depends on Service | X50: Offline | Y50: No | AA50: Yes | AB50: Yes | AC50: To Verify | AD50: To Verify | AE50: No | AF50: No | AG50: To Verify | AH50: No | AI50: No | AJ50: No | AK50: No | AL50: HDFC Bank BC Point | AM50: AEPS / Biometric Banking | AN50: =BA50&", "&AZ50 -> HDFC BC – AEPS Cash Withdrawal, HDFC Bank BC Point, Devmobile Stores, HDFC BC – AEPS नकद निकासी, HDFC बैंक BC पॉइंट, सेवा | AO50: hdfc-bc-aeps-cash-withdrawal | AP50: 👆 | AQ50: 50 | AR50: Q1: Does my bank account need to be Aadhaar-linked? A1: Yes, AEPS works only when the account is linked with Aadhaar. | AS50: Depends on your HDFC Bank BC agreement and activated services. Confirm with the shop before visiting. | AT50: Fees, documents and processing time are subject to change as per government / bank / portal rules. Final charges are confirmed at the shop before the service starts. | AV50: To Verify | AW50: Whether AEPS is enabled on your HDFC BC ID must be confirmed | AX50: HDFC BC – AEPS Cash Withdrawal Service | Devmobile Stores | AY50: HDFC BC – AEPS Cash Withdrawal (HDFC BC – AEPS नकद निकासी) at Devmobile Stores and Common Service Center & Aadhaar Centre. Check required documents, charges and process before you visit. | AZ50: HDFC BC – AEPS नकद निकासी, HDFC बैंक BC पॉइंट, सेवा | BA50: HDFC BC – AEPS Cash Withdrawal, HDFC Bank BC Point, Devmobile Stores | BC50: =IFERROR(INDEX(CATEGORY_MASTER!$C$4:$C$30,MATCH(B50,CATEGORY_MASTER!$A$4:$A$30,0)),"") -> 🏦 | BD50: ="/services/"&AO50 -> /services/hdfc-bc-aeps-cash-withdrawal | BE50: =IF(AND(AH50="Yes",AG50="Active",I50<>"Not Available"),"LIVE","HIDDEN") -> HIDDEN | BF50: In-person assistance at the shop • Help checking your documents • Receipt / acknowledgement where applicable | BG50: Check Documents | BH50: =B50&"|"&COUNTIF($B$4:B50,B50) -> HDFC Bank BC Point|5 | BI50: =IF(AND(AI50="Yes",BE50="LIVE"),COUNTIFS($AI$4:AI50,"Yes",$BE$4:BE50,"LIVE"),"") | BJ50: =IF(AND(AJ50="Yes",BE50="LIVE"),COUNTIFS($AJ$4:AJ50,"Yes",$BE$4:BE50,"LIVE"),"") | BK50: =IF(AND(AK50="Yes",BE50="LIVE"),COUNTIFS($AK$4:AK50,"Yes",$BE$4:BE50,"LIVE"),"") | BL50: =IF(I50="To Verify",COUNTIF($I$4:I50,"To Verify"),"")
A51: HDF-006 | B51: HDFC Bank BC Point | C51: Banking Services | D51: AEPS / Biometric Banking | E51: HDFC BC – AEPS Balance Enquiry | F51: HDFC BC – AEPS बैलेंस पूछताछ | G51: HDFC BC – AEPS Balance Enquiry at our HDFC Bank BC Point. | H51: AEPS balance enquiry using Aadhaar and fingerprint. | I51: Authorization Required | J51: =IFERROR(INDEX(AVAILABILITY_MASTER!$C$4:$C$10,MATCH(I51,AVAILABILITY_MASTER!$A$4:$A$10,0)),"To Be Confirmed") -> Please Confirm at Shop | K51: Yes | L51: To Verify | M51: =IFERROR(INDEX(SERVICE_DOCUMENTS!$S$4:$S$1000,MATCH(A51,SERVICE_DOCUMENTS!$A$4:$A$1000,0))&"","") -> ✓ Aadhaar Card ✓ Customer Presence for Biometrics | N51: =IFERROR(INDEX(SERVICE_DOCUMENTS!$T$4:$T$1000,MATCH(A51,SERVICE_DOCUMENTS!$A$4:$A$1000,0))&"","") | O51: Customers with an Aadhaar-linked bank account. | P51: Step 1 → Give your Aadhaar number and select your bank. Step 2 → Place your finger for biometric authentication. Step 3 → Operator completes the balance enquiry. Step 4 → Collect cash / receipt as applicable. | Q51: 5–10 Minutes | R51: To Verify | S51: To Verify | T51: =IF(AND(OR(ISNUMBER(R51),R51="N/A"),OR(ISNUMBER(S51),S51="N/A"),OR(ISNUMBER(R51),ISNUMBER(S51))),N(R51)+N(S51),"To Verify") -> To Verify | U51: To Verify | V51: No | W51: Depends on Service | X51: Offline | Y51: No | AA51: Yes | AB51: Yes | AC51: To Verify | AD51: To Verify | AE51: No | AF51: No | AG51: To Verify | AH51: No | AI51: No | AJ51: No | AK51: No | AL51: HDFC Bank BC Point | AM51: AEPS / Biometric Banking | AN51: =BA51&", "&AZ51 -> HDFC BC – AEPS Balance Enquiry, HDFC Bank BC Point, Devmobile Stores, HDFC BC – AEPS बैलेंस पूछताछ, HDFC बैंक BC पॉइंट, सेवा | AO51: hdfc-bc-aeps-balance-enquiry | AP51: 👆 | AQ51: 60 | AR51: Q1: Does my bank account need to be Aadhaar-linked? A1: Yes, AEPS works only when the account is linked with Aadhaar. | AS51: Depends on your HDFC Bank BC agreement and activated services. Confirm with the shop before visiting. | AT51: Fees, documents and processing time are subject to change as per government / bank / portal rules. Final charges are confirmed at the shop before the service starts. | AV51: To Verify | AX51: HDFC BC – AEPS Balance Enquiry Service | Devmobile Stores | AY51: HDFC BC – AEPS Balance Enquiry (HDFC BC – AEPS बैलेंस पूछताछ) at Devmobile Stores and Common Service Center & Aadhaar Centre. Check required documents, charges and process before you visit. | AZ51: HDFC BC – AEPS बैलेंस पूछताछ, HDFC बैंक BC पॉइंट, सेवा | BA51: HDFC BC – AEPS Balance Enquiry, HDFC Bank BC Point, Devmobile Stores | BC51: =IFERROR(INDEX(CATEGORY_MASTER!$C$4:$C$30,MATCH(B51,CATEGORY_MASTER!$A$4:$A$30,0)),"") -> 🏦 | BD51: ="/services/"&AO51 -> /services/hdfc-bc-aeps-balance-enquiry | BE51: =IF(AND(AH51="Yes",AG51="Active",I51<>"Not Available"),"LIVE","HIDDEN") -> HIDDEN | BF51: In-person assistance at the shop • Help checking your documents • Receipt / acknowledgement where applicable | BG51: Check Documents | BH51: =B51&"|"&COUNTIF($B$4:B51,B51) -> HDFC Bank BC Point|6 | BI51: =IF(AND(AI51="Yes",BE51="LIVE"),COUNTIFS($AI$4:AI51,"Yes",$BE$4:BE51,"LIVE"),"") | BJ51: =IF(AND(AJ51="Yes",BE51="LIVE"),COUNTIFS($AJ$4:AJ51,"Yes",$BE$4:BE51,"LIVE"),"") | BK51: =IF(AND(AK51="Yes",BE51="LIVE"),COUNTIFS($AK$4:AK51,"Yes",$BE$4:BE51,"LIVE"),"") | BL51: =IF(I51="To Verify",COUNTIF($I$4:I51,"To Verify"),"")
A52: HDF-007 | B52: HDFC Bank BC Point | C52: Banking Services | D52: AEPS / Biometric Banking | E52: HDFC BC – AEPS Mini Statement | F52: HDFC BC – AEPS मिनी स्टेटमेंट | G52: HDFC BC – AEPS Mini Statement at our HDFC Bank BC Point. | H52: AEPS mini statement using Aadhaar and fingerprint. | I52: Authorization Required | J52: =IFERROR(INDEX(AVAILABILITY_MASTER!$C$4:$C$10,MATCH(I52,AVAILABILITY_MASTER!$A$4:$A$10,0)),"To Be Confirmed") -> Please Confirm at Shop | K52: Yes | L52: To Verify | M52: =IFERROR(INDEX(SERVICE_DOCUMENTS!$S$4:$S$1000,MATCH(A52,SERVICE_DOCUMENTS!$A$4:$A$1000,0))&"","") -> ✓ Aadhaar Card ✓ Customer Presence for Biometrics | N52: =IFERROR(INDEX(SERVICE_DOCUMENTS!$T$4:$T$1000,MATCH(A52,SERVICE_DOCUMENTS!$A$4:$A$1000,0))&"","") | O52: Customers with an Aadhaar-linked bank account. | P52: Step 1 → Give your Aadhaar number and select your bank. Step 2 → Place your finger for biometric authentication. Step 3 → Operator completes the mini statement. Step 4 → Collect cash / receipt as applicable. | Q52: 5–10 Minutes | R52: To Verify | S52: To Verify | T52: =IF(AND(OR(ISNUMBER(R52),R52="N/A"),OR(ISNUMBER(S52),S52="N/A"),OR(ISNUMBER(R52),ISNUMBER(S52))),N(R52)+N(S52),"To Verify") -> To Verify | U52: To Verify | V52: No | W52: Depends on Service | X52: Offline | Y52: No | AA52: Yes | AB52: Yes | AC52: To Verify | AD52: To Verify | AE52: No | AF52: No | AG52: To Verify | AH52: No | AI52: No | AJ52: No | AK52: No | AL52: HDFC Bank BC Point | AM52: AEPS / Biometric Banking | AN52: =BA52&", "&AZ52 -> HDFC BC – AEPS Mini Statement, HDFC Bank BC Point, Devmobile Stores, HDFC BC – AEPS मिनी स्टेटमेंट, HDFC बैंक BC पॉइंट, सेवा | AO52: hdfc-bc-aeps-mini-statement | AP52: 👆 | AQ52: 70 | AR52: Q1: Does my bank account need to be Aadhaar-linked? A1: Yes, AEPS works only when the account is linked with Aadhaar. | AS52: Depends on your HDFC Bank BC agreement and activated services. Confirm with the shop before visiting. | AT52: Fees, documents and processing time are subject to change as per government / bank / portal rules. Final charges are confirmed at the shop before the service starts. | AV52: To Verify | AX52: HDFC BC – AEPS Mini Statement Service | Devmobile Stores | AY52: HDFC BC – AEPS Mini Statement (HDFC BC – AEPS मिनी स्टेटमेंट) at Devmobile Stores and Common Service Center & Aadhaar Centre. Check required documents, charges and process before you visit. | AZ52: HDFC BC – AEPS मिनी स्टेटमेंट, HDFC बैंक BC पॉइंट, सेवा | BA52: HDFC BC – AEPS Mini Statement, HDFC Bank BC Point, Devmobile Stores | BC52: =IFERROR(INDEX(CATEGORY_MASTER!$C$4:$C$30,MATCH(B52,CATEGORY_MASTER!$A$4:$A$30,0)),"") -> 🏦 | BD52: ="/services/"&AO52 -> /services/hdfc-bc-aeps-mini-statement | BE52: =IF(AND(AH52="Yes",AG52="Active",I52<>"Not Available"),"LIVE","HIDDEN") -> HIDDEN | BF52: In-person assistance at the shop • Help checking your documents • Receipt / acknowledgement where applicable | BG52: Check Documents | BH52: =B52&"|"&COUNTIF($B$4:B52,B52) -> HDFC Bank BC Point|7 | BI52: =IF(AND(AI52="Yes",BE52="LIVE"),COUNTIFS($AI$4:AI52,"Yes",$BE$4:BE52,"LIVE"),"") | BJ52: =IF(AND(AJ52="Yes",BE52="LIVE"),COUNTIFS($AJ$4:AJ52,"Yes",$BE$4:BE52,"LIVE"),"") | BK52: =IF(AND(AK52="Yes",BE52="LIVE"),COUNTIFS($AK$4:AK52,"Yes",$BE$4:BE52,"LIVE"),"") | BL52: =IF(I52="To Verify",COUNTIF($I$4:I52,"To Verify"),"")
A53: HDF-008 | B53: HDFC Bank BC Point | C53: Banking Services | D53: AEPS / Biometric Banking | E53: HDFC BC – Biometric Banking (Fingerprint Authenticated) | F53: HDFC BC – बायोमेट्रिक बैंकिंग (फिंगरप्रिंट सत्यापित) | G53: HDFC BC – Biometric Banking (Fingerprint Authenticated) at our HDFC Bank BC Point. | H53: Banking transactions authenticated with fingerprint. | I53: Authorization Required | J53: =IFERROR(INDEX(AVAILABILITY_MASTER!$C$4:$C$10,MATCH(I53,AVAILABILITY_MASTER!$A$4:$A$10,0)),"To Be Confirmed") -> Please Confirm at Shop | K53: Yes | L53: To Verify | M53: =IFERROR(INDEX(SERVICE_DOCUMENTS!$S$4:$S$1000,MATCH(A53,SERVICE_DOCUMENTS!$A$4:$A$1000,0))&"","") -> ✓ Aadhaar Card ✓ Customer Presence for Biometrics | N53: =IFERROR(INDEX(SERVICE_DOCUMENTS!$T$4:$T$1000,MATCH(A53,SERVICE_DOCUMENTS!$A$4:$A$1000,0))&"","") | O53: Customers with Aadhaar-linked accounts. | P53: Step 1 → Give Aadhaar number and choose the transaction. Step 2 → Fingerprint is verified on the device. Step 3 → Transaction is completed and receipt / SMS is generated. | Q53: 5–10 Minutes | R53: To Verify | S53: To Verify | T53: =IF(AND(OR(ISNUMBER(R53),R53="N/A"),OR(ISNUMBER(S53),S53="N/A"),OR(ISNUMBER(R53),ISNUMBER(S53))),N(R53)+N(S53),"To Verify") -> To Verify | U53: To Verify | V53: No | W53: Depends on Service | X53: Offline | Y53: No | AA53: Yes | AB53: Yes | AC53: To Verify | AD53: To Verify | AE53: No | AF53: No | AG53: To Verify | AH53: No | AI53: No | AJ53: No | AK53: No | AL53: HDFC Bank BC Point | AM53: AEPS / Biometric Banking | AN53: =BA53&", "&AZ53 -> HDFC BC – Biometric Banking (Fingerprint Authenticated), HDFC Bank BC Point, Devmobile Stores, HDFC BC – बायोमेट्रिक बैंकिंग (फिंगरप्रिंट सत्यापित), HDFC बैंक BC पॉइंट, सेवा | AO53: hdfc-bc-biometric-banking-fingerprint-authenticated | AP53: 👆 | AQ53: 80 | AR53: Q1: Where can I check the current charges? A1: Charges are confirmed at the shop and may change as per government / bank rules. | AS53: Depends on your HDFC Bank BC agreement and activated services. Confirm with the shop before visiting. | AT53: Fees, documents and processing time are subject to change as per government / bank / portal rules. Final charges are confirmed at the shop before the service starts. | AV53: To Verify | AX53: HDFC BC – Biometric Banking (Fingerprint Authenticated) Service | Devmobile Stores | AY53: HDFC BC – Biometric Banking (Fingerprint Authenticated) (HDFC BC – बायोमेट्रिक बैंकिंग (फिंगरप्रिंट सत्यापित)) at Devmobile Stores and Common Service Center & Aadhaar Centre. Check required documents, charges and process before you visit. | AZ53: HDFC BC – बायोमेट्रिक बैंकिंग (फिंगरप्रिंट सत्यापित), HDFC बैंक BC पॉइंट, सेवा | BA53: HDFC BC – Biometric Banking (Fingerprint Authenticated), HDFC Bank BC Point, Devmobile Stores | BC53: =IFERROR(INDEX(CATEGORY_MASTER!$C$4:$C$30,MATCH(B53,CATEGORY_MASTER!$A$4:$A$30,0)),"") -> 🏦 | BD53: ="/services/"&AO53 -> /services/hdfc-bc-biometric-banking-fingerprint-authenticated | BE53: =IF(AND(AH53="Yes",AG53="Active",I53<>"Not Available"),"LIVE","HIDDEN") -> HIDDEN | BF53: In-person assistance at the shop • Help checking your documents • Receipt / acknowledgement where applicable | BG53: Check Documents | BH53: =B53&"|"&COUNTIF($B$4:B53,B53) -> HDFC Bank BC Point|8 | BI53: =IF(AND(AI53="Yes",BE53="LIVE"),COUNTIFS($AI$4:AI53,"Yes",$BE$4:BE53,"LIVE"),"") | BJ53: =IF(AND(AJ53="Yes",BE53="LIVE"),COUNTIFS($AJ$4:AJ53,"Yes",$BE$4:BE53,"LIVE"),"") | BK53: =IF(AND(AK53="Yes",BE53="LIVE"),COUNTIFS($AK$4:AK53,"Yes",$BE$4:BE53,"LIVE"),"") | BL53: =IF(I53="To Verify",COUNTIF($I$4:I53,"To Verify"),"")
A54: HDF-009 | B54: HDFC Bank BC Point | C54: Banking Services | D54: Micro ATM | E54: HDFC BC – Micro ATM Cash Withdrawal | F54: HDFC BC – Micro ATM नकद निकासी | G54: HDFC BC – Micro ATM Cash Withdrawal at our HDFC Bank BC Point. | H54: HDFC BC – Micro ATM Cash Withdrawal using the Micro ATM device. | I54: Authorization Required | J54: =IFERROR(INDEX(AVAILABILITY_MASTER!$C$4:$C$10,MATCH(I54,AVAILABILITY_MASTER!$A$4:$A$10,0)),"To Be Confirmed") -> Please Confirm at Shop | K54: Yes | L54: To Verify | M54: =IFERROR(INDEX(SERVICE_DOCUMENTS!$S$4:$S$1000,MATCH(A54,SERVICE_DOCUMENTS!$A$4:$A$1000,0))&"","") -> ✓ Debit Card | N54: =IFERROR(INDEX(SERVICE_DOCUMENTS!$T$4:$T$1000,MATCH(A54,SERVICE_DOCUMENTS!$A$4:$A$1000,0))&"","") | O54: Debit card holders. | P54: Step 1 → Bring your debit card. Step 2 → Operator starts the Micro ATM transaction. Step 3 → Swipe / insert card and enter your PIN yourself. Step 4 → Collect cash / receipt. | Q54: 5–10 Minutes | R54: To Verify | S54: To Verify | T54: =IF(AND(OR(ISNUMBER(R54),R54="N/A"),OR(ISNUMBER(S54),S54="N/A"),OR(ISNUMBER(R54),ISNUMBER(S54))),N(R54)+N(S54),"To Verify") -> To Verify | U54: To Verify | V54: No | W54: Depends on Service | X54: Offline | Y54: No | AA54: Yes | AB54: Yes | AC54: To Verify | AD54: To Verify | AE54: No | AF54: No | AG54: To Verify | AH54: No | AI54: No | AJ54: No | AK54: No | AL54: HDFC Bank BC Point | AM54: Micro ATM | AN54: =BA54&", "&AZ54 -> HDFC BC – Micro ATM Cash Withdrawal, HDFC Bank BC Point, Devmobile Stores, HDFC BC – Micro ATM नकद निकासी, HDFC बैंक BC पॉइंट, सेवा | AO54: hdfc-bc-micro-atm-cash-withdrawal | AP54: 🏧 | AQ54: 90 | AR54: Q1: Who enters the PIN? A1: You should enter the PIN yourself on the device. | AS54: Depends on your HDFC Bank BC agreement and activated services. Confirm with the shop before visiting. | AT54: Fees, documents and processing time are subject to change as per government / bank / portal rules. Final charges are confirmed at the shop before the service starts. | AV54: To Verify | AW54: Micro ATM device availability to be verified | AX54: HDFC BC – Micro ATM Cash Withdrawal Service | Devmobile Stores | AY54: HDFC BC – Micro ATM Cash Withdrawal (HDFC BC – Micro ATM नकद निकासी) at Devmobile Stores and Common Service Center & Aadhaar Centre. Check required documents, charges and process before you visit. | AZ54: HDFC BC – Micro ATM नकद निकासी, HDFC बैंक BC पॉइंट, सेवा | BA54: HDFC BC – Micro ATM Cash Withdrawal, HDFC Bank BC Point, Devmobile Stores | BC54: =IFERROR(INDEX(CATEGORY_MASTER!$C$4:$C$30,MATCH(B54,CATEGORY_MASTER!$A$4:$A$30,0)),"") -> 🏦 | BD54: ="/services/"&AO54 -> /services/hdfc-bc-micro-atm-cash-withdrawal | BE54: =IF(AND(AH54="Yes",AG54="Active",I54<>"Not Available"),"LIVE","HIDDEN") -> HIDDEN | BF54: In-person assistance at the shop • Help checking your documents • Receipt / acknowledgement where applicable | BG54: Check Documents | BH54: =B54&"|"&COUNTIF($B$4:B54,B54) -> HDFC Bank BC Point|9 | BI54: =IF(AND(AI54="Yes",BE54="LIVE"),COUNTIFS($AI$4:AI54,"Yes",$BE$4:BE54,"LIVE"),"") | BJ54: =IF(AND(AJ54="Yes",BE54="LIVE"),COUNTIFS($AJ$4:AJ54,"Yes",$BE$4:BE54,"LIVE"),"") | BK54: =IF(AND(AK54="Yes",BE54="LIVE"),COUNTIFS($AK$4:AK54,"Yes",$BE$4:BE54,"LIVE"),"") | BL54: =IF(I54="To Verify",COUNTIF($I$4:I54,"To Verify"),"")
A55: HDF-010 | B55: HDFC Bank BC Point | C55: Banking Services | D55: Micro ATM | E55: HDFC BC – Micro ATM Balance Enquiry | F55: HDFC BC – Micro ATM बैलेंस पूछताछ | G55: HDFC BC – Micro ATM Balance Enquiry at our HDFC Bank BC Point. | H55: HDFC BC – Micro ATM Balance Enquiry using the Micro ATM device. | I55: Authorization Required | J55: =IFERROR(INDEX(AVAILABILITY_MASTER!$C$4:$C$10,MATCH(I55,AVAILABILITY_MASTER!$A$4:$A$10,0)),"To Be Confirmed") -> Please Confirm at Shop | K55: Yes | L55: To Verify | M55: =IFERROR(INDEX(SERVICE_DOCUMENTS!$S$4:$S$1000,MATCH(A55,SERVICE_DOCUMENTS!$A$4:$A$1000,0))&"","") -> ✓ Debit Card | N55: =IFERROR(INDEX(SERVICE_DOCUMENTS!$T$4:$T$1000,MATCH(A55,SERVICE_DOCUMENTS!$A$4:$A$1000,0))&"","") | O55: Debit card holders. | P55: Step 1 → Bring your debit card. Step 2 → Operator starts the Micro ATM transaction. Step 3 → Swipe / insert card and enter your PIN yourself. Step 4 → Collect cash / receipt. | Q55: 5–10 Minutes | R55: To Verify | S55: To Verify | T55: =IF(AND(OR(ISNUMBER(R55),R55="N/A"),OR(ISNUMBER(S55),S55="N/A"),OR(ISNUMBER(R55),ISNUMBER(S55))),N(R55)+N(S55),"To Verify") -> To Verify | U55: To Verify | V55: No | W55: Depends on Service | X55: Offline | Y55: No | AA55: Yes | AB55: Yes | AC55: To Verify | AD55: To Verify | AE55: No | AF55: No | AG55: To Verify | AH55: No | AI55: No | AJ55: No | AK55: No | AL55: HDFC Bank BC Point | AM55: Micro ATM | AN55: =BA55&", "&AZ55 -> HDFC BC – Micro ATM Balance Enquiry, HDFC Bank BC Point, Devmobile Stores, HDFC BC – Micro ATM बैलेंस पूछताछ, HDFC बैंक BC पॉइंट, सेवा | AO55: hdfc-bc-micro-atm-balance-enquiry | AP55: 🏧 | AQ55: 100 | AR55: Q1: Who enters the PIN? A1: You should enter the PIN yourself on the device. | AS55: Depends on your HDFC Bank BC agreement and activated services. Confirm with the shop before visiting. | AT55: Fees, documents and processing time are subject to change as per government / bank / portal rules. Final charges are confirmed at the shop before the service starts. | AV55: To Verify | AX55: HDFC BC – Micro ATM Balance Enquiry Service | Devmobile Stores | AY55: HDFC BC – Micro ATM Balance Enquiry (HDFC BC – Micro ATM बैलेंस पूछताछ) at Devmobile Stores and Common Service Center & Aadhaar Centre. Check required documents, charges and process before you visit. | AZ55: HDFC BC – Micro ATM बैलेंस पूछताछ, HDFC बैंक BC पॉइंट, सेवा | BA55: HDFC BC – Micro ATM Balance Enquiry, HDFC Bank BC Point, Devmobile Stores | BC55: =IFERROR(INDEX(CATEGORY_MASTER!$C$4:$C$30,MATCH(B55,CATEGORY_MASTER!$A$4:$A$30,0)),"") -> 🏦 | BD55: ="/services/"&AO55 -> /services/hdfc-bc-micro-atm-balance-enquiry | BE55: =IF(AND(AH55="Yes",AG55="Active",I55<>"Not Available"),"LIVE","HIDDEN") -> HIDDEN | BF55: In-person assistance at the shop • Help checking your documents • Receipt / acknowledgement where applicable | BG55: Check Documents | BH55: =B55&"|"&COUNTIF($B$4:B55,B55) -> HDFC Bank BC Point|10 | BI55: =IF(AND(AI55="Yes",BE55="LIVE"),COUNTIFS($AI$4:AI55,"Yes",$BE$4:BE55,"LIVE"),"") | BJ55: =IF(AND(AJ55="Yes",BE55="LIVE"),COUNTIFS($AJ$4:AJ55,"Yes",$BE$4:BE55,"LIVE"),"") | BK55: =IF(AND(AK55="Yes",BE55="LIVE"),COUNTIFS($AK$4:AK55,"Yes",$BE$4:BE55,"LIVE"),"") | BL55: =IF(I55="To Verify",COUNTIF($I$4:I55,"To Verify"),"")
A56: HDF-011 | B56: HDFC Bank BC Point | C56: Banking Services | D56: Micro ATM | E56: HDFC BC – Micro ATM Mini Statement | F56: HDFC BC – Micro ATM मिनी स्टेटमेंट | G56: HDFC BC – Micro ATM Mini Statement at our HDFC Bank BC Point. | H56: HDFC BC – Micro ATM Mini Statement using the Micro ATM device. | I56: Authorization Required | J56: =IFERROR(INDEX(AVAILABILITY_MASTER!$C$4:$C$10,MATCH(I56,AVAILABILITY_MASTER!$A$4:$A$10,0)),"To Be Confirmed") -> Please Confirm at Shop | K56: Yes | L56: To Verify | M56: =IFERROR(INDEX(SERVICE_DOCUMENTS!$S$4:$S$1000,MATCH(A56,SERVICE_DOCUMENTS!$A$4:$A$1000,0))&"","") -> ✓ Debit Card | N56: =IFERROR(INDEX(SERVICE_DOCUMENTS!$T$4:$T$1000,MATCH(A56,SERVICE_DOCUMENTS!$A$4:$A$1000,0))&"","") | O56: Debit card holders. | P56: Step 1 → Bring your debit card. Step 2 → Operator starts the Micro ATM transaction. Step 3 → Swipe / insert card and enter your PIN yourself. Step 4 → Collect cash / receipt. | Q56: 5–10 Minutes | R56: To Verify | S56: To Verify | T56: =IF(AND(OR(ISNUMBER(R56),R56="N/A"),OR(ISNUMBER(S56),S56="N/A"),OR(ISNUMBER(R56),ISNUMBER(S56))),N(R56)+N(S56),"To Verify") -> To Verify | U56: To Verify | V56: No | W56: Depends on Service | X56: Offline | Y56: No | AA56: Yes | AB56: Yes | AC56: To Verify | AD56: To Verify | AE56: No | AF56: No | AG56: To Verify | AH56: No | AI56: No | AJ56: No | AK56: No | AL56: HDFC Bank BC Point | AM56: Micro ATM | AN56: =BA56&", "&AZ56 -> HDFC BC – Micro ATM Mini Statement, HDFC Bank BC Point, Devmobile Stores, HDFC BC – Micro ATM मिनी स्टेटमेंट, HDFC बैंक BC पॉइंट, सेवा | AO56: hdfc-bc-micro-atm-mini-statement | AP56: 🏧 | AQ56: 110 | AR56: Q1: Who enters the PIN? A1: You should enter the PIN yourself on the device. | AS56: Depends on your HDFC Bank BC agreement and activated services. Confirm with the shop before visiting. | AT56: Fees, documents and processing time are subject to change as per government / bank / portal rules. Final charges are confirmed at the shop before the service starts. | AV56: To Verify | AX56: HDFC BC – Micro ATM Mini Statement Service | Devmobile Stores | AY56: HDFC BC – Micro ATM Mini Statement (HDFC BC – Micro ATM मिनी स्टेटमेंट) at Devmobile Stores and Common Service Center & Aadhaar Centre. Check required documents, charges and process before you visit. | AZ56: HDFC BC – Micro ATM मिनी स्टेटमेंट, HDFC बैंक BC पॉइंट, सेवा | BA56: HDFC BC – Micro ATM Mini Statement, HDFC Bank BC Point, Devmobile Stores | BC56: =IFERROR(INDEX(CATEGORY_MASTER!$C$4:$C$30,MATCH(B56,CATEGORY_MASTER!$A$4:$A$30,0)),"") -> 🏦 | BD56: ="/services/"&AO56 -> /services/hdfc-bc-micro-atm-mini-statement | BE56: =IF(AND(AH56="Yes",AG56="Active",I56<>"Not Available"),"LIVE","HIDDEN") -> HIDDEN | BF56: In-person assistance at the shop • Help checking your documents • Receipt / acknowledgement where applicable | BG56: Check Documents | BH56: =B56&"|"&COUNTIF($B$4:B56,B56) -> HDFC Bank BC Point|11 | BI56: =IF(AND(AI56="Yes",BE56="LIVE"),COUNTIFS($AI$4:AI56,"Yes",$BE$4:BE56,"LIVE"),"") | BJ56: =IF(AND(AJ56="Yes",BE56="LIVE"),COUNTIFS($AJ$4:AJ56,"Yes",$BE$4:BE56,"LIVE"),"") | BK56: =IF(AND(AK56="Yes",BE56="LIVE"),COUNTIFS($AK$4:AK56,"Yes",$BE$4:BE56,"LIVE"),"") | BL56: =IF(I56="To Verify",COUNTIF($I$4:I56,"To Verify"),"")
A57: HDF-012 | B57: HDFC Bank BC Point | C57: Banking Services | D57: Money Transfer | E57: HDFC BC – Money Transfer (Domestic) | F57: HDFC BC – मनी ट्रांसफर (घरेलू) | G57: HDFC BC – Money Transfer (Domestic) at our HDFC Bank BC Point. | H57: Send money to a bank account by paying cash at our BC Point. | I57: Authorization Required | J57: =IFERROR(INDEX(AVAILABILITY_MASTER!$C$4:$C$10,MATCH(I57,AVAILABILITY_MASTER!$A$4:$A$10,0)),"To Be Confirmed") -> Please Confirm at Shop | K57: Yes | L57: To Verify | M57: =IFERROR(INDEX(SERVICE_DOCUMENTS!$S$4:$S$1000,MATCH(A57,SERVICE_DOCUMENTS!$A$4:$A$1000,0))&"","") -> ✓ Beneficiary Account Details ✓ Cash Amount ✓ Active Mobile Number | N57: =IFERROR(INDEX(SERVICE_DOCUMENTS!$T$4:$T$1000,MATCH(A57,SERVICE_DOCUMENTS!$A$4:$A$1000,0))&"","") -> • Identity Proof (To Verify) | O57: Individuals sending domestic money (limits per bank rules). | P57: Step 1 → Give the receiver's account number / IFSC and the amount. Step 2 → Operator registers / verifies the sender and receiver on the BC system. Step 3 → Pay the cash and the transfer charge. Step 4 → Transfer is done; collect the receipt / reference. | Q57: Same Day | R57: To Verify | S57: To Verify | T57: =IF(AND(OR(ISNUMBER(R57),R57="N/A"),OR(ISNUMBER(S57),S57="N/A"),OR(ISNUMBER(R57),ISNUMBER(S57))),N(R57)+N(S57),"To Verify") -> To Verify | U57: To Verify | V57: No | W57: Depends on Service | X57: Offline | Y57: No | AA57: Yes | AB57: Yes | AC57: To Verify | AD57: To Verify | AE57: No | AF57: No | AG57: To Verify | AH57: No | AI57: No | AJ57: No | AK57: No | AL57: HDFC Bank BC Point | AM57: Money Transfer | AN57: =BA57&", "&AZ57 -> HDFC BC – Money Transfer (Domestic), HDFC Bank BC Point, Devmobile Stores, HDFC BC – मनी ट्रांसफर (घरेलू), HDFC बैंक BC पॉइंट, सेवा | AO57: hdfc-bc-money-transfer-domestic | AP57: 💸 | AQ57: 120 | AR57: Q1: Where can I check the current charges? A1: Charges are confirmed at the shop and may change as per government / bank rules. | AS57: Depends on your HDFC Bank BC agreement and activated services. Confirm with the shop before visiting. | AT57: Fees, documents and processing time are subject to change as per government / bank / portal rules. Final charges are confirmed at the shop before the service starts. | AV57: To Verify | AW57: Limits and charges as per bank BC policy | AX57: HDFC BC – Money Transfer (Domestic) Service | Devmobile Stores | AY57: HDFC BC – Money Transfer (Domestic) (HDFC BC – मनी ट्रांसफर (घरेलू)) at Devmobile Stores and Common Service Center & Aadhaar Centre. Check required documents, charges and process before you visit. | AZ57: HDFC BC – मनी ट्रांसफर (घरेलू), HDFC बैंक BC पॉइंट, सेवा | BA57: HDFC BC – Money Transfer (Domestic), HDFC Bank BC Point, Devmobile Stores | BC57: =IFERROR(INDEX(CATEGORY_MASTER!$C$4:$C$30,MATCH(B57,CATEGORY_MASTER!$A$4:$A$30,0)),"") -> 🏦 | BD57: ="/services/"&AO57 -> /services/hdfc-bc-money-transfer-domestic | BE57: =IF(AND(AH57="Yes",AG57="Active",I57<>"Not Available"),"LIVE","HIDDEN") -> HIDDEN | BF57: In-person assistance at the shop • Help checking your documents • Receipt / acknowledgement where applicable | BG57: Check Documents | BH57: =B57&"|"&COUNTIF($B$4:B57,B57) -> HDFC Bank BC Point|12 | BI57: =IF(AND(AI57="Yes",BE57="LIVE"),COUNTIFS($AI$4:AI57,"Yes",$BE$4:BE57,"LIVE"),"") | BJ57: =IF(AND(AJ57="Yes",BE57="LIVE"),COUNTIFS($AJ$4:AJ57,"Yes",$BE$4:BE57,"LIVE"),"") | BK57: =IF(AND(AK57="Yes",BE57="LIVE"),COUNTIFS($AK$4:AK57,"Yes",$BE$4:BE57,"LIVE"),"") | BL57: =IF(I57="To Verify",COUNTIF($I$4:I57,"To Verify"),"")
A58: HDF-013 | B58: HDFC Bank BC Point | C58: Banking Services | D58: Account & KYC Services | E58: HDFC BC – New Savings Account Opening Assistance | F58: HDFC BC – नया बचत खाता खुलवाने में सहायता | G58: HDFC BC – New Savings Account Opening Assistance at our HDFC Bank BC Point. | H58: Assistance to open a new HDFC Bank account. | I58: To Verify | J58: =IFERROR(INDEX(AVAILABILITY_MASTER!$C$4:$C$10,MATCH(I58,AVAILABILITY_MASTER!$A$4:$A$10,0)),"To Be Confirmed") -> To Be Confirmed | K58: Depends | L58: To Verify | M58: =IFERROR(INDEX(SERVICE_DOCUMENTS!$S$4:$S$1000,MATCH(A58,SERVICE_DOCUMENTS!$A$4:$A$1000,0))&"","") -> ✓ Aadhaar Card ✓ Passport Photo ✓ Active Mobile Number | N58: =IFERROR(INDEX(SERVICE_DOCUMENTS!$T$4:$T$1000,MATCH(A58,SERVICE_DOCUMENTS!$A$4:$A$1000,0))&"","") -> • PAN Card (To Verify) • Nominee Details (If Applicable) | O58: Individuals eligible for the bank's account type. | P58: Step 1 → Bring Aadhaar, mobile number and photo. Step 2 → Operator starts the account opening form on the BC system. Step 3 → eKYC / biometric verification is completed. Step 4 → Form is submitted and the account details are shared. | Q58: Depends on Department | R58: To Verify | S58: To Verify | T58: =IF(AND(OR(ISNUMBER(R58),R58="N/A"),OR(ISNUMBER(S58),S58="N/A"),OR(ISNUMBER(R58),ISNUMBER(S58))),N(R58)+N(S58),"To Verify") -> To Verify | U58: To Verify | V58: No | W58: Depends on Service | X58: Offline | Y58: No | AA58: Yes | AB58: Yes | AC58: To Verify | AD58: To Verify | AE58: No | AF58: No | AG58: To Verify | AH58: No | AI58: No | AJ58: No | AK58: No | AL58: HDFC Bank BC Point | AM58: Account & KYC Services | AN58: =BA58&", "&AZ58 -> HDFC BC – New Savings Account Opening Assistance, HDFC Bank BC Point, Devmobile Stores, HDFC BC – नया बचत खाता खुलवाने में सहायता, HDFC बैंक BC पॉइंट, सेवा | AO58: hdfc-bc-new-savings-account-opening-assistance | AP58: 🗂️ | AQ58: 130 | AR58: Q1: Where can I check the current charges? A1: Charges are confirmed at the shop and may change as per government / bank rules. | AS58: Depends on your HDFC Bank BC agreement and activated services. Confirm with the shop before visiting. | AT58: Fees, documents and processing time are subject to change as per government / bank / portal rules. Final charges are confirmed at the shop before the service starts. | AV58: To Verify | AX58: HDFC BC – New Savings Account Opening Assistance Service | Devmobile Stores | AY58: HDFC BC – New Savings Account Opening Assistance (HDFC BC – नया बचत खाता खुलवाने में सहायता) at Devmobile Stores and Common Service Center & Aadhaar Centre. Check required documents, charges and process before you visit. | AZ58: HDFC BC – नया बचत खाता खुलवाने में सहायता, HDFC बैंक BC पॉइंट, सेवा | BA58: HDFC BC – New Savings Account Opening Assistance, HDFC Bank BC Point, Devmobile Stores | BC58: =IFERROR(INDEX(CATEGORY_MASTER!$C$4:$C$30,MATCH(B58,CATEGORY_MASTER!$A$4:$A$30,0)),"") -> 🏦 | BD58: ="/services/"&AO58 -> /services/hdfc-bc-new-savings-account-opening-assistance | BE58: =IF(AND(AH58="Yes",AG58="Active",I58<>"Not Available"),"LIVE","HIDDEN") -> HIDDEN | BF58: In-person assistance at the shop • Help checking your documents • Receipt / acknowledgement where applicable | BG58: Check Documents | BH58: =B58&"|"&COUNTIF($B$4:B58,B58) -> HDFC Bank BC Point|13 | BI58: =IF(AND(AI58="Yes",BE58="LIVE"),COUNTIFS($AI$4:AI58,"Yes",$BE$4:BE58,"LIVE"),"") | BJ58: =IF(AND(AJ58="Yes",BE58="LIVE"),COUNTIFS($AJ$4:AJ58,"Yes",$BE$4:BE58,"LIVE"),"") | BK58: =IF(AND(AK58="Yes",BE58="LIVE"),COUNTIFS($AK$4:AK58,"Yes",$BE$4:BE58,"LIVE"),"") | BL58: =IF(I58="To Verify",COUNTIF($I$4:I58,"To Verify"),"") -> 5
